{"detailBundle":"de-camper","street":"De Camper","houses":[{"id":"c0269116-a61f-5dc9-830b-cc93ee661eeb","address":"De Camper 1","postcode":"1749BX","city":"Warmenhuizen","lat":52.71857732220558,"lon":4.731141168718189,"nearestContainerId":"WH20","nearestContainerAddress":"Oudewal 24","nearestContainerAccuracy":"handmatig bepaald (zeer hoog, onzekerheid -1 m)","nearestContainers":[{"id":"WH20","address":"Oudewal 24","accuracy":"handmatig bepaald (zeer hoog, onzekerheid -1 m)","type":"rest","status":"new","straightDistance":127.3,"walkingDistance":140.1,"walkingDuration":112,"coverageStatus":"between_125_150","routeCacheKey":"route-v1|https://routing.openstreetmap.de/routed-foot|foot|c0269116-a61f-5dc9-830b-cc93ee661eeb|52.718577|4.731141|WH20|52.719722|4.731197","routeGeometry":[[52.718724,4.731096],[52.719612,4.730873],[52.719637,4.731302],[52.719721,4.731304]],"routeError":null},{"id":"WH21","address":"Oudewal 57","accuracy":"handmatig bepaald (zeer hoog, onzekerheid -1 m)","type":"rest","status":"new","straightDistance":335.8,"walkingDistance":422.8,"walkingDuration":338.3,"coverageStatus":"over_275","routeCacheKey":"route-v1|https://routing.openstreetmap.de/routed-foot|foot|c0269116-a61f-5dc9-830b-cc93ee661eeb|52.718577|4.731141|WH21|52.719220|4.726270","routeGeometry":[[52.718724,4.731096],[52.719612,4.730873],[52.719556,4.729219],[52.719435,4.728108],[52.719263,4.726936],[52.719261,4.726341],[52.719204,4.726347],[52.719198,4.726275]],"routeError":null},{"id":"WH19","address":"Zwartepad 32","accuracy":"handmatig bepaald (zeer hoog, onzekerheid -1 m)","type":"rest","status":"new","straightDistance":320.8,"walkingDistance":454.5,"walkingDuration":363.7,"coverageStatus":"over_275","routeCacheKey":"route-v1|https://routing.openstreetmap.de/routed-foot|foot|c0269116-a61f-5dc9-830b-cc93ee661eeb|52.718577|4.731141|WH19|52.720963|4.733820","routeGeometry":[[52.718724,4.731096],[52.719612,4.730873],[52.719637,4.731302],[52.719984,4.731311],[52.720026,4.732075],[52.720761,4.732091],[52.720754,4.732581],[52.720894,4.73259],[52.720909,4.732841],[52.721014,4.732848],[52.721005,4.733877],[52.720964,4.733879]],"routeError":null}],"straightDistance":127.3,"walkingDistance":140.1,"walkingDuration":112,"coverageStatus":"between_125_150","analysisError":null},{"id":"044878ef-89a2-5c6b-88c7-e15fd1dd208a","address":"De Camper 2","postcode":"1749BX","city":"Warmenhuizen","lat":52.71927978846614,"lon":4.730819550053156,"nearestContainerId":"WH20","nearestContainerAddress":"Oudewal 24","nearestContainerAccuracy":"handmatig bepaald (zeer hoog, onzekerheid -1 m)","nearestContainers":[{"id":"WH20","address":"Oudewal 24","accuracy":"handmatig bepaald (zeer hoog, onzekerheid -1 m)","type":"rest","status":"new","straightDistance":55.4,"walkingDistance":74.3,"walkingDuration":59.4,"coverageStatus":"within_100","routeCacheKey":"route-v1|https://routing.openstreetmap.de/routed-foot|foot|044878ef-89a2-5c6b-88c7-e15fd1dd208a|52.719280|4.730820|WH20|52.719722|4.731197","routeGeometry":[[52.719295,4.730962],[52.719612,4.730873],[52.719637,4.731302],[52.719721,4.731304]],"routeError":null},{"id":"WH21","address":"Oudewal 57","accuracy":"handmatig bepaald (zeer hoog, onzekerheid -1 m)","type":"rest","status":"new","straightDistance":306.5,"walkingDistance":356.9,"walkingDuration":285.7,"coverageStatus":"over_275","routeCacheKey":"route-v1|https://routing.openstreetmap.de/routed-foot|foot|044878ef-89a2-5c6b-88c7-e15fd1dd208a|52.719280|4.730820|WH21|52.719220|4.726270","routeGeometry":[[52.719295,4.730962],[52.719612,4.730873],[52.719556,4.729219],[52.719435,4.728108],[52.719263,4.726936],[52.719261,4.726341],[52.719204,4.726347],[52.719198,4.726275]],"routeError":null},{"id":"WH19","address":"Zwartepad 32","accuracy":"handmatig bepaald (zeer hoog, onzekerheid -1 m)","type":"rest","status":"new","straightDistance":275.4,"walkingDistance":388.7,"walkingDuration":311.1,"coverageStatus":"over_275","routeCacheKey":"route-v1|https://routing.openstreetmap.de/routed-foot|foot|044878ef-89a2-5c6b-88c7-e15fd1dd208a|52.719280|4.730820|WH19|52.720963|4.733820","routeGeometry":[[52.719295,4.730962],[52.719612,4.730873],[52.719637,4.731302],[52.719984,4.731311],[52.720026,4.732075],[52.720761,4.732091],[52.720754,4.732581],[52.720894,4.73259],[52.720909,4.732841],[52.721014,4.732848],[52.721005,4.733877],[52.720964,4.733879]],"routeError":null}],"straightDistance":55.4,"walkingDistance":74.3,"walkingDuration":59.4,"coverageStatus":"within_100","analysisError":null},{"id":"49c89b3c-18fa-5fdb-a167-400997b79868","address":"De Camper 3","postcode":"1749BX","city":"Warmenhuizen","lat":52.71854990708594,"lon":4.7306251991221195,"nearestContainerId":"WH20","nearestContainerAddress":"Oudewal 24","nearestContainerAccuracy":"handmatig bepaald (zeer hoog, onzekerheid -1 m)","nearestContainers":[{"id":"WH20","address":"Oudewal 24","accuracy":"handmatig bepaald (zeer hoog, onzekerheid -1 m)","type":"rest","status":"new","straightDistance":135.9,"walkingDistance":174.9,"walkingDuration":139.9,"coverageStatus":"between_150_275","routeCacheKey":"route-v1|https://routing.openstreetmap.de/routed-foot|foot|49c89b3c-18fa-5fdb-a167-400997b79868|52.718550|4.730625|WH20|52.719722|4.731197","routeGeometry":[[52.718668,4.730589],[52.718727,4.731121],[52.719612,4.730873],[52.719637,4.731302],[52.719721,4.731304]],"routeError":null},{"id":"WH21","address":"Oudewal 57","accuracy":"handmatig bepaald (zeer hoog, onzekerheid -1 m)","type":"rest","status":"new","straightDistance":302.7,"walkingDistance":457.6,"walkingDuration":366.2,"coverageStatus":"over_275","routeCacheKey":"route-v1|https://routing.openstreetmap.de/routed-foot|foot|49c89b3c-18fa-5fdb-a167-400997b79868|52.718550|4.730625|WH21|52.719220|4.726270","routeGeometry":[[52.718668,4.730589],[52.718727,4.731121],[52.719612,4.730873],[52.719556,4.729219],[52.719435,4.728108],[52.719263,4.726936],[52.719261,4.726341],[52.719204,4.726347],[52.719198,4.726275]],"routeError":null},{"id":"WH19","address":"Zwartepad 32","accuracy":"handmatig bepaald (zeer hoog, onzekerheid -1 m)","type":"rest","status":"new","straightDistance":343.9,"walkingDistance":489.3,"walkingDuration":391.6,"coverageStatus":"over_275","routeCacheKey":"route-v1|https://routing.openstreetmap.de/routed-foot|foot|49c89b3c-18fa-5fdb-a167-400997b79868|52.718550|4.730625|WH19|52.720963|4.733820","routeGeometry":[[52.718668,4.730589],[52.718727,4.731121],[52.719612,4.730873],[52.719637,4.731302],[52.719984,4.731311],[52.720026,4.732075],[52.720761,4.732091],[52.720754,4.732581],[52.720894,4.73259],[52.720909,4.732841],[52.721014,4.732848],[52.721005,4.733877],[52.720964,4.733879]],"routeError":null}],"straightDistance":135.9,"walkingDistance":174.9,"walkingDuration":139.9,"coverageStatus":"between_150_275","analysisError":null},{"id":"45d27e6b-d6cb-5714-8af1-b049052ce452","address":"De Camper 4","postcode":"1749BX","city":"Warmenhuizen","lat":52.719177689129886,"lon":4.730883712048222,"nearestContainerId":"WH20","nearestContainerAddress":"Oudewal 24","nearestContainerAccuracy":"handmatig bepaald (zeer hoog, onzekerheid -1 m)","nearestContainers":[{"id":"WH20","address":"Oudewal 24","accuracy":"handmatig bepaald (zeer hoog, onzekerheid -1 m)","type":"rest","status":"new","straightDistance":64.1,"walkingDistance":86.2,"walkingDuration":68.9,"coverageStatus":"within_100","routeCacheKey":"route-v1|https://routing.openstreetmap.de/routed-foot|foot|45d27e6b-d6cb-5714-8af1-b049052ce452|52.719178|4.730884|WH20|52.719722|4.731197","routeGeometry":[[52.719189,4.730992],[52.719612,4.730873],[52.719637,4.731302],[52.719721,4.731304]],"routeError":null},{"id":"WH21","address":"Oudewal 57","accuracy":"handmatig bepaald (zeer hoog, onzekerheid -1 m)","type":"rest","status":"new","straightDistance":310.8,"walkingDistance":368.9,"walkingDuration":295.2,"coverageStatus":"over_275","routeCacheKey":"route-v1|https://routing.openstreetmap.de/routed-foot|foot|45d27e6b-d6cb-5714-8af1-b049052ce452|52.719178|4.730884|WH21|52.719220|4.726270","routeGeometry":[[52.719189,4.730992],[52.719612,4.730873],[52.719556,4.729219],[52.719435,4.728108],[52.719263,4.726936],[52.719261,4.726341],[52.719204,4.726347],[52.719198,4.726275]],"routeError":null},{"id":"WH19","address":"Zwartepad 32","accuracy":"handmatig bepaald (zeer hoog, onzekerheid -1 m)","type":"rest","status":"new","straightDistance":280.2,"walkingDistance":400.7,"walkingDuration":320.6,"coverageStatus":"over_275","routeCacheKey":"route-v1|https://routing.openstreetmap.de/routed-foot|foot|45d27e6b-d6cb-5714-8af1-b049052ce452|52.719178|4.730884|WH19|52.720963|4.733820","routeGeometry":[[52.719189,4.730992],[52.719612,4.730873],[52.719637,4.731302],[52.719984,4.731311],[52.720026,4.732075],[52.720761,4.732091],[52.720754,4.732581],[52.720894,4.73259],[52.720909,4.732841],[52.721014,4.732848],[52.721005,4.733877],[52.720964,4.733879]],"routeError":null}],"straightDistance":64.1,"walkingDistance":86.2,"walkingDuration":68.9,"coverageStatus":"within_100","analysisError":null},{"id":"edb43716-ad25-5278-ac53-942ef76f4459","address":"De Camper 5","postcode":"1749BX","city":"Warmenhuizen","lat":52.71851596707558,"lon":4.730293619887933,"nearestContainerId":"WH20","nearestContainerAddress":"Oudewal 24","nearestContainerAccuracy":"handmatig bepaald (zeer hoog, onzekerheid -1 m)","nearestContainers":[{"id":"WH20","address":"Oudewal 24","accuracy":"handmatig bepaald (zeer hoog, onzekerheid -1 m)","type":"rest","status":"new","straightDistance":147.3,"walkingDistance":197.6,"walkingDuration":158,"coverageStatus":"between_150_275","routeCacheKey":"route-v1|https://routing.openstreetmap.de/routed-foot|foot|edb43716-ad25-5278-ac53-942ef76f4459|52.718516|4.730294|WH20|52.719722|4.731197","routeGeometry":[[52.718631,4.730259],[52.718727,4.731121],[52.719612,4.730873],[52.719637,4.731302],[52.719721,4.731304]],"routeError":null},{"id":"WH21","address":"Oudewal 57","accuracy":"handmatig bepaald (zeer hoog, onzekerheid -1 m)","type":"rest","status":"new","straightDistance":282.1,"walkingDistance":480.3,"walkingDuration":384.3,"coverageStatus":"over_275","routeCacheKey":"route-v1|https://routing.openstreetmap.de/routed-foot|foot|edb43716-ad25-5278-ac53-942ef76f4459|52.718516|4.730294|WH21|52.719220|4.726270","routeGeometry":[[52.718631,4.730259],[52.718727,4.731121],[52.719612,4.730873],[52.719556,4.729219],[52.719435,4.728108],[52.719263,4.726936],[52.719261,4.726341],[52.719204,4.726347],[52.719198,4.726275]],"routeError":null},{"id":"WH19","address":"Zwartepad 32","accuracy":"handmatig bepaald (zeer hoog, onzekerheid -1 m)","type":"rest","status":"new","straightDistance":361.2,"walkingDistance":512,"walkingDuration":409.7,"coverageStatus":"over_275","routeCacheKey":"route-v1|https://routing.openstreetmap.de/routed-foot|foot|edb43716-ad25-5278-ac53-942ef76f4459|52.718516|4.730294|WH19|52.720963|4.733820","routeGeometry":[[52.718631,4.730259],[52.718727,4.731121],[52.719612,4.730873],[52.719637,4.731302],[52.719984,4.731311],[52.720026,4.732075],[52.720761,4.732091],[52.720754,4.732581],[52.720894,4.73259],[52.720909,4.732841],[52.721014,4.732848],[52.721005,4.733877],[52.720964,4.733879]],"routeError":null}],"straightDistance":147.3,"walkingDistance":197.6,"walkingDuration":158,"coverageStatus":"between_150_275","analysisError":null},{"id":"9398e681-2a5e-5886-a6e3-c07592f8cf8a","address":"De Camper 5A","postcode":"1749BX","city":"Warmenhuizen","lat":52.718394899015024,"lon":4.730465810950387,"nearestContainerId":"WH20","nearestContainerAddress":"Oudewal 24","nearestContainerAccuracy":"handmatig bepaald (zeer hoog, onzekerheid -1 m)","nearestContainers":[{"id":"WH20","address":"Oudewal 24","accuracy":"handmatig bepaald (zeer hoog, onzekerheid -1 m)","type":"rest","status":"new","straightDistance":155.6,"walkingDistance":188.6,"walkingDuration":150.8,"coverageStatus":"between_150_275","routeCacheKey":"route-v1|https://routing.openstreetmap.de/routed-foot|foot|9398e681-2a5e-5886-a6e3-c07592f8cf8a|52.718395|4.730466|WH20|52.719722|4.731197","routeGeometry":[[52.718646,4.73039],[52.718727,4.731121],[52.719612,4.730873],[52.719637,4.731302],[52.719721,4.731304]],"routeError":null},{"id":"WH21","address":"Oudewal 57","accuracy":"handmatig bepaald (zeer hoog, onzekerheid -1 m)","type":"rest","status":"new","straightDistance":297.1,"walkingDistance":471.3,"walkingDuration":377.1,"coverageStatus":"over_275","routeCacheKey":"route-v1|https://routing.openstreetmap.de/routed-foot|foot|9398e681-2a5e-5886-a6e3-c07592f8cf8a|52.718395|4.730466|WH21|52.719220|4.726270","routeGeometry":[[52.718646,4.73039],[52.718727,4.731121],[52.719612,4.730873],[52.719556,4.729219],[52.719435,4.728108],[52.719263,4.726936],[52.719261,4.726341],[52.719204,4.726347],[52.719198,4.726275]],"routeError":null},{"id":"WH19","address":"Zwartepad 32","accuracy":"handmatig bepaald (zeer hoog, onzekerheid -1 m)","type":"rest","status":"new","straightDistance":364.1,"walkingDistance":503,"walkingDuration":402.5,"coverageStatus":"over_275","routeCacheKey":"route-v1|https://routing.openstreetmap.de/routed-foot|foot|9398e681-2a5e-5886-a6e3-c07592f8cf8a|52.718395|4.730466|WH19|52.720963|4.733820","routeGeometry":[[52.718646,4.73039],[52.718727,4.731121],[52.719612,4.730873],[52.719637,4.731302],[52.719984,4.731311],[52.720026,4.732075],[52.720761,4.732091],[52.720754,4.732581],[52.720894,4.73259],[52.720909,4.732841],[52.721014,4.732848],[52.721005,4.733877],[52.720964,4.733879]],"routeError":null}],"straightDistance":155.6,"walkingDistance":188.6,"walkingDuration":150.8,"coverageStatus":"between_150_275","analysisError":null},{"id":"d24c4d7e-a29a-5d51-8ccb-c37a18e8b3d0","address":"De Camper 7","postcode":"1749BX","city":"Warmenhuizen","lat":52.71844224309951,"lon":4.729858384352043,"nearestContainerId":"WH20","nearestContainerAddress":"Oudewal 24","nearestContainerAccuracy":"handmatig bepaald (zeer hoog, onzekerheid -1 m)","nearestContainers":[{"id":"WH20","address":"Oudewal 24","accuracy":"handmatig bepaald (zeer hoog, onzekerheid -1 m)","type":"rest","status":"new","straightDistance":168.5,"walkingDistance":228,"walkingDuration":182.4,"coverageStatus":"between_150_275","routeCacheKey":"route-v1|https://routing.openstreetmap.de/routed-foot|foot|d24c4d7e-a29a-5d51-8ccb-c37a18e8b3d0|52.718442|4.729858|WH20|52.719722|4.731197","routeGeometry":[[52.718582,4.729816],[52.718727,4.731121],[52.719612,4.730873],[52.719637,4.731302],[52.719721,4.731304]],"routeError":null},{"id":"WH21","address":"Oudewal 57","accuracy":"handmatig bepaald (zeer hoog, onzekerheid -1 m)","type":"rest","status":"new","straightDistance":256.7,"walkingDistance":510.7,"walkingDuration":408.7,"coverageStatus":"over_275","routeCacheKey":"route-v1|https://routing.openstreetmap.de/routed-foot|foot|d24c4d7e-a29a-5d51-8ccb-c37a18e8b3d0|52.718442|4.729858|WH21|52.719220|4.726270","routeGeometry":[[52.718582,4.729816],[52.718727,4.731121],[52.719612,4.730873],[52.719556,4.729219],[52.719435,4.728108],[52.719263,4.726936],[52.719261,4.726341],[52.719204,4.726347],[52.719198,4.726275]],"routeError":null},{"id":"WH19","address":"Zwartepad 32","accuracy":"handmatig bepaald (zeer hoog, onzekerheid -1 m)","type":"rest","status":"new","straightDistance":387,"walkingDistance":542.4,"walkingDuration":434.1,"coverageStatus":"over_275","routeCacheKey":"route-v1|https://routing.openstreetmap.de/routed-foot|foot|d24c4d7e-a29a-5d51-8ccb-c37a18e8b3d0|52.718442|4.729858|WH19|52.720963|4.733820","routeGeometry":[[52.718582,4.729816],[52.718727,4.731121],[52.719612,4.730873],[52.719637,4.731302],[52.719984,4.731311],[52.720026,4.732075],[52.720761,4.732091],[52.720754,4.732581],[52.720894,4.73259],[52.720909,4.732841],[52.721014,4.732848],[52.721005,4.733877],[52.720964,4.733879]],"routeError":null}],"straightDistance":168.5,"walkingDistance":228,"walkingDuration":182.4,"coverageStatus":"between_150_275","analysisError":null},{"id":"005ef96a-aaee-56cb-8cbd-cfb592910b1e","address":"De Camper 7A","postcode":"1749BX","city":"Warmenhuizen","lat":52.71836570960407,"lon":4.730109238451178,"nearestContainerId":"WH20","nearestContainerAddress":"Oudewal 24","nearestContainerAccuracy":"handmatig bepaald (zeer hoog, onzekerheid -1 m)","nearestContainers":[{"id":"WH20","address":"Oudewal 24","accuracy":"handmatig bepaald (zeer hoog, onzekerheid -1 m)","type":"rest","status":"new","straightDistance":167.7,"walkingDistance":212.9,"walkingDuration":170.2,"coverageStatus":"between_150_275","routeCacheKey":"route-v1|https://routing.openstreetmap.de/routed-foot|foot|005ef96a-aaee-56cb-8cbd-cfb592910b1e|52.718366|4.730109|WH20|52.719722|4.731197","routeGeometry":[[52.718607,4.730036],[52.718727,4.731121],[52.719612,4.730873],[52.719637,4.731302],[52.719721,4.731304]],"routeError":null},{"id":"WH21","address":"Oudewal 57","accuracy":"handmatig bepaald (zeer hoog, onzekerheid -1 m)","type":"rest","status":"new","straightDistance":275.5,"walkingDistance":495.6,"walkingDuration":396.5,"coverageStatus":"over_275","routeCacheKey":"route-v1|https://routing.openstreetmap.de/routed-foot|foot|005ef96a-aaee-56cb-8cbd-cfb592910b1e|52.718366|4.730109|WH21|52.719220|4.726270","routeGeometry":[[52.718607,4.730036],[52.718727,4.731121],[52.719612,4.730873],[52.719556,4.729219],[52.719435,4.728108],[52.719263,4.726936],[52.719261,4.726341],[52.719204,4.726347],[52.719198,4.726275]],"routeError":null},{"id":"WH19","address":"Zwartepad 32","accuracy":"handmatig bepaald (zeer hoog, onzekerheid -1 m)","type":"rest","status":"new","straightDistance":381.9,"walkingDistance":527.3,"walkingDuration":421.9,"coverageStatus":"over_275","routeCacheKey":"route-v1|https://routing.openstreetmap.de/routed-foot|foot|005ef96a-aaee-56cb-8cbd-cfb592910b1e|52.718366|4.730109|WH19|52.720963|4.733820","routeGeometry":[[52.718607,4.730036],[52.718727,4.731121],[52.719612,4.730873],[52.719637,4.731302],[52.719984,4.731311],[52.720026,4.732075],[52.720761,4.732091],[52.720754,4.732581],[52.720894,4.73259],[52.720909,4.732841],[52.721014,4.732848],[52.721005,4.733877],[52.720964,4.733879]],"routeError":null}],"straightDistance":167.7,"walkingDistance":212.9,"walkingDuration":170.2,"coverageStatus":"between_150_275","analysisError":null},{"id":"8e513549-a07f-58c9-a7af-943e39d5b852","address":"De Camper 8","postcode":"1749BX","city":"Warmenhuizen","lat":52.71887626683354,"lon":4.72979330562347,"nearestContainerId":"WH20","nearestContainerAddress":"Oudewal 24","nearestContainerAccuracy":"handmatig bepaald (zeer hoog, onzekerheid -1 m)","nearestContainers":[{"id":"WH20","address":"Oudewal 24","accuracy":"handmatig bepaald (zeer hoog, onzekerheid -1 m)","type":"rest","status":"new","straightDistance":133.3,"walkingDistance":223.6,"walkingDuration":178.9,"coverageStatus":"between_150_275","routeCacheKey":"route-v1|https://routing.openstreetmap.de/routed-foot|foot|8e513549-a07f-58c9-a7af-943e39d5b852|52.718876|4.729793|WH20|52.719722|4.731197","routeGeometry":[[52.718589,4.72988],[52.718727,4.731121],[52.719612,4.730873],[52.719637,4.731302],[52.719721,4.731304]],"routeError":null},{"id":"WH21","address":"Oudewal 57","accuracy":"handmatig bepaald (zeer hoog, onzekerheid -1 m)","type":"rest","status":"new","straightDistance":240.4,"walkingDistance":506.3,"walkingDuration":405.2,"coverageStatus":"over_275","routeCacheKey":"route-v1|https://routing.openstreetmap.de/routed-foot|foot|8e513549-a07f-58c9-a7af-943e39d5b852|52.718876|4.729793|WH21|52.719220|4.726270","routeGeometry":[[52.718589,4.72988],[52.718727,4.731121],[52.719612,4.730873],[52.719556,4.729219],[52.719435,4.728108],[52.719263,4.726936],[52.719261,4.726341],[52.719204,4.726347],[52.719198,4.726275]],"routeError":null},{"id":"WH19","address":"Zwartepad 32","accuracy":"handmatig bepaald (zeer hoog, onzekerheid -1 m)","type":"rest","status":"new","straightDistance":356.9,"walkingDistance":538,"walkingDuration":430.6,"coverageStatus":"over_275","routeCacheKey":"route-v1|https://routing.openstreetmap.de/routed-foot|foot|8e513549-a07f-58c9-a7af-943e39d5b852|52.718876|4.729793|WH19|52.720963|4.733820","routeGeometry":[[52.718589,4.72988],[52.718727,4.731121],[52.719612,4.730873],[52.719637,4.731302],[52.719984,4.731311],[52.720026,4.732075],[52.720761,4.732091],[52.720754,4.732581],[52.720894,4.73259],[52.720909,4.732841],[52.721014,4.732848],[52.721005,4.733877],[52.720964,4.733879]],"routeError":null}],"straightDistance":133.3,"walkingDistance":223.6,"walkingDuration":178.9,"coverageStatus":"between_150_275","analysisError":null},{"id":"930b9905-ca3a-5519-b6d3-d837147d7486","address":"De Camper 10","postcode":"1749BX","city":"Warmenhuizen","lat":52.71874895712818,"lon":4.729272999122775,"nearestContainerId":"WH20","nearestContainerAddress":"Oudewal 24","nearestContainerAccuracy":"handmatig bepaald (zeer hoog, onzekerheid -1 m)","nearestContainers":[{"id":"WH20","address":"Oudewal 24","accuracy":"handmatig bepaald (zeer hoog, onzekerheid -1 m)","type":"rest","status":"new","straightDistance":168.8,"walkingDistance":246.7,"walkingDuration":197.3,"coverageStatus":"between_150_275","routeCacheKey":"route-v1|https://routing.openstreetmap.de/routed-foot|foot|930b9905-ca3a-5519-b6d3-d837147d7486|52.718749|4.729273|WH20|52.719722|4.731197","routeGeometry":[[52.718552,4.729543],[52.718727,4.731121],[52.719612,4.730873],[52.719637,4.731302],[52.719721,4.731304]],"routeError":null},{"id":"WH21","address":"Oudewal 57","accuracy":"handmatig bepaald (zeer hoog, onzekerheid -1 m)","type":"rest","status":"new","straightDistance":208.9,"walkingDistance":529.4,"walkingDuration":423.6,"coverageStatus":"over_275","routeCacheKey":"route-v1|https://routing.openstreetmap.de/routed-foot|foot|930b9905-ca3a-5519-b6d3-d837147d7486|52.718749|4.729273|WH21|52.719220|4.726270","routeGeometry":[[52.718552,4.729543],[52.718727,4.731121],[52.719612,4.730873],[52.719556,4.729219],[52.719435,4.728108],[52.719263,4.726936],[52.719261,4.726341],[52.719204,4.726347],[52.719198,4.726275]],"routeError":null},{"id":"WH18","address":"Schelphoek Noord 48","accuracy":"handmatig bepaald (zeer hoog, onzekerheid -1 m)","type":"rest","status":"new","straightDistance":371.4,"walkingDistance":562.6,"walkingDuration":450.1,"coverageStatus":"over_275","routeCacheKey":"route-v1|https://routing.openstreetmap.de/routed-foot|foot|930b9905-ca3a-5519-b6d3-d837147d7486|52.718749|4.729273|WH18|52.721767|4.731634","routeGeometry":[[52.718552,4.729543],[52.718727,4.731121],[52.719612,4.730873],[52.719637,4.731302],[52.720498,4.731338],[52.720511,4.730772],[52.721739,4.73083],[52.72174,4.731634]],"routeError":null}],"straightDistance":168.8,"walkingDistance":246.7,"walkingDuration":197.3,"coverageStatus":"between_150_275","analysisError":null},{"id":"ef697900-e054-5dc7-8388-7049611e9bba","address":"De Camper 10A","postcode":"1749BX","city":"Warmenhuizen","lat":52.71873331775169,"lon":4.729113316559976,"nearestContainerId":"WH20","nearestContainerAddress":"Oudewal 24","nearestContainerAccuracy":"handmatig bepaald (zeer hoog, onzekerheid -1 m)","nearestContainers":[{"id":"WH20","address":"Oudewal 24","accuracy":"handmatig bepaald (zeer hoog, onzekerheid -1 m)","type":"rest","status":"new","straightDistance":178.3,"walkingDistance":246.7,"walkingDuration":197.3,"coverageStatus":"between_150_275","routeCacheKey":"route-v1|https://routing.openstreetmap.de/routed-foot|foot|ef697900-e054-5dc7-8388-7049611e9bba|52.718733|4.729113|WH20|52.719722|4.731197","routeGeometry":[[52.718552,4.729543],[52.718727,4.731121],[52.719612,4.730873],[52.719637,4.731302],[52.719721,4.731304]],"routeError":null},{"id":"WH21","address":"Oudewal 57","accuracy":"handmatig bepaald (zeer hoog, onzekerheid -1 m)","type":"rest","status":"new","straightDistance":199,"walkingDistance":529.4,"walkingDuration":423.6,"coverageStatus":"over_275","routeCacheKey":"route-v1|https://routing.openstreetmap.de/routed-foot|foot|ef697900-e054-5dc7-8388-7049611e9bba|52.718733|4.729113|WH21|52.719220|4.726270","routeGeometry":[[52.718552,4.729543],[52.718727,4.731121],[52.719612,4.730873],[52.719556,4.729219],[52.719435,4.728108],[52.719263,4.726936],[52.719261,4.726341],[52.719204,4.726347],[52.719198,4.726275]],"routeError":null},{"id":"WH18","address":"Schelphoek Noord 48","accuracy":"handmatig bepaald (zeer hoog, onzekerheid -1 m)","type":"rest","status":"new","straightDistance":377.6,"walkingDistance":562.6,"walkingDuration":450.1,"coverageStatus":"over_275","routeCacheKey":"route-v1|https://routing.openstreetmap.de/routed-foot|foot|ef697900-e054-5dc7-8388-7049611e9bba|52.718733|4.729113|WH18|52.721767|4.731634","routeGeometry":[[52.718552,4.729543],[52.718727,4.731121],[52.719612,4.730873],[52.719637,4.731302],[52.720498,4.731338],[52.720511,4.730772],[52.721739,4.73083],[52.72174,4.731634]],"routeError":null}],"straightDistance":178.3,"walkingDistance":246.7,"walkingDuration":197.3,"coverageStatus":"between_150_275","analysisError":null},{"id":"5d5ca585-fde4-5dee-b9ca-24b022c6e91b","address":"De Camper 16A","postcode":"1749BX","city":"Warmenhuizen","lat":52.71821666578108,"lon":4.728731197314397,"nearestContainerId":"WH20","nearestContainerAddress":"Oudewal 24","nearestContainerAccuracy":"handmatig bepaald (zeer hoog, onzekerheid -1 m)","nearestContainers":[{"id":"WH20","address":"Oudewal 24","accuracy":"handmatig bepaald (zeer hoog, onzekerheid -1 m)","type":"rest","status":"new","straightDistance":235.8,"walkingDistance":276.2,"walkingDuration":221,"coverageStatus":"over_275","routeCacheKey":"route-v1|https://routing.openstreetmap.de/routed-foot|foot|5d5ca585-fde4-5dee-b9ca-24b022c6e91b|52.718217|4.728731|WH20|52.719722|4.731197","routeGeometry":[[52.71829,4.729604],[52.718552,4.729543],[52.718727,4.731121],[52.719612,4.730873],[52.719637,4.731302],[52.719721,4.731304]],"routeError":null},{"id":"WH21","address":"Oudewal 57","accuracy":"handmatig bepaald (zeer hoog, onzekerheid -1 m)","type":"rest","status":"new","straightDistance":199.8,"walkingDistance":558.9,"walkingDuration":447.3,"coverageStatus":"over_275","routeCacheKey":"route-v1|https://routing.openstreetmap.de/routed-foot|foot|5d5ca585-fde4-5dee-b9ca-24b022c6e91b|52.718217|4.728731|WH21|52.719220|4.726270","routeGeometry":[[52.71829,4.729604],[52.718552,4.729543],[52.718727,4.731121],[52.719612,4.730873],[52.719556,4.729219],[52.719435,4.728108],[52.719263,4.726936],[52.719261,4.726341],[52.719204,4.726347],[52.719198,4.726275]],"routeError":null},{"id":"WH22","address":"Oudevaart 87","accuracy":"handmatig bepaald (zeer hoog, onzekerheid -1 m)","type":"rest","status":"new","straightDistance":263.4,"walkingDistance":588,"walkingDuration":470.3,"coverageStatus":"over_275","routeCacheKey":"route-v1|https://routing.openstreetmap.de/routed-foot|foot|5d5ca585-fde4-5dee-b9ca-24b022c6e91b|52.718217|4.728731|WH22|52.715871|4.728182","routeGeometry":[[52.71829,4.729604],[52.717311,4.729826],[52.717429,4.731297],[52.716315,4.731552],[52.716019,4.7281],[52.715867,4.728139]],"routeError":null}],"straightDistance":235.8,"walkingDistance":276.2,"walkingDuration":221,"coverageStatus":"over_275","analysisError":null},{"id":"6e9c0961-eec1-511c-9b29-69805584db0e","address":"De Camper 18","postcode":"1749BX","city":"Warmenhuizen","lat":52.71805993176451,"lon":4.729433768017835,"nearestContainerId":"WH20","nearestContainerAddress":"Oudewal 24","nearestContainerAccuracy":"handmatig bepaald (zeer hoog, onzekerheid -1 m)","nearestContainers":[{"id":"WH20","address":"Oudewal 24","accuracy":"handmatig bepaald (zeer hoog, onzekerheid -1 m)","type":"rest","status":"new","straightDistance":219.7,"walkingDistance":300,"walkingDuration":240,"coverageStatus":"over_275","routeCacheKey":"route-v1|https://routing.openstreetmap.de/routed-foot|foot|6e9c0961-eec1-511c-9b29-69805584db0e|52.718060|4.729434|WH20|52.719722|4.731197","routeGeometry":[[52.718078,4.729652],[52.718552,4.729543],[52.718727,4.731121],[52.719612,4.730873],[52.719637,4.731302],[52.719721,4.731304]],"routeError":null},{"id":"WH22","address":"Oudevaart 87","accuracy":"handmatig bepaald (zeer hoog, onzekerheid -1 m)","type":"rest","status":"new","straightDistance":257.6,"walkingDistance":564.2,"walkingDuration":451.3,"coverageStatus":"over_275","routeCacheKey":"route-v1|https://routing.openstreetmap.de/routed-foot|foot|6e9c0961-eec1-511c-9b29-69805584db0e|52.718060|4.729434|WH22|52.715871|4.728182","routeGeometry":[[52.718078,4.729652],[52.717311,4.729826],[52.717429,4.731297],[52.716315,4.731552],[52.716019,4.7281],[52.715867,4.728139]],"routeError":null},{"id":"WH21","address":"Oudewal 57","accuracy":"handmatig bepaald (zeer hoog, onzekerheid -1 m)","type":"rest","status":"new","straightDistance":249.1,"walkingDistance":582.7,"walkingDuration":466.3,"coverageStatus":"over_275","routeCacheKey":"route-v1|https://routing.openstreetmap.de/routed-foot|foot|6e9c0961-eec1-511c-9b29-69805584db0e|52.718060|4.729434|WH21|52.719220|4.726270","routeGeometry":[[52.718078,4.729652],[52.718552,4.729543],[52.718727,4.731121],[52.719612,4.730873],[52.719556,4.729219],[52.719435,4.728108],[52.719263,4.726936],[52.719261,4.726341],[52.719204,4.726347],[52.719198,4.726275]],"routeError":null}],"straightDistance":219.7,"walkingDistance":300,"walkingDuration":240,"coverageStatus":"over_275","analysisError":null}]}
