{"detailBundle":"heerlijkheid","street":"Heerlijkheid","houses":[{"id":"a0bf2a5f-e136-560b-81cb-b8be38801f40","address":"Heerlijkheid 1","postcode":"1749LA","city":"Warmenhuizen","lat":52.72598002065399,"lon":4.74968383215468,"nearestContainerId":"WH06","nearestContainerAddress":"Soeverein 2","nearestContainerAccuracy":"hvc import (exacte locatie)","nearestContainers":[{"id":"WH06","address":"Soeverein 2","accuracy":"hvc import (exacte locatie)","type":"rest","status":"existing","straightDistance":183.8,"walkingDistance":188.1,"walkingDuration":150.5,"coverageStatus":"between_150_275","routeCacheKey":"route-v1|https://routing.openstreetmap.de/routed-foot|foot|a0bf2a5f-e136-560b-81cb-b8be38801f40|52.725980|4.749684|WH06|52.727578|4.750383","routeGeometry":[[52.726029,4.749696],[52.726015,4.749854],[52.727589,4.750259]],"routeError":null},{"id":"WH05","address":"Kuipersven 36","accuracy":"hvc import (exacte locatie)","type":"rest","status":"existing","straightDistance":129.2,"walkingDistance":212.9,"walkingDuration":170.3,"coverageStatus":"between_150_275","routeCacheKey":"route-v1|https://routing.openstreetmap.de/routed-foot|foot|a0bf2a5f-e136-560b-81cb-b8be38801f40|52.725980|4.749684|WH05|52.726883|4.748476","routeGeometry":[[52.726029,4.749696],[52.726087,4.749053],[52.726242,4.748978],[52.726204,4.748766],[52.726113,4.748806],[52.726099,4.748761],[52.72614,4.748207],[52.726891,4.748392]],"routeError":null},{"id":"WH04","address":"Maasweid 1","accuracy":"handmatig bepaald (zeer hoog, onzekerheid -1 m)","type":"rest","status":"new","straightDistance":338.3,"walkingDistance":407.9,"walkingDuration":326.2,"coverageStatus":"over_275","routeCacheKey":"route-v1|https://routing.openstreetmap.de/routed-foot|foot|a0bf2a5f-e136-560b-81cb-b8be38801f40|52.725980|4.749684|WH04|52.726813|4.744852","routeGeometry":[[52.726029,4.749696],[52.726087,4.749053],[52.726242,4.748978],[52.726204,4.748766],[52.726113,4.748806],[52.726099,4.748761],[52.72614,4.748207],[52.726319,4.748247],[52.726373,4.746633],[52.726416,4.746617],[52.726604,4.746314],[52.726696,4.746246],[52.72668,4.745977],[52.726713,4.745926],[52.726702,4.74577],[52.726757,4.745791],[52.726804,4.745082],[52.726792,4.744848]],"routeError":null}],"straightDistance":183.8,"walkingDistance":188.1,"walkingDuration":150.5,"coverageStatus":"between_150_275","analysisError":null},{"id":"9be18381-c38b-5e12-9b99-d952b943a5e4","address":"Heerlijkheid 2","postcode":"1749LA","city":"Warmenhuizen","lat":52.727413914273484,"lon":4.750071023518604,"nearestContainerId":"WH06","nearestContainerAddress":"Soeverein 2","nearestContainerAccuracy":"hvc import (exacte locatie)","nearestContainers":[{"id":"WH06","address":"Soeverein 2","accuracy":"hvc import (exacte locatie)","type":"rest","status":"existing","straightDistance":27.8,"walkingDistance":21.7,"walkingDuration":17.3,"coverageStatus":"within_100","routeCacheKey":"route-v1|https://routing.openstreetmap.de/routed-foot|foot|9be18381-c38b-5e12-9b99-d952b943a5e4|52.727414|4.750071|WH06|52.727578|4.750383","routeGeometry":[[52.727494,4.750092],[52.727481,4.750232],[52.727589,4.750259]],"routeError":null},{"id":"WH05","address":"Kuipersven 36","accuracy":"hvc import (exacte locatie)","type":"rest","status":"existing","straightDistance":122.6,"walkingDistance":181.2,"walkingDuration":145,"coverageStatus":"between_150_275","routeCacheKey":"route-v1|https://routing.openstreetmap.de/routed-foot|foot|9be18381-c38b-5e12-9b99-d952b943a5e4|52.727414|4.750071|WH05|52.726883|4.748476","routeGeometry":[[52.727494,4.750092],[52.727577,4.749218],[52.72698,4.74907],[52.726956,4.749005],[52.726989,4.748551],[52.726966,4.748411],[52.726891,4.748392]],"routeError":null},{"id":"WH34","address":"Poolster 25","accuracy":"hvc import (exacte locatie)","type":"rest","status":"existing","straightDistance":343.2,"walkingDistance":370.3,"walkingDuration":296.1,"coverageStatus":"over_275","routeCacheKey":"route-v1|https://routing.openstreetmap.de/routed-foot|foot|9be18381-c38b-5e12-9b99-d952b943a5e4|52.727414|4.750071|WH34|52.730485|4.750576","routeGeometry":[[52.727494,4.750092],[52.727481,4.750232],[52.727801,4.750312],[52.727939,4.750224],[52.72802,4.750245],[52.728154,4.750541],[52.728277,4.750581],[52.72834,4.750573],[52.728393,4.750515],[52.728521,4.750275],[52.728638,4.750238],[52.730448,4.750667],[52.730456,4.75057]],"routeError":null}],"straightDistance":27.8,"walkingDistance":21.7,"walkingDuration":17.3,"coverageStatus":"within_100","analysisError":null},{"id":"c3262870-c306-50de-8990-36a45242c23d","address":"Heerlijkheid 3","postcode":"1749LA","city":"Warmenhuizen","lat":52.72598582899351,"lon":4.74961719487798,"nearestContainerId":"WH06","nearestContainerAddress":"Soeverein 2","nearestContainerAccuracy":"hvc import (exacte locatie)","nearestContainers":[{"id":"WH06","address":"Soeverein 2","accuracy":"hvc import (exacte locatie)","type":"rest","status":"existing","straightDistance":184.4,"walkingDistance":193.3,"walkingDuration":154.6,"coverageStatus":"between_150_275","routeCacheKey":"route-v1|https://routing.openstreetmap.de/routed-foot|foot|c3262870-c306-50de-8990-36a45242c23d|52.725986|4.749617|WH06|52.727578|4.750383","routeGeometry":[[52.726035,4.749629],[52.72604,4.749578],[52.726363,4.749656],[52.726417,4.749962],[52.727589,4.750259]],"routeError":null},{"id":"WH05","address":"Kuipersven 36","accuracy":"hvc import (exacte locatie)","type":"rest","status":"existing","straightDistance":125.9,"walkingDistance":208.4,"walkingDuration":166.7,"coverageStatus":"between_150_275","routeCacheKey":"route-v1|https://routing.openstreetmap.de/routed-foot|foot|c3262870-c306-50de-8990-36a45242c23d|52.725986|4.749617|WH05|52.726883|4.748476","routeGeometry":[[52.726035,4.749629],[52.726087,4.749053],[52.726242,4.748978],[52.726204,4.748766],[52.726113,4.748806],[52.726099,4.748761],[52.72614,4.748207],[52.726891,4.748392]],"routeError":null},{"id":"WH04","address":"Maasweid 1","accuracy":"handmatig bepaald (zeer hoog, onzekerheid -1 m)","type":"rest","status":"new","straightDistance":333.8,"walkingDistance":403.3,"walkingDuration":322.6,"coverageStatus":"over_275","routeCacheKey":"route-v1|https://routing.openstreetmap.de/routed-foot|foot|c3262870-c306-50de-8990-36a45242c23d|52.725986|4.749617|WH04|52.726813|4.744852","routeGeometry":[[52.726035,4.749629],[52.726087,4.749053],[52.726242,4.748978],[52.726204,4.748766],[52.726113,4.748806],[52.726099,4.748761],[52.72614,4.748207],[52.726319,4.748247],[52.726373,4.746633],[52.726416,4.746617],[52.726604,4.746314],[52.726696,4.746246],[52.72668,4.745977],[52.726713,4.745926],[52.726702,4.74577],[52.726757,4.745791],[52.726804,4.745082],[52.726792,4.744848]],"routeError":null}],"straightDistance":184.4,"walkingDistance":193.3,"walkingDuration":154.6,"coverageStatus":"between_150_275","analysisError":null},{"id":"c9eda7ce-3737-51c1-be16-0373b8f45483","address":"Heerlijkheid 4","postcode":"1749LA","city":"Warmenhuizen","lat":52.72736138225975,"lon":4.750058788958958,"nearestContainerId":"WH06","nearestContainerAddress":"Soeverein 2","nearestContainerAccuracy":"hvc import (exacte locatie)","nearestContainers":[{"id":"WH06","address":"Soeverein 2","accuracy":"hvc import (exacte locatie)","type":"rest","status":"existing","straightDistance":32.5,"walkingDistance":26.9,"walkingDuration":21.5,"coverageStatus":"within_100","routeCacheKey":"route-v1|https://routing.openstreetmap.de/routed-foot|foot|c9eda7ce-3737-51c1-be16-0373b8f45483|52.727361|4.750059|WH06|52.727578|4.750383","routeGeometry":[[52.72735,4.750199],[52.727589,4.750259]],"routeError":null},{"id":"WH05","address":"Kuipersven 36","accuracy":"hvc import (exacte locatie)","type":"rest","status":"existing","straightDistance":119.1,"walkingDistance":177.7,"walkingDuration":142.1,"coverageStatus":"between_150_275","routeCacheKey":"route-v1|https://routing.openstreetmap.de/routed-foot|foot|c9eda7ce-3737-51c1-be16-0373b8f45483|52.727361|4.750059|WH05|52.726883|4.748476","routeGeometry":[[52.72735,4.750199],[52.726951,4.7501],[52.72706,4.749087],[52.72698,4.74907],[52.726956,4.749005],[52.726989,4.748551],[52.726966,4.748411],[52.726891,4.748392]],"routeError":null},{"id":"WH34","address":"Poolster 25","accuracy":"hvc import (exacte locatie)","type":"rest","status":"existing","straightDistance":349.1,"walkingDistance":375.5,"walkingDuration":300.3,"coverageStatus":"over_275","routeCacheKey":"route-v1|https://routing.openstreetmap.de/routed-foot|foot|c9eda7ce-3737-51c1-be16-0373b8f45483|52.727361|4.750059|WH34|52.730485|4.750576","routeGeometry":[[52.72735,4.750199],[52.727801,4.750312],[52.72799,4.750228],[52.728048,4.750275],[52.728154,4.750541],[52.728277,4.750581],[52.72834,4.750573],[52.728393,4.750515],[52.728521,4.750275],[52.728638,4.750238],[52.730448,4.750667],[52.730456,4.75057]],"routeError":null}],"straightDistance":32.5,"walkingDistance":26.9,"walkingDuration":21.5,"coverageStatus":"within_100","analysisError":null},{"id":"24b6689b-8305-5338-b5be-e68ec78d9006","address":"Heerlijkheid 5","postcode":"1749LA","city":"Warmenhuizen","lat":52.726000304006206,"lon":4.749475633636292,"nearestContainerId":"WH06","nearestContainerAddress":"Soeverein 2","nearestContainerAccuracy":"hvc import (exacte locatie)","nearestContainers":[{"id":"WH06","address":"Soeverein 2","accuracy":"hvc import (exacte locatie)","type":"rest","status":"existing","straightDistance":185.8,"walkingDistance":196,"walkingDuration":156.7,"coverageStatus":"between_150_275","routeCacheKey":"route-v1|https://routing.openstreetmap.de/routed-foot|foot|24b6689b-8305-5338-b5be-e68ec78d9006|52.726000|4.749476|WH06|52.727578|4.750383","routeGeometry":[[52.726048,4.749488],[52.72604,4.749578],[52.726363,4.749656],[52.726417,4.749962],[52.727589,4.750259]],"routeError":null},{"id":"WH05","address":"Kuipersven 36","accuracy":"hvc import (exacte locatie)","type":"rest","status":"existing","straightDistance":119,"walkingDistance":198.7,"walkingDuration":159,"coverageStatus":"between_150_275","routeCacheKey":"route-v1|https://routing.openstreetmap.de/routed-foot|foot|24b6689b-8305-5338-b5be-e68ec78d9006|52.726000|4.749476|WH05|52.726883|4.748476","routeGeometry":[[52.726048,4.749488],[52.726087,4.749053],[52.726242,4.748978],[52.726204,4.748766],[52.726113,4.748806],[52.726099,4.748761],[52.72614,4.748207],[52.726891,4.748392]],"routeError":null},{"id":"WH04","address":"Maasweid 1","accuracy":"handmatig bepaald (zeer hoog, onzekerheid -1 m)","type":"rest","status":"new","straightDistance":324.2,"walkingDistance":393.7,"walkingDuration":314.9,"coverageStatus":"over_275","routeCacheKey":"route-v1|https://routing.openstreetmap.de/routed-foot|foot|24b6689b-8305-5338-b5be-e68ec78d9006|52.726000|4.749476|WH04|52.726813|4.744852","routeGeometry":[[52.726048,4.749488],[52.726087,4.749053],[52.726242,4.748978],[52.726204,4.748766],[52.726113,4.748806],[52.726099,4.748761],[52.72614,4.748207],[52.726319,4.748247],[52.726373,4.746633],[52.726416,4.746617],[52.726604,4.746314],[52.726696,4.746246],[52.72668,4.745977],[52.726713,4.745926],[52.726702,4.74577],[52.726757,4.745791],[52.726804,4.745082],[52.726792,4.744848]],"routeError":null}],"straightDistance":185.8,"walkingDistance":196,"walkingDuration":156.7,"coverageStatus":"between_150_275","analysisError":null},{"id":"1851c437-ba71-5e6d-a491-841a4e1d3715","address":"Heerlijkheid 6","postcode":"1749LA","city":"Warmenhuizen","lat":52.72731688691751,"lon":4.750046970668028,"nearestContainerId":"WH06","nearestContainerAddress":"Soeverein 2","nearestContainerAccuracy":"hvc import (exacte locatie)","nearestContainers":[{"id":"WH06","address":"Soeverein 2","accuracy":"hvc import (exacte locatie)","type":"rest","status":"existing","straightDistance":36.8,"walkingDistance":32.1,"walkingDuration":25.7,"coverageStatus":"within_100","routeCacheKey":"route-v1|https://routing.openstreetmap.de/routed-foot|foot|1851c437-ba71-5e6d-a491-841a4e1d3715|52.727317|4.750047|WH06|52.727578|4.750383","routeGeometry":[[52.727304,4.750188],[52.727589,4.750259]],"routeError":null},{"id":"WH05","address":"Kuipersven 36","accuracy":"hvc import (exacte locatie)","type":"rest","status":"existing","straightDistance":116.3,"walkingDistance":172.5,"walkingDuration":137.9,"coverageStatus":"between_150_275","routeCacheKey":"route-v1|https://routing.openstreetmap.de/routed-foot|foot|1851c437-ba71-5e6d-a491-841a4e1d3715|52.727317|4.750047|WH05|52.726883|4.748476","routeGeometry":[[52.727304,4.750188],[52.726951,4.7501],[52.72706,4.749087],[52.72698,4.74907],[52.726956,4.749005],[52.726989,4.748551],[52.726966,4.748411],[52.726891,4.748392]],"routeError":null},{"id":"WH34","address":"Poolster 25","accuracy":"hvc import (exacte locatie)","type":"rest","status":"existing","straightDistance":354.1,"walkingDistance":380.7,"walkingDuration":304.5,"coverageStatus":"over_275","routeCacheKey":"route-v1|https://routing.openstreetmap.de/routed-foot|foot|1851c437-ba71-5e6d-a491-841a4e1d3715|52.727317|4.750047|WH34|52.730485|4.750576","routeGeometry":[[52.727304,4.750188],[52.727801,4.750312],[52.72799,4.750228],[52.728048,4.750275],[52.728154,4.750541],[52.728277,4.750581],[52.72834,4.750573],[52.728393,4.750515],[52.728521,4.750275],[52.728638,4.750238],[52.730448,4.750667],[52.730456,4.75057]],"routeError":null}],"straightDistance":36.8,"walkingDistance":32.1,"walkingDuration":25.7,"coverageStatus":"within_100","analysisError":null},{"id":"2d53bdfc-2cd5-57fb-ade5-83bb2d85da92","address":"Heerlijkheid 7","postcode":"1749LA","city":"Warmenhuizen","lat":52.72600513314055,"lon":4.749402378919812,"nearestContainerId":"WH05","nearestContainerAddress":"Kuipersven 36","nearestContainerAccuracy":"hvc import (exacte locatie)","nearestContainers":[{"id":"WH05","address":"Kuipersven 36","accuracy":"hvc import (exacte locatie)","type":"rest","status":"existing","straightDistance":115.8,"walkingDistance":193.7,"walkingDuration":155,"coverageStatus":"between_150_275","routeCacheKey":"route-v1|https://routing.openstreetmap.de/routed-foot|foot|2d53bdfc-2cd5-57fb-ade5-83bb2d85da92|52.726005|4.749402|WH05|52.726883|4.748476","routeGeometry":[[52.726055,4.749414],[52.726087,4.749053],[52.726242,4.748978],[52.726204,4.748766],[52.726113,4.748806],[52.726099,4.748761],[52.72614,4.748207],[52.726891,4.748392]],"routeError":null},{"id":"WH06","address":"Soeverein 2","accuracy":"hvc import (exacte locatie)","type":"rest","status":"existing","straightDistance":186.9,"walkingDistance":201,"walkingDuration":160.7,"coverageStatus":"between_150_275","routeCacheKey":"route-v1|https://routing.openstreetmap.de/routed-foot|foot|2d53bdfc-2cd5-57fb-ade5-83bb2d85da92|52.726005|4.749402|WH06|52.727578|4.750383","routeGeometry":[[52.726055,4.749414],[52.72604,4.749578],[52.726363,4.749656],[52.726417,4.749962],[52.727589,4.750259]],"routeError":null},{"id":"WH04","address":"Maasweid 1","accuracy":"handmatig bepaald (zeer hoog, onzekerheid -1 m)","type":"rest","status":"new","straightDistance":319.3,"walkingDistance":388.6,"walkingDuration":310.9,"coverageStatus":"over_275","routeCacheKey":"route-v1|https://routing.openstreetmap.de/routed-foot|foot|2d53bdfc-2cd5-57fb-ade5-83bb2d85da92|52.726005|4.749402|WH04|52.726813|4.744852","routeGeometry":[[52.726055,4.749414],[52.726087,4.749053],[52.726242,4.748978],[52.726204,4.748766],[52.726113,4.748806],[52.726099,4.748761],[52.72614,4.748207],[52.726319,4.748247],[52.726373,4.746633],[52.726416,4.746617],[52.726604,4.746314],[52.726696,4.746246],[52.72668,4.745977],[52.726713,4.745926],[52.726702,4.74577],[52.726757,4.745791],[52.726804,4.745082],[52.726792,4.744848]],"routeError":null}],"straightDistance":115.8,"walkingDistance":193.7,"walkingDuration":155,"coverageStatus":"between_150_275","analysisError":null},{"id":"5c291f76-3cc6-54ed-94c7-c1c438b85b4a","address":"Heerlijkheid 8","postcode":"1749LA","city":"Warmenhuizen","lat":52.727267959655094,"lon":4.750029872814644,"nearestContainerId":"WH06","nearestContainerAddress":"Soeverein 2","nearestContainerAccuracy":"hvc import (exacte locatie)","nearestContainers":[{"id":"WH06","address":"Soeverein 2","accuracy":"hvc import (exacte locatie)","type":"rest","status":"existing","straightDistance":41.9,"walkingDistance":37.6,"walkingDuration":30.1,"coverageStatus":"within_100","routeCacheKey":"route-v1|https://routing.openstreetmap.de/routed-foot|foot|5c291f76-3cc6-54ed-94c7-c1c438b85b4a|52.727268|4.750030|WH06|52.727578|4.750383","routeGeometry":[[52.727255,4.750175],[52.727589,4.750259]],"routeError":null},{"id":"WH05","address":"Kuipersven 36","accuracy":"hvc import (exacte locatie)","type":"rest","status":"existing","straightDistance":113.1,"walkingDistance":167,"walkingDuration":133.5,"coverageStatus":"between_150_275","routeCacheKey":"route-v1|https://routing.openstreetmap.de/routed-foot|foot|5c291f76-3cc6-54ed-94c7-c1c438b85b4a|52.727268|4.750030|WH05|52.726883|4.748476","routeGeometry":[[52.727255,4.750175],[52.726951,4.7501],[52.72706,4.749087],[52.72698,4.74907],[52.726956,4.749005],[52.726989,4.748551],[52.726966,4.748411],[52.726891,4.748392]],"routeError":null},{"id":"WH34","address":"Poolster 25","accuracy":"hvc import (exacte locatie)","type":"rest","status":"existing","straightDistance":359.6,"walkingDistance":386.2,"walkingDuration":308.9,"coverageStatus":"over_275","routeCacheKey":"route-v1|https://routing.openstreetmap.de/routed-foot|foot|5c291f76-3cc6-54ed-94c7-c1c438b85b4a|52.727268|4.750030|WH34|52.730485|4.750576","routeGeometry":[[52.727255,4.750175],[52.727801,4.750312],[52.72799,4.750228],[52.728048,4.750275],[52.728154,4.750541],[52.728277,4.750581],[52.72834,4.750573],[52.728393,4.750515],[52.728521,4.750275],[52.728638,4.750238],[52.730448,4.750667],[52.730456,4.75057]],"routeError":null}],"straightDistance":41.9,"walkingDistance":37.6,"walkingDuration":30.1,"coverageStatus":"within_100","analysisError":null},{"id":"697e38ec-1f04-5976-8766-6c19a225df58","address":"Heerlijkheid 9","postcode":"1749LA","city":"Warmenhuizen","lat":52.72601248090065,"lon":4.749327873760902,"nearestContainerId":"WH05","nearestContainerAddress":"Kuipersven 36","nearestContainerAccuracy":"hvc import (exacte locatie)","nearestContainers":[{"id":"WH05","address":"Kuipersven 36","accuracy":"hvc import (exacte locatie)","type":"rest","status":"existing","straightDistance":112.5,"walkingDistance":188.6,"walkingDuration":150.9,"coverageStatus":"between_150_275","routeCacheKey":"route-v1|https://routing.openstreetmap.de/routed-foot|foot|697e38ec-1f04-5976-8766-6c19a225df58|52.726012|4.749328|WH05|52.726883|4.748476","routeGeometry":[[52.726061,4.74934],[52.726087,4.749053],[52.726242,4.748978],[52.726204,4.748766],[52.726113,4.748806],[52.726099,4.748761],[52.72614,4.748207],[52.726891,4.748392]],"routeError":null},{"id":"WH06","address":"Soeverein 2","accuracy":"hvc import (exacte locatie)","type":"rest","status":"existing","straightDistance":188,"walkingDistance":206.1,"walkingDuration":164.8,"coverageStatus":"between_150_275","routeCacheKey":"route-v1|https://routing.openstreetmap.de/routed-foot|foot|697e38ec-1f04-5976-8766-6c19a225df58|52.726012|4.749328|WH06|52.727578|4.750383","routeGeometry":[[52.726061,4.74934],[52.72604,4.749578],[52.726363,4.749656],[52.726417,4.749962],[52.727589,4.750259]],"routeError":null},{"id":"WH04","address":"Maasweid 1","accuracy":"handmatig bepaald (zeer hoog, onzekerheid -1 m)","type":"rest","status":"new","straightDistance":314.3,"walkingDistance":383.6,"walkingDuration":306.8,"coverageStatus":"over_275","routeCacheKey":"route-v1|https://routing.openstreetmap.de/routed-foot|foot|697e38ec-1f04-5976-8766-6c19a225df58|52.726012|4.749328|WH04|52.726813|4.744852","routeGeometry":[[52.726061,4.74934],[52.726087,4.749053],[52.726242,4.748978],[52.726204,4.748766],[52.726113,4.748806],[52.726099,4.748761],[52.72614,4.748207],[52.726319,4.748247],[52.726373,4.746633],[52.726416,4.746617],[52.726604,4.746314],[52.726696,4.746246],[52.72668,4.745977],[52.726713,4.745926],[52.726702,4.74577],[52.726757,4.745791],[52.726804,4.745082],[52.726792,4.744848]],"routeError":null}],"straightDistance":112.5,"walkingDistance":188.6,"walkingDuration":150.9,"coverageStatus":"between_150_275","analysisError":null},{"id":"75369edf-bab6-569f-a902-37f6514b831f","address":"Heerlijkheid 10","postcode":"1749LA","city":"Warmenhuizen","lat":52.72721160302364,"lon":4.750009966649369,"nearestContainerId":"WH06","nearestContainerAddress":"Soeverein 2","nearestContainerAccuracy":"hvc import (exacte locatie)","nearestContainers":[{"id":"WH06","address":"Soeverein 2","accuracy":"hvc import (exacte locatie)","type":"rest","status":"existing","straightDistance":47.9,"walkingDistance":44,"walkingDuration":35.2,"coverageStatus":"within_100","routeCacheKey":"route-v1|https://routing.openstreetmap.de/routed-foot|foot|75369edf-bab6-569f-a902-37f6514b831f|52.727212|4.750010|WH06|52.727578|4.750383","routeGeometry":[[52.727198,4.750161],[52.727589,4.750259]],"routeError":null},{"id":"WH05","address":"Kuipersven 36","accuracy":"hvc import (exacte locatie)","type":"rest","status":"existing","straightDistance":109.6,"walkingDistance":160.6,"walkingDuration":128.4,"coverageStatus":"between_150_275","routeCacheKey":"route-v1|https://routing.openstreetmap.de/routed-foot|foot|75369edf-bab6-569f-a902-37f6514b831f|52.727212|4.750010|WH05|52.726883|4.748476","routeGeometry":[[52.727198,4.750161],[52.726951,4.7501],[52.72706,4.749087],[52.72698,4.74907],[52.726956,4.749005],[52.726989,4.748551],[52.726966,4.748411],[52.726891,4.748392]],"routeError":null},{"id":"WH34","address":"Poolster 25","accuracy":"hvc import (exacte locatie)","type":"rest","status":"existing","straightDistance":366,"walkingDistance":392.6,"walkingDuration":314,"coverageStatus":"over_275","routeCacheKey":"route-v1|https://routing.openstreetmap.de/routed-foot|foot|75369edf-bab6-569f-a902-37f6514b831f|52.727212|4.750010|WH34|52.730485|4.750576","routeGeometry":[[52.727198,4.750161],[52.727801,4.750312],[52.72799,4.750228],[52.728048,4.750275],[52.728154,4.750541],[52.728277,4.750581],[52.72834,4.750573],[52.728393,4.750515],[52.728521,4.750275],[52.728638,4.750238],[52.730448,4.750667],[52.730456,4.75057]],"routeError":null}],"straightDistance":47.9,"walkingDistance":44,"walkingDuration":35.2,"coverageStatus":"within_100","analysisError":null},{"id":"70b8095c-312e-5f71-a199-c1fb21cc242e","address":"Heerlijkheid 11","postcode":"1749LA","city":"Warmenhuizen","lat":52.72601933608566,"lon":4.749260407021094,"nearestContainerId":"WH05","nearestContainerAddress":"Kuipersven 36","nearestContainerAccuracy":"hvc import (exacte locatie)","nearestContainers":[{"id":"WH05","address":"Kuipersven 36","accuracy":"hvc import (exacte locatie)","type":"rest","status":"existing","straightDistance":109.6,"walkingDistance":184,"walkingDuration":147.1,"coverageStatus":"between_150_275","routeCacheKey":"route-v1|https://routing.openstreetmap.de/routed-foot|foot|70b8095c-312e-5f71-a199-c1fb21cc242e|52.726019|4.749260|WH05|52.726883|4.748476","routeGeometry":[[52.726068,4.749272],[52.726087,4.749053],[52.726242,4.748978],[52.726204,4.748766],[52.726113,4.748806],[52.726099,4.748761],[52.72614,4.748207],[52.726891,4.748392]],"routeError":null},{"id":"WH06","address":"Soeverein 2","accuracy":"hvc import (exacte locatie)","type":"rest","status":"existing","straightDistance":189.1,"walkingDistance":206.9,"walkingDuration":165.4,"coverageStatus":"between_150_275","routeCacheKey":"route-v1|https://routing.openstreetmap.de/routed-foot|foot|70b8095c-312e-5f71-a199-c1fb21cc242e|52.726019|4.749260|WH06|52.727578|4.750383","routeGeometry":[[52.726068,4.749272],[52.726152,4.749235],[52.726223,4.749622],[52.726363,4.749656],[52.726417,4.749962],[52.727589,4.750259]],"routeError":null},{"id":"WH04","address":"Maasweid 1","accuracy":"handmatig bepaald (zeer hoog, onzekerheid -1 m)","type":"rest","status":"new","straightDistance":309.7,"walkingDistance":378.9,"walkingDuration":303,"coverageStatus":"over_275","routeCacheKey":"route-v1|https://routing.openstreetmap.de/routed-foot|foot|70b8095c-312e-5f71-a199-c1fb21cc242e|52.726019|4.749260|WH04|52.726813|4.744852","routeGeometry":[[52.726068,4.749272],[52.726087,4.749053],[52.726242,4.748978],[52.726204,4.748766],[52.726113,4.748806],[52.726099,4.748761],[52.72614,4.748207],[52.726319,4.748247],[52.726373,4.746633],[52.726416,4.746617],[52.726604,4.746314],[52.726696,4.746246],[52.72668,4.745977],[52.726713,4.745926],[52.726702,4.74577],[52.726757,4.745791],[52.726804,4.745082],[52.726792,4.744848]],"routeError":null}],"straightDistance":109.6,"walkingDistance":184,"walkingDuration":147.1,"coverageStatus":"between_150_275","analysisError":null},{"id":"063dd8f6-e51d-53be-988a-65bbb86c79e2","address":"Heerlijkheid 12","postcode":"1749LA","city":"Warmenhuizen","lat":52.72717014925604,"lon":4.750010642507154,"nearestContainerId":"WH06","nearestContainerAddress":"Soeverein 2","nearestContainerAccuracy":"hvc import (exacte locatie)","nearestContainers":[{"id":"WH06","address":"Soeverein 2","accuracy":"hvc import (exacte locatie)","type":"rest","status":"existing","straightDistance":51.8,"walkingDistance":48.6,"walkingDuration":38.9,"coverageStatus":"within_100","routeCacheKey":"route-v1|https://routing.openstreetmap.de/routed-foot|foot|063dd8f6-e51d-53be-988a-65bbb86c79e2|52.727170|4.750011|WH06|52.727578|4.750383","routeGeometry":[[52.727157,4.750151],[52.727589,4.750259]],"routeError":null},{"id":"WH05","address":"Kuipersven 36","accuracy":"hvc import (exacte locatie)","type":"rest","status":"existing","straightDistance":108.2,"walkingDistance":155.9,"walkingDuration":124.7,"coverageStatus":"between_150_275","routeCacheKey":"route-v1|https://routing.openstreetmap.de/routed-foot|foot|063dd8f6-e51d-53be-988a-65bbb86c79e2|52.727170|4.750011|WH05|52.726883|4.748476","routeGeometry":[[52.727157,4.750151],[52.726951,4.7501],[52.72706,4.749087],[52.72698,4.74907],[52.726956,4.749005],[52.726989,4.748551],[52.726966,4.748411],[52.726891,4.748392]],"routeError":null},{"id":"WH34","address":"Poolster 25","accuracy":"hvc import (exacte locatie)","type":"rest","status":"existing","straightDistance":370.6,"walkingDistance":397.2,"walkingDuration":317.7,"coverageStatus":"over_275","routeCacheKey":"route-v1|https://routing.openstreetmap.de/routed-foot|foot|063dd8f6-e51d-53be-988a-65bbb86c79e2|52.727170|4.750011|WH34|52.730485|4.750576","routeGeometry":[[52.727157,4.750151],[52.727801,4.750312],[52.72799,4.750228],[52.728048,4.750275],[52.728154,4.750541],[52.728277,4.750581],[52.72834,4.750573],[52.728393,4.750515],[52.728521,4.750275],[52.728638,4.750238],[52.730448,4.750667],[52.730456,4.75057]],"routeError":null}],"straightDistance":51.8,"walkingDistance":48.6,"walkingDuration":38.9,"coverageStatus":"within_100","analysisError":null},{"id":"1e2aa835-5944-5cab-812b-a7d7f2ae9b02","address":"Heerlijkheid 13","postcode":"1749LA","city":"Warmenhuizen","lat":52.72605032122276,"lon":4.748986609705132,"nearestContainerId":"WH05","nearestContainerAddress":"Kuipersven 36","nearestContainerAccuracy":"hvc import (exacte locatie)","nearestContainers":[{"id":"WH05","address":"Kuipersven 36","accuracy":"hvc import (exacte locatie)","type":"rest","status":"existing","straightDistance":98.8,"walkingDistance":171.7,"walkingDuration":137.4,"coverageStatus":"between_150_275","routeCacheKey":"route-v1|https://routing.openstreetmap.de/routed-foot|foot|1e2aa835-5944-5cab-812b-a7d7f2ae9b02|52.726050|4.748987|WH05|52.726883|4.748476","routeGeometry":[[52.726064,4.749064],[52.726242,4.748978],[52.726204,4.748766],[52.726113,4.748806],[52.726099,4.748761],[52.72614,4.748207],[52.726891,4.748392]],"routeError":null},{"id":"WH06","address":"Soeverein 2","accuracy":"hvc import (exacte locatie)","type":"rest","status":"existing","straightDistance":194.2,"walkingDistance":216.4,"walkingDuration":173,"coverageStatus":"between_150_275","routeCacheKey":"route-v1|https://routing.openstreetmap.de/routed-foot|foot|1e2aa835-5944-5cab-812b-a7d7f2ae9b02|52.726050|4.748987|WH06|52.727578|4.750383","routeGeometry":[[52.726064,4.749064],[52.726116,4.749039],[52.726223,4.749622],[52.726363,4.749656],[52.726417,4.749962],[52.727589,4.750259]],"routeError":null},{"id":"WH04","address":"Maasweid 1","accuracy":"handmatig bepaald (zeer hoog, onzekerheid -1 m)","type":"rest","status":"new","straightDistance":291.1,"walkingDistance":366.6,"walkingDuration":293.3,"coverageStatus":"over_275","routeCacheKey":"route-v1|https://routing.openstreetmap.de/routed-foot|foot|1e2aa835-5944-5cab-812b-a7d7f2ae9b02|52.726050|4.748987|WH04|52.726813|4.744852","routeGeometry":[[52.726064,4.749064],[52.726242,4.748978],[52.726204,4.748766],[52.726113,4.748806],[52.726099,4.748761],[52.72614,4.748207],[52.726319,4.748247],[52.726373,4.746633],[52.726416,4.746617],[52.726604,4.746314],[52.726696,4.746246],[52.72668,4.745977],[52.726713,4.745926],[52.726702,4.74577],[52.726757,4.745791],[52.726804,4.745082],[52.726792,4.744848]],"routeError":null}],"straightDistance":98.8,"walkingDistance":171.7,"walkingDuration":137.4,"coverageStatus":"between_150_275","analysisError":null},{"id":"89422675-29a9-543b-8b53-5238b8296e03","address":"Heerlijkheid 14","postcode":"1749LA","city":"Warmenhuizen","lat":52.72711546420124,"lon":4.749989054196778,"nearestContainerId":"WH06","nearestContainerAddress":"Soeverein 2","nearestContainerAccuracy":"hvc import (exacte locatie)","nearestContainers":[{"id":"WH06","address":"Soeverein 2","accuracy":"hvc import (exacte locatie)","type":"rest","status":"existing","straightDistance":57.9,"walkingDistance":54.8,"walkingDuration":43.9,"coverageStatus":"within_100","routeCacheKey":"route-v1|https://routing.openstreetmap.de/routed-foot|foot|89422675-29a9-543b-8b53-5238b8296e03|52.727115|4.749989|WH06|52.727578|4.750383","routeGeometry":[[52.727102,4.750137],[52.727589,4.750259]],"routeError":null},{"id":"WH05","address":"Kuipersven 36","accuracy":"hvc import (exacte locatie)","type":"rest","status":"existing","straightDistance":105.1,"walkingDistance":149.8,"walkingDuration":119.7,"coverageStatus":"between_125_150","routeCacheKey":"route-v1|https://routing.openstreetmap.de/routed-foot|foot|89422675-29a9-543b-8b53-5238b8296e03|52.727115|4.749989|WH05|52.726883|4.748476","routeGeometry":[[52.727102,4.750137],[52.726951,4.7501],[52.72706,4.749087],[52.72698,4.74907],[52.726956,4.749005],[52.726989,4.748551],[52.726966,4.748411],[52.726891,4.748392]],"routeError":null},{"id":"WH04","address":"Maasweid 1","accuracy":"handmatig bepaald (zeer hoog, onzekerheid -1 m)","type":"rest","status":"new","straightDistance":347.6,"walkingDistance":399.2,"walkingDuration":319.1,"coverageStatus":"over_275","routeCacheKey":"route-v1|https://routing.openstreetmap.de/routed-foot|foot|89422675-29a9-543b-8b53-5238b8296e03|52.727115|4.749989|WH04|52.726813|4.744852","routeGeometry":[[52.727102,4.750137],[52.726951,4.7501],[52.72706,4.749087],[52.72698,4.74907],[52.726956,4.749005],[52.726989,4.748551],[52.726785,4.747248],[52.726765,4.746825],[52.726733,4.746833],[52.726696,4.746246],[52.72668,4.745977],[52.726713,4.745926],[52.726702,4.74577],[52.726757,4.745791],[52.726804,4.745082],[52.726792,4.744848]],"routeError":null}],"straightDistance":57.9,"walkingDistance":54.8,"walkingDuration":43.9,"coverageStatus":"within_100","analysisError":null},{"id":"33fa223d-58b5-54a1-87e0-b538cc8dd1b8","address":"Heerlijkheid 15","postcode":"1749LA","city":"Warmenhuizen","lat":52.72608887879689,"lon":4.748970402545405,"nearestContainerId":"WH05","nearestContainerAddress":"Kuipersven 36","nearestContainerAccuracy":"hvc import (exacte locatie)","nearestContainers":[{"id":"WH05","address":"Kuipersven 36","accuracy":"hvc import (exacte locatie)","type":"rest","status":"existing","straightDistance":94.4,"walkingDistance":167.3,"walkingDuration":133.7,"coverageStatus":"between_150_275","routeCacheKey":"route-v1|https://routing.openstreetmap.de/routed-foot|foot|33fa223d-58b5-54a1-87e0-b538cc8dd1b8|52.726089|4.748970|WH05|52.726883|4.748476","routeGeometry":[[52.726102,4.749046],[52.726242,4.748978],[52.726204,4.748766],[52.726113,4.748806],[52.726099,4.748761],[52.72614,4.748207],[52.726891,4.748392]],"routeError":null},{"id":"WH06","address":"Soeverein 2","accuracy":"hvc import (exacte locatie)","type":"rest","status":"existing","straightDistance":191,"walkingDistance":212,"walkingDuration":169.3,"coverageStatus":"between_150_275","routeCacheKey":"route-v1|https://routing.openstreetmap.de/routed-foot|foot|33fa223d-58b5-54a1-87e0-b538cc8dd1b8|52.726089|4.748970|WH06|52.727578|4.750383","routeGeometry":[[52.726102,4.749046],[52.726223,4.749622],[52.726363,4.749656],[52.726417,4.749962],[52.727589,4.750259]],"routeError":null},{"id":"WH04","address":"Maasweid 1","accuracy":"handmatig bepaald (zeer hoog, onzekerheid -1 m)","type":"rest","status":"new","straightDistance":288.8,"walkingDistance":362.2,"walkingDuration":289.6,"coverageStatus":"over_275","routeCacheKey":"route-v1|https://routing.openstreetmap.de/routed-foot|foot|33fa223d-58b5-54a1-87e0-b538cc8dd1b8|52.726089|4.748970|WH04|52.726813|4.744852","routeGeometry":[[52.726102,4.749046],[52.726242,4.748978],[52.726204,4.748766],[52.726113,4.748806],[52.726099,4.748761],[52.72614,4.748207],[52.726319,4.748247],[52.726373,4.746633],[52.726416,4.746617],[52.726604,4.746314],[52.726696,4.746246],[52.72668,4.745977],[52.726713,4.745926],[52.726702,4.74577],[52.726757,4.745791],[52.726804,4.745082],[52.726792,4.744848]],"routeError":null}],"straightDistance":94.4,"walkingDistance":167.3,"walkingDuration":133.7,"coverageStatus":"between_150_275","analysisError":null},{"id":"ed64be36-24f6-5ac2-ab46-6bfe3382ea72","address":"Heerlijkheid 16","postcode":"1749LA","city":"Warmenhuizen","lat":52.72707598986716,"lon":4.749980079344028,"nearestContainerId":"WH06","nearestContainerAddress":"Soeverein 2","nearestContainerAccuracy":"hvc import (exacte locatie)","nearestContainers":[{"id":"WH06","address":"Soeverein 2","accuracy":"hvc import (exacte locatie)","type":"rest","status":"existing","straightDistance":62.1,"walkingDistance":59.2,"walkingDuration":47.4,"coverageStatus":"within_100","routeCacheKey":"route-v1|https://routing.openstreetmap.de/routed-foot|foot|ed64be36-24f6-5ac2-ab46-6bfe3382ea72|52.727076|4.749980|WH06|52.727578|4.750383","routeGeometry":[[52.727063,4.750128],[52.727589,4.750259]],"routeError":null},{"id":"WH05","address":"Kuipersven 36","accuracy":"hvc import (exacte locatie)","type":"rest","status":"existing","straightDistance":103.5,"walkingDistance":145.4,"walkingDuration":116.2,"coverageStatus":"between_125_150","routeCacheKey":"route-v1|https://routing.openstreetmap.de/routed-foot|foot|ed64be36-24f6-5ac2-ab46-6bfe3382ea72|52.727076|4.749980|WH05|52.726883|4.748476","routeGeometry":[[52.727063,4.750128],[52.726951,4.7501],[52.72706,4.749087],[52.72698,4.74907],[52.726956,4.749005],[52.726989,4.748551],[52.726966,4.748411],[52.726891,4.748392]],"routeError":null},{"id":"WH04","address":"Maasweid 1","accuracy":"handmatig bepaald (zeer hoog, onzekerheid -1 m)","type":"rest","status":"new","straightDistance":346.6,"walkingDistance":394.8,"walkingDuration":315.6,"coverageStatus":"over_275","routeCacheKey":"route-v1|https://routing.openstreetmap.de/routed-foot|foot|ed64be36-24f6-5ac2-ab46-6bfe3382ea72|52.727076|4.749980|WH04|52.726813|4.744852","routeGeometry":[[52.727063,4.750128],[52.726951,4.7501],[52.72706,4.749087],[52.72698,4.74907],[52.726956,4.749005],[52.726989,4.748551],[52.726785,4.747248],[52.726765,4.746825],[52.726733,4.746833],[52.72668,4.745977],[52.726713,4.745926],[52.726702,4.74577],[52.726757,4.745791],[52.726804,4.745082],[52.726792,4.744848]],"routeError":null}],"straightDistance":62.1,"walkingDistance":59.2,"walkingDuration":47.4,"coverageStatus":"within_100","analysisError":null},{"id":"9ed33957-07b5-58f9-80a5-8db8ae077118","address":"Heerlijkheid 17","postcode":"1749LA","city":"Warmenhuizen","lat":52.72612338609225,"lon":4.748951382524538,"nearestContainerId":"WH05","nearestContainerAddress":"Kuipersven 36","nearestContainerAccuracy":"hvc import (exacte locatie)","nearestContainers":[{"id":"WH05","address":"Kuipersven 36","accuracy":"hvc import (exacte locatie)","type":"rest","status":"existing","straightDistance":90.3,"walkingDistance":163.2,"walkingDuration":130.6,"coverageStatus":"between_150_275","routeCacheKey":"route-v1|https://routing.openstreetmap.de/routed-foot|foot|9ed33957-07b5-58f9-80a5-8db8ae077118|52.726123|4.748951|WH05|52.726883|4.748476","routeGeometry":[[52.726137,4.749029],[52.726242,4.748978],[52.726204,4.748766],[52.726113,4.748806],[52.726099,4.748761],[52.72614,4.748207],[52.726891,4.748392]],"routeError":null},{"id":"WH06","address":"Soeverein 2","accuracy":"hvc import (exacte locatie)","type":"rest","status":"existing","straightDistance":188.3,"walkingDistance":212.8,"walkingDuration":170,"coverageStatus":"between_150_275","routeCacheKey":"route-v1|https://routing.openstreetmap.de/routed-foot|foot|9ed33957-07b5-58f9-80a5-8db8ae077118|52.726123|4.748951|WH06|52.727578|4.750383","routeGeometry":[[52.726137,4.749029],[52.726116,4.749039],[52.726223,4.749622],[52.726363,4.749656],[52.726417,4.749962],[52.727589,4.750259]],"routeError":null},{"id":"WH04","address":"Maasweid 1","accuracy":"handmatig bepaald (zeer hoog, onzekerheid -1 m)","type":"rest","status":"new","straightDistance":286.5,"walkingDistance":358.2,"walkingDuration":286.5,"coverageStatus":"over_275","routeCacheKey":"route-v1|https://routing.openstreetmap.de/routed-foot|foot|9ed33957-07b5-58f9-80a5-8db8ae077118|52.726123|4.748951|WH04|52.726813|4.744852","routeGeometry":[[52.726137,4.749029],[52.726242,4.748978],[52.726204,4.748766],[52.726113,4.748806],[52.726099,4.748761],[52.72614,4.748207],[52.726319,4.748247],[52.726373,4.746633],[52.726416,4.746617],[52.726604,4.746314],[52.726696,4.746246],[52.72668,4.745977],[52.726713,4.745926],[52.726702,4.74577],[52.726757,4.745791],[52.726804,4.745082],[52.726792,4.744848]],"routeError":null}],"straightDistance":90.3,"walkingDistance":163.2,"walkingDuration":130.6,"coverageStatus":"between_150_275","analysisError":null},{"id":"500fd195-5fe0-5bbb-b49f-37096d256165","address":"Heerlijkheid 18","postcode":"1749LA","city":"Warmenhuizen","lat":52.72671103059979,"lon":4.749732692005231,"nearestContainerId":"WH05","nearestContainerAddress":"Kuipersven 36","nearestContainerAccuracy":"hvc import (exacte locatie)","nearestContainers":[{"id":"WH05","address":"Kuipersven 36","accuracy":"hvc import (exacte locatie)","type":"rest","status":"existing","straightDistance":86.8,"walkingDistance":134.5,"walkingDuration":107.6,"coverageStatus":"between_125_150","routeCacheKey":"route-v1|https://routing.openstreetmap.de/routed-foot|foot|500fd195-5fe0-5bbb-b49f-37096d256165|52.726711|4.749733|WH05|52.726883|4.748476","routeGeometry":[[52.72672,4.749783],[52.727004,4.749646],[52.72706,4.749087],[52.72698,4.74907],[52.726956,4.749005],[52.726989,4.748551],[52.726966,4.748411],[52.726891,4.748392]],"routeError":null},{"id":"WH06","address":"Soeverein 2","accuracy":"hvc import (exacte locatie)","type":"rest","status":"existing","straightDistance":105.9,"walkingDistance":136,"walkingDuration":108.8,"coverageStatus":"between_125_150","routeCacheKey":"route-v1|https://routing.openstreetmap.de/routed-foot|foot|500fd195-5fe0-5bbb-b49f-37096d256165|52.726711|4.749733|WH06|52.727578|4.750383","routeGeometry":[[52.72672,4.749783],[52.727004,4.749646],[52.726951,4.7501],[52.727589,4.750259]],"routeError":null},{"id":"WH04","address":"Maasweid 1","accuracy":"handmatig bepaald (zeer hoog, onzekerheid -1 m)","type":"rest","status":"new","straightDistance":328.9,"walkingDistance":383.9,"walkingDuration":307,"coverageStatus":"over_275","routeCacheKey":"route-v1|https://routing.openstreetmap.de/routed-foot|foot|500fd195-5fe0-5bbb-b49f-37096d256165|52.726711|4.749733|WH04|52.726813|4.744852","routeGeometry":[[52.72672,4.749783],[52.727004,4.749646],[52.72706,4.749087],[52.72698,4.74907],[52.726956,4.749005],[52.726989,4.748551],[52.726785,4.747248],[52.726765,4.746825],[52.726733,4.746833],[52.72668,4.745977],[52.726713,4.745926],[52.726702,4.74577],[52.726757,4.745791],[52.726804,4.745082],[52.726792,4.744848]],"routeError":null}],"straightDistance":86.8,"walkingDistance":134.5,"walkingDuration":107.6,"coverageStatus":"between_125_150","analysisError":null},{"id":"2463b141-b8ff-57dc-a6c8-8f949d72b560","address":"Heerlijkheid 19","postcode":"1749LA","city":"Warmenhuizen","lat":52.72616948837319,"lon":4.748930994830015,"nearestContainerId":"WH05","nearestContainerAddress":"Kuipersven 36","nearestContainerAccuracy":"hvc import (exacte locatie)","nearestContainers":[{"id":"WH05","address":"Kuipersven 36","accuracy":"hvc import (exacte locatie)","type":"rest","status":"existing","straightDistance":85,"walkingDistance":158,"walkingDuration":126.4,"coverageStatus":"between_150_275","routeCacheKey":"route-v1|https://routing.openstreetmap.de/routed-foot|foot|2463b141-b8ff-57dc-a6c8-8f949d72b560|52.726169|4.748931|WH05|52.726883|4.748476","routeGeometry":[[52.726182,4.749007],[52.726242,4.748978],[52.726204,4.748766],[52.726113,4.748806],[52.726099,4.748761],[52.72614,4.748207],[52.726891,4.748392]],"routeError":null},{"id":"WH06","address":"Soeverein 2","accuracy":"hvc import (exacte locatie)","type":"rest","status":"existing","straightDistance":184.6,"walkingDistance":208.2,"walkingDuration":166.4,"coverageStatus":"between_150_275","routeCacheKey":"route-v1|https://routing.openstreetmap.de/routed-foot|foot|2463b141-b8ff-57dc-a6c8-8f949d72b560|52.726169|4.748931|WH06|52.727578|4.750383","routeGeometry":[[52.726182,4.749007],[52.726242,4.748978],[52.726417,4.749962],[52.727589,4.750259]],"routeError":null},{"id":"WH04","address":"Maasweid 1","accuracy":"handmatig bepaald (zeer hoog, onzekerheid -1 m)","type":"rest","status":"new","straightDistance":283.9,"walkingDistance":353,"walkingDuration":282.3,"coverageStatus":"over_275","routeCacheKey":"route-v1|https://routing.openstreetmap.de/routed-foot|foot|2463b141-b8ff-57dc-a6c8-8f949d72b560|52.726169|4.748931|WH04|52.726813|4.744852","routeGeometry":[[52.726182,4.749007],[52.726242,4.748978],[52.726204,4.748766],[52.726113,4.748806],[52.726099,4.748761],[52.72614,4.748207],[52.726319,4.748247],[52.726373,4.746633],[52.726416,4.746617],[52.726604,4.746314],[52.726696,4.746246],[52.72668,4.745977],[52.726713,4.745926],[52.726702,4.74577],[52.726757,4.745791],[52.726804,4.745082],[52.726792,4.744848]],"routeError":null}],"straightDistance":85,"walkingDistance":158,"walkingDuration":126.4,"coverageStatus":"between_150_275","analysisError":null},{"id":"579c373d-7426-5a0e-88a9-a05772cd4ad3","address":"Heerlijkheid 20","postcode":"1749LA","city":"Warmenhuizen","lat":52.726659951238446,"lon":4.749753432652943,"nearestContainerId":"WH05","nearestContainerAddress":"Kuipersven 36","nearestContainerAccuracy":"hvc import (exacte locatie)","nearestContainers":[{"id":"WH05","address":"Kuipersven 36","accuracy":"hvc import (exacte locatie)","type":"rest","status":"existing","straightDistance":89.5,"walkingDistance":140.3,"walkingDuration":112.3,"coverageStatus":"between_125_150","routeCacheKey":"route-v1|https://routing.openstreetmap.de/routed-foot|foot|579c373d-7426-5a0e-88a9-a05772cd4ad3|52.726660|4.749753|WH05|52.726883|4.748476","routeGeometry":[[52.72667,4.749807],[52.727004,4.749646],[52.72706,4.749087],[52.72698,4.74907],[52.726956,4.749005],[52.726989,4.748551],[52.726966,4.748411],[52.726891,4.748392]],"routeError":null},{"id":"WH06","address":"Soeverein 2","accuracy":"hvc import (exacte locatie)","type":"rest","status":"existing","straightDistance":110.5,"walkingDistance":141.8,"walkingDuration":113.5,"coverageStatus":"between_125_150","routeCacheKey":"route-v1|https://routing.openstreetmap.de/routed-foot|foot|579c373d-7426-5a0e-88a9-a05772cd4ad3|52.726660|4.749753|WH06|52.727578|4.750383","routeGeometry":[[52.72667,4.749807],[52.727004,4.749646],[52.726951,4.7501],[52.727589,4.750259]],"routeError":null},{"id":"WH04","address":"Maasweid 1","accuracy":"handmatig bepaald (zeer hoog, onzekerheid -1 m)","type":"rest","status":"new","straightDistance":330.5,"walkingDistance":389.7,"walkingDuration":311.7,"coverageStatus":"over_275","routeCacheKey":"route-v1|https://routing.openstreetmap.de/routed-foot|foot|579c373d-7426-5a0e-88a9-a05772cd4ad3|52.726660|4.749753|WH04|52.726813|4.744852","routeGeometry":[[52.72667,4.749807],[52.727004,4.749646],[52.72706,4.749087],[52.72698,4.74907],[52.726956,4.749005],[52.726989,4.748551],[52.726785,4.747248],[52.726765,4.746825],[52.726733,4.746833],[52.72668,4.745977],[52.726713,4.745926],[52.726702,4.74577],[52.726757,4.745791],[52.726804,4.745082],[52.726792,4.744848]],"routeError":null}],"straightDistance":89.5,"walkingDistance":140.3,"walkingDuration":112.3,"coverageStatus":"between_125_150","analysisError":null},{"id":"1838ebe5-a7e8-58d4-b124-8bca8841d9c7","address":"Heerlijkheid 21","postcode":"1749LA","city":"Warmenhuizen","lat":52.726302435834675,"lon":4.749721455335349,"nearestContainerId":"WH06","nearestContainerAddress":"Soeverein 2","nearestContainerAccuracy":"hvc import (exacte locatie)","nearestContainers":[{"id":"WH06","address":"Soeverein 2","accuracy":"hvc import (exacte locatie)","type":"rest","status":"existing","straightDistance":148.7,"walkingDistance":159.6,"walkingDuration":127.6,"coverageStatus":"between_150_275","routeCacheKey":"route-v1|https://routing.openstreetmap.de/routed-foot|foot|1838ebe5-a7e8-58d4-b124-8bca8841d9c7|52.726302|4.749721|WH06|52.727578|4.750383","routeGeometry":[[52.726309,4.749643],[52.726363,4.749656],[52.726417,4.749962],[52.727589,4.750259]],"routeError":null},{"id":"WH05","address":"Kuipersven 36","accuracy":"hvc import (exacte locatie)","type":"rest","status":"existing","straightDistance":105.8,"walkingDistance":204.9,"walkingDuration":163.8,"coverageStatus":"between_150_275","routeCacheKey":"route-v1|https://routing.openstreetmap.de/routed-foot|foot|1838ebe5-a7e8-58d4-b124-8bca8841d9c7|52.726302|4.749721|WH05|52.726883|4.748476","routeGeometry":[[52.726309,4.749643],[52.726363,4.749656],[52.726204,4.748766],[52.726113,4.748806],[52.726099,4.748761],[52.72614,4.748207],[52.726891,4.748392]],"routeError":null},{"id":"WH04","address":"Maasweid 1","accuracy":"handmatig bepaald (zeer hoog, onzekerheid -1 m)","type":"rest","status":"new","straightDistance":332.8,"walkingDistance":399.8,"walkingDuration":319.7,"coverageStatus":"over_275","routeCacheKey":"route-v1|https://routing.openstreetmap.de/routed-foot|foot|1838ebe5-a7e8-58d4-b124-8bca8841d9c7|52.726302|4.749721|WH04|52.726813|4.744852","routeGeometry":[[52.726309,4.749643],[52.726363,4.749656],[52.726204,4.748766],[52.726113,4.748806],[52.726099,4.748761],[52.72614,4.748207],[52.726319,4.748247],[52.726373,4.746633],[52.726416,4.746617],[52.726604,4.746314],[52.726696,4.746246],[52.72668,4.745977],[52.726713,4.745926],[52.726702,4.74577],[52.726757,4.745791],[52.726804,4.745082],[52.726792,4.744848]],"routeError":null}],"straightDistance":148.7,"walkingDistance":159.6,"walkingDuration":127.6,"coverageStatus":"between_150_275","analysisError":null},{"id":"5aca535d-2490-506d-95a0-a4da1ecb5d85","address":"Heerlijkheid 22","postcode":"1749LA","city":"Warmenhuizen","lat":52.72661427495202,"lon":4.749776196792863,"nearestContainerId":"WH05","nearestContainerAddress":"Kuipersven 36","nearestContainerAccuracy":"hvc import (exacte locatie)","nearestContainers":[{"id":"WH05","address":"Kuipersven 36","accuracy":"hvc import (exacte locatie)","type":"rest","status":"existing","straightDistance":92.5,"walkingDistance":145.7,"walkingDuration":116.6,"coverageStatus":"between_125_150","routeCacheKey":"route-v1|https://routing.openstreetmap.de/routed-foot|foot|5aca535d-2490-506d-95a0-a4da1ecb5d85|52.726614|4.749776|WH05|52.726883|4.748476","routeGeometry":[[52.726623,4.749829],[52.727004,4.749646],[52.72706,4.749087],[52.72698,4.74907],[52.726956,4.749005],[52.726989,4.748551],[52.726966,4.748411],[52.726891,4.748392]],"routeError":null},{"id":"WH06","address":"Soeverein 2","accuracy":"hvc import (exacte locatie)","type":"rest","status":"existing","straightDistance":114.7,"walkingDistance":147.2,"walkingDuration":117.8,"coverageStatus":"between_125_150","routeCacheKey":"route-v1|https://routing.openstreetmap.de/routed-foot|foot|5aca535d-2490-506d-95a0-a4da1ecb5d85|52.726614|4.749776|WH06|52.727578|4.750383","routeGeometry":[[52.726623,4.749829],[52.727004,4.749646],[52.726951,4.7501],[52.727589,4.750259]],"routeError":null},{"id":"WH04","address":"Maasweid 1","accuracy":"handmatig bepaald (zeer hoog, onzekerheid -1 m)","type":"rest","status":"new","straightDistance":332.3,"walkingDistance":395.1,"walkingDuration":316,"coverageStatus":"over_275","routeCacheKey":"route-v1|https://routing.openstreetmap.de/routed-foot|foot|5aca535d-2490-506d-95a0-a4da1ecb5d85|52.726614|4.749776|WH04|52.726813|4.744852","routeGeometry":[[52.726623,4.749829],[52.727004,4.749646],[52.72706,4.749087],[52.72698,4.74907],[52.726956,4.749005],[52.726989,4.748551],[52.726785,4.747248],[52.726765,4.746825],[52.726733,4.746833],[52.72668,4.745977],[52.726713,4.745926],[52.726702,4.74577],[52.726757,4.745791],[52.726804,4.745082],[52.726792,4.744848]],"routeError":null}],"straightDistance":92.5,"walkingDistance":145.7,"walkingDuration":116.6,"coverageStatus":"between_125_150","analysisError":null},{"id":"a6bb0eac-0398-5a73-a4e1-892cd9d3dd66","address":"Heerlijkheid 23","postcode":"1749LA","city":"Warmenhuizen","lat":52.7262512062574,"lon":4.749712459192302,"nearestContainerId":"WH06","nearestContainerAddress":"Soeverein 2","nearestContainerAccuracy":"hvc import (exacte locatie)","nearestContainers":[{"id":"WH06","address":"Soeverein 2","accuracy":"hvc import (exacte locatie)","type":"rest","status":"existing","straightDistance":154.3,"walkingDistance":165.3,"walkingDuration":132.2,"coverageStatus":"between_150_275","routeCacheKey":"route-v1|https://routing.openstreetmap.de/routed-foot|foot|a6bb0eac-0398-5a73-a4e1-892cd9d3dd66|52.726251|4.749712|WH06|52.727578|4.750383","routeGeometry":[[52.726258,4.749631],[52.726363,4.749656],[52.726417,4.749962],[52.727589,4.750259]],"routeError":null},{"id":"WH05","address":"Kuipersven 36","accuracy":"hvc import (exacte locatie)","type":"rest","status":"existing","straightDistance":108.9,"walkingDistance":210.5,"walkingDuration":168.2,"coverageStatus":"between_150_275","routeCacheKey":"route-v1|https://routing.openstreetmap.de/routed-foot|foot|a6bb0eac-0398-5a73-a4e1-892cd9d3dd66|52.726251|4.749712|WH05|52.726883|4.748476","routeGeometry":[[52.726258,4.749631],[52.726223,4.749622],[52.726183,4.749402],[52.726307,4.749341],[52.726204,4.748766],[52.726113,4.748806],[52.726099,4.748761],[52.72614,4.748207],[52.726891,4.748392]],"routeError":null},{"id":"WH04","address":"Maasweid 1","accuracy":"handmatig bepaald (zeer hoog, onzekerheid -1 m)","type":"rest","status":"new","straightDistance":333.2,"walkingDistance":405.4,"walkingDuration":324.1,"coverageStatus":"over_275","routeCacheKey":"route-v1|https://routing.openstreetmap.de/routed-foot|foot|a6bb0eac-0398-5a73-a4e1-892cd9d3dd66|52.726251|4.749712|WH04|52.726813|4.744852","routeGeometry":[[52.726258,4.749631],[52.726223,4.749622],[52.726183,4.749402],[52.726307,4.749341],[52.726204,4.748766],[52.726113,4.748806],[52.726099,4.748761],[52.72614,4.748207],[52.726319,4.748247],[52.726373,4.746633],[52.726416,4.746617],[52.726604,4.746314],[52.726696,4.746246],[52.72668,4.745977],[52.726713,4.745926],[52.726702,4.74577],[52.726757,4.745791],[52.726804,4.745082],[52.726792,4.744848]],"routeError":null}],"straightDistance":154.3,"walkingDistance":165.3,"walkingDuration":132.2,"coverageStatus":"between_150_275","analysisError":null},{"id":"8e0a1ea5-a1ce-5c5c-8076-60d57a3d9f4c","address":"Heerlijkheid 24","postcode":"1749LA","city":"Warmenhuizen","lat":52.72656317408192,"lon":4.749786205562317,"nearestContainerId":"WH05","nearestContainerAddress":"Kuipersven 36","nearestContainerAccuracy":"hvc import (exacte locatie)","nearestContainers":[{"id":"WH05","address":"Kuipersven 36","accuracy":"hvc import (exacte locatie)","type":"rest","status":"existing","straightDistance":95.1,"walkingDistance":151.3,"walkingDuration":121.1,"coverageStatus":"between_150_275","routeCacheKey":"route-v1|https://routing.openstreetmap.de/routed-foot|foot|8e0a1ea5-a1ce-5c5c-8076-60d57a3d9f4c|52.726563|4.749786|WH05|52.726883|4.748476","routeGeometry":[[52.726575,4.749853],[52.727004,4.749646],[52.72706,4.749087],[52.72698,4.74907],[52.726956,4.749005],[52.726989,4.748551],[52.726966,4.748411],[52.726891,4.748392]],"routeError":null},{"id":"WH06","address":"Soeverein 2","accuracy":"hvc import (exacte locatie)","type":"rest","status":"existing","straightDistance":119.8,"walkingDistance":152.8,"walkingDuration":122.3,"coverageStatus":"between_150_275","routeCacheKey":"route-v1|https://routing.openstreetmap.de/routed-foot|foot|8e0a1ea5-a1ce-5c5c-8076-60d57a3d9f4c|52.726563|4.749786|WH06|52.727578|4.750383","routeGeometry":[[52.726575,4.749853],[52.727004,4.749646],[52.726951,4.7501],[52.727589,4.750259]],"routeError":null},{"id":"WH04","address":"Maasweid 1","accuracy":"handmatig bepaald (zeer hoog, onzekerheid -1 m)","type":"rest","status":"new","straightDistance":333.4,"walkingDistance":400.7,"walkingDuration":320.5,"coverageStatus":"over_275","routeCacheKey":"route-v1|https://routing.openstreetmap.de/routed-foot|foot|8e0a1ea5-a1ce-5c5c-8076-60d57a3d9f4c|52.726563|4.749786|WH04|52.726813|4.744852","routeGeometry":[[52.726575,4.749853],[52.727004,4.749646],[52.72706,4.749087],[52.72698,4.74907],[52.726956,4.749005],[52.726989,4.748551],[52.726785,4.747248],[52.726765,4.746825],[52.726733,4.746833],[52.72668,4.745977],[52.726713,4.745926],[52.726702,4.74577],[52.726757,4.745791],[52.726804,4.745082],[52.726792,4.744848]],"routeError":null}],"straightDistance":95.1,"walkingDistance":151.3,"walkingDuration":121.1,"coverageStatus":"between_150_275","analysisError":null},{"id":"7865bf74-b377-511d-8163-c615209e8f51","address":"Heerlijkheid 25","postcode":"1749LA","city":"Warmenhuizen","lat":52.72620402235655,"lon":4.749700384542263,"nearestContainerId":"WH06","nearestContainerAddress":"Soeverein 2","nearestContainerAccuracy":"hvc import (exacte locatie)","nearestContainers":[{"id":"WH06","address":"Soeverein 2","accuracy":"hvc import (exacte locatie)","type":"rest","status":"existing","straightDistance":159.5,"walkingDistance":170.6,"walkingDuration":136.4,"coverageStatus":"between_150_275","routeCacheKey":"route-v1|https://routing.openstreetmap.de/routed-foot|foot|7865bf74-b377-511d-8163-c615209e8f51|52.726204|4.749700|WH06|52.727578|4.750383","routeGeometry":[[52.726211,4.749619],[52.726363,4.749656],[52.726417,4.749962],[52.727589,4.750259]],"routeError":null},{"id":"WH05","address":"Kuipersven 36","accuracy":"hvc import (exacte locatie)","type":"rest","status":"existing","straightDistance":111.8,"walkingDistance":207.9,"walkingDuration":166.2,"coverageStatus":"between_150_275","routeCacheKey":"route-v1|https://routing.openstreetmap.de/routed-foot|foot|7865bf74-b377-511d-8163-c615209e8f51|52.726204|4.749700|WH05|52.726883|4.748476","routeGeometry":[[52.726211,4.749619],[52.726183,4.749402],[52.726307,4.749341],[52.726204,4.748766],[52.726113,4.748806],[52.726099,4.748761],[52.72614,4.748207],[52.726891,4.748392]],"routeError":null},{"id":"WH04","address":"Maasweid 1","accuracy":"handmatig bepaald (zeer hoog, onzekerheid -1 m)","type":"rest","status":"new","straightDistance":333.4,"walkingDistance":402.8,"walkingDuration":322.1,"coverageStatus":"over_275","routeCacheKey":"route-v1|https://routing.openstreetmap.de/routed-foot|foot|7865bf74-b377-511d-8163-c615209e8f51|52.726204|4.749700|WH04|52.726813|4.744852","routeGeometry":[[52.726211,4.749619],[52.726183,4.749402],[52.726307,4.749341],[52.726204,4.748766],[52.726113,4.748806],[52.726099,4.748761],[52.72614,4.748207],[52.726319,4.748247],[52.726373,4.746633],[52.726416,4.746617],[52.726604,4.746314],[52.726696,4.746246],[52.72668,4.745977],[52.726713,4.745926],[52.726702,4.74577],[52.726757,4.745791],[52.726804,4.745082],[52.726792,4.744848]],"routeError":null}],"straightDistance":159.5,"walkingDistance":170.6,"walkingDuration":136.4,"coverageStatus":"between_150_275","analysisError":null},{"id":"494238c8-056a-537e-92b0-f73c5a199757","address":"Heerlijkheid 26","postcode":"1749LA","city":"Warmenhuizen","lat":52.72629788713497,"lon":4.749783337889354,"nearestContainerId":"WH06","nearestContainerAddress":"Soeverein 2","nearestContainerAccuracy":"hvc import (exacte locatie)","nearestContainers":[{"id":"WH06","address":"Soeverein 2","accuracy":"hvc import (exacte locatie)","type":"rest","status":"existing","straightDistance":148,"walkingDistance":147.3,"walkingDuration":117.8,"coverageStatus":"between_125_150","routeCacheKey":"route-v1|https://routing.openstreetmap.de/routed-foot|foot|494238c8-056a-537e-92b0-f73c5a199757|52.726298|4.749783|WH06|52.727578|4.750383","routeGeometry":[[52.726379,4.749744],[52.726417,4.749962],[52.727589,4.750259]],"routeError":null},{"id":"WH05","address":"Kuipersven 36","accuracy":"hvc import (exacte locatie)","type":"rest","status":"existing","straightDistance":109.5,"walkingDistance":205,"walkingDuration":163.8,"coverageStatus":"between_150_275","routeCacheKey":"route-v1|https://routing.openstreetmap.de/routed-foot|foot|494238c8-056a-537e-92b0-f73c5a199757|52.726298|4.749783|WH05|52.726883|4.748476","routeGeometry":[[52.726379,4.749744],[52.726204,4.748766],[52.726113,4.748806],[52.726099,4.748761],[52.72614,4.748207],[52.726891,4.748392]],"routeError":null},{"id":"WH04","address":"Maasweid 1","accuracy":"handmatig bepaald (zeer hoog, onzekerheid -1 m)","type":"rest","status":"new","straightDistance":337,"walkingDistance":399.9,"walkingDuration":319.7,"coverageStatus":"over_275","routeCacheKey":"route-v1|https://routing.openstreetmap.de/routed-foot|foot|494238c8-056a-537e-92b0-f73c5a199757|52.726298|4.749783|WH04|52.726813|4.744852","routeGeometry":[[52.726379,4.749744],[52.726204,4.748766],[52.726113,4.748806],[52.726099,4.748761],[52.72614,4.748207],[52.726319,4.748247],[52.726373,4.746633],[52.726416,4.746617],[52.726604,4.746314],[52.726696,4.746246],[52.72668,4.745977],[52.726713,4.745926],[52.726702,4.74577],[52.726757,4.745791],[52.726804,4.745082],[52.726792,4.744848]],"routeError":null}],"straightDistance":148,"walkingDistance":147.3,"walkingDuration":117.8,"coverageStatus":"between_125_150","analysisError":null},{"id":"5e74902b-e11e-5b8d-bca3-a394b1beb5c5","address":"Heerlijkheid 27","postcode":"1749LA","city":"Warmenhuizen","lat":52.7261653532317,"lon":4.749689059600813,"nearestContainerId":"WH06","nearestContainerAddress":"Soeverein 2","nearestContainerAccuracy":"hvc import (exacte locatie)","nearestContainers":[{"id":"WH06","address":"Soeverein 2","accuracy":"hvc import (exacte locatie)","type":"rest","status":"existing","straightDistance":163.9,"walkingDistance":175,"walkingDuration":139.9,"coverageStatus":"between_150_275","routeCacheKey":"route-v1|https://routing.openstreetmap.de/routed-foot|foot|5e74902b-e11e-5b8d-bca3-a394b1beb5c5|52.726165|4.749689|WH06|52.727578|4.750383","routeGeometry":[[52.726172,4.74961],[52.726363,4.749656],[52.726417,4.749962],[52.727589,4.750259]],"routeError":null},{"id":"WH05","address":"Kuipersven 36","accuracy":"hvc import (exacte locatie)","type":"rest","status":"existing","straightDistance":114.2,"walkingDistance":212.3,"walkingDuration":169.7,"coverageStatus":"between_150_275","routeCacheKey":"route-v1|https://routing.openstreetmap.de/routed-foot|foot|5e74902b-e11e-5b8d-bca3-a394b1beb5c5|52.726165|4.749689|WH05|52.726883|4.748476","routeGeometry":[[52.726172,4.74961],[52.726223,4.749622],[52.726183,4.749402],[52.726307,4.749341],[52.726204,4.748766],[52.726113,4.748806],[52.726099,4.748761],[52.72614,4.748207],[52.726891,4.748392]],"routeError":null},{"id":"WH04","address":"Maasweid 1","accuracy":"handmatig bepaald (zeer hoog, onzekerheid -1 m)","type":"rest","status":"new","straightDistance":333.6,"walkingDistance":407.2,"walkingDuration":325.6,"coverageStatus":"over_275","routeCacheKey":"route-v1|https://routing.openstreetmap.de/routed-foot|foot|5e74902b-e11e-5b8d-bca3-a394b1beb5c5|52.726165|4.749689|WH04|52.726813|4.744852","routeGeometry":[[52.726172,4.74961],[52.726223,4.749622],[52.726183,4.749402],[52.726307,4.749341],[52.726204,4.748766],[52.726113,4.748806],[52.726099,4.748761],[52.72614,4.748207],[52.726319,4.748247],[52.726373,4.746633],[52.726416,4.746617],[52.726604,4.746314],[52.726696,4.746246],[52.72668,4.745977],[52.726713,4.745926],[52.726702,4.74577],[52.726757,4.745791],[52.726804,4.745082],[52.726792,4.744848]],"routeError":null}],"straightDistance":163.9,"walkingDistance":175,"walkingDuration":139.9,"coverageStatus":"between_150_275","analysisError":null},{"id":"5f117f58-c48a-5d5e-b2b9-31c75cf1865b","address":"Heerlijkheid 28","postcode":"1749LA","city":"Warmenhuizen","lat":52.7262472960099,"lon":4.749769373470808,"nearestContainerId":"WH06","nearestContainerAddress":"Soeverein 2","nearestContainerAccuracy":"hvc import (exacte locatie)","nearestContainers":[{"id":"WH06","address":"Soeverein 2","accuracy":"hvc import (exacte locatie)","type":"rest","status":"existing","straightDistance":153.6,"walkingDistance":165.2,"walkingDuration":132.1,"coverageStatus":"between_150_275","routeCacheKey":"route-v1|https://routing.openstreetmap.de/routed-foot|foot|5f117f58-c48a-5d5e-b2b9-31c75cf1865b|52.726247|4.749769|WH06|52.727578|4.750383","routeGeometry":[[52.726259,4.749631],[52.726363,4.749656],[52.726417,4.749962],[52.727589,4.750259]],"routeError":null},{"id":"WH05","address":"Kuipersven 36","accuracy":"hvc import (exacte locatie)","type":"rest","status":"existing","straightDistance":112.2,"walkingDistance":210.6,"walkingDuration":168.3,"coverageStatus":"between_150_275","routeCacheKey":"route-v1|https://routing.openstreetmap.de/routed-foot|foot|5f117f58-c48a-5d5e-b2b9-31c75cf1865b|52.726247|4.749769|WH05|52.726883|4.748476","routeGeometry":[[52.726259,4.749631],[52.726223,4.749622],[52.726183,4.749402],[52.726307,4.749341],[52.726204,4.748766],[52.726113,4.748806],[52.726099,4.748761],[52.72614,4.748207],[52.726891,4.748392]],"routeError":null},{"id":"WH04","address":"Maasweid 1","accuracy":"handmatig bepaald (zeer hoog, onzekerheid -1 m)","type":"rest","status":"new","straightDistance":337.1,"walkingDistance":405.5,"walkingDuration":324.2,"coverageStatus":"over_275","routeCacheKey":"route-v1|https://routing.openstreetmap.de/routed-foot|foot|5f117f58-c48a-5d5e-b2b9-31c75cf1865b|52.726247|4.749769|WH04|52.726813|4.744852","routeGeometry":[[52.726259,4.749631],[52.726223,4.749622],[52.726183,4.749402],[52.726307,4.749341],[52.726204,4.748766],[52.726113,4.748806],[52.726099,4.748761],[52.72614,4.748207],[52.726319,4.748247],[52.726373,4.746633],[52.726416,4.746617],[52.726604,4.746314],[52.726696,4.746246],[52.72668,4.745977],[52.726713,4.745926],[52.726702,4.74577],[52.726757,4.745791],[52.726804,4.745082],[52.726792,4.744848]],"routeError":null}],"straightDistance":153.6,"walkingDistance":165.2,"walkingDuration":132.1,"coverageStatus":"between_150_275","analysisError":null},{"id":"5b342c3c-c04d-592e-9767-006bc40232e2","address":"Heerlijkheid 30","postcode":"1749LA","city":"Warmenhuizen","lat":52.72620662432302,"lon":4.749760016704834,"nearestContainerId":"WH06","nearestContainerAddress":"Soeverein 2","nearestContainerAccuracy":"hvc import (exacte locatie)","nearestContainers":[{"id":"WH06","address":"Soeverein 2","accuracy":"hvc import (exacte locatie)","type":"rest","status":"existing","straightDistance":158.2,"walkingDistance":169.2,"walkingDuration":135.3,"coverageStatus":"between_150_275","routeCacheKey":"route-v1|https://routing.openstreetmap.de/routed-foot|foot|5b342c3c-c04d-592e-9767-006bc40232e2|52.726207|4.749760|WH06|52.727578|4.750383","routeGeometry":[[52.726223,4.749622],[52.726363,4.749656],[52.726417,4.749962],[52.727589,4.750259]],"routeError":null},{"id":"WH05","address":"Kuipersven 36","accuracy":"hvc import (exacte locatie)","type":"rest","status":"existing","straightDistance":114.6,"walkingDistance":206.5,"walkingDuration":165.1,"coverageStatus":"between_150_275","routeCacheKey":"route-v1|https://routing.openstreetmap.de/routed-foot|foot|5b342c3c-c04d-592e-9767-006bc40232e2|52.726207|4.749760|WH05|52.726883|4.748476","routeGeometry":[[52.726223,4.749622],[52.726183,4.749402],[52.726307,4.749341],[52.726204,4.748766],[52.726113,4.748806],[52.726099,4.748761],[52.72614,4.748207],[52.726891,4.748392]],"routeError":null},{"id":"WH04","address":"Maasweid 1","accuracy":"handmatig bepaald (zeer hoog, onzekerheid -1 m)","type":"rest","status":"new","straightDistance":337.3,"walkingDistance":401.5,"walkingDuration":321,"coverageStatus":"over_275","routeCacheKey":"route-v1|https://routing.openstreetmap.de/routed-foot|foot|5b342c3c-c04d-592e-9767-006bc40232e2|52.726207|4.749760|WH04|52.726813|4.744852","routeGeometry":[[52.726223,4.749622],[52.726183,4.749402],[52.726307,4.749341],[52.726204,4.748766],[52.726113,4.748806],[52.726099,4.748761],[52.72614,4.748207],[52.726319,4.748247],[52.726373,4.746633],[52.726416,4.746617],[52.726604,4.746314],[52.726696,4.746246],[52.72668,4.745977],[52.726713,4.745926],[52.726702,4.74577],[52.726757,4.745791],[52.726804,4.745082],[52.726792,4.744848]],"routeError":null}],"straightDistance":158.2,"walkingDistance":169.2,"walkingDuration":135.3,"coverageStatus":"between_150_275","analysisError":null},{"id":"01ea44cd-6000-5eb6-8d9c-b45d292e3965","address":"Heerlijkheid 32","postcode":"1749LA","city":"Warmenhuizen","lat":52.72616071218119,"lon":4.749748796907193,"nearestContainerId":"WH06","nearestContainerAddress":"Soeverein 2","nearestContainerAccuracy":"hvc import (exacte locatie)","nearestContainers":[{"id":"WH06","address":"Soeverein 2","accuracy":"hvc import (exacte locatie)","type":"rest","status":"existing","straightDistance":163.3,"walkingDistance":174.9,"walkingDuration":139.8,"coverageStatus":"between_150_275","routeCacheKey":"route-v1|https://routing.openstreetmap.de/routed-foot|foot|01ea44cd-6000-5eb6-8d9c-b45d292e3965|52.726161|4.749749|WH06|52.727578|4.750383","routeGeometry":[[52.726173,4.74961],[52.726363,4.749656],[52.726417,4.749962],[52.727589,4.750259]],"routeError":null},{"id":"WH05","address":"Kuipersven 36","accuracy":"hvc import (exacte locatie)","type":"rest","status":"existing","straightDistance":117.5,"walkingDistance":212.2,"walkingDuration":169.6,"coverageStatus":"between_150_275","routeCacheKey":"route-v1|https://routing.openstreetmap.de/routed-foot|foot|01ea44cd-6000-5eb6-8d9c-b45d292e3965|52.726161|4.749749|WH05|52.726883|4.748476","routeGeometry":[[52.726173,4.74961],[52.726223,4.749622],[52.726183,4.749402],[52.726307,4.749341],[52.726204,4.748766],[52.726113,4.748806],[52.726099,4.748761],[52.72614,4.748207],[52.726891,4.748392]],"routeError":null},{"id":"WH04","address":"Maasweid 1","accuracy":"handmatig bepaald (zeer hoog, onzekerheid -1 m)","type":"rest","status":"new","straightDistance":337.6,"walkingDistance":407.1,"walkingDuration":325.5,"coverageStatus":"over_275","routeCacheKey":"route-v1|https://routing.openstreetmap.de/routed-foot|foot|01ea44cd-6000-5eb6-8d9c-b45d292e3965|52.726161|4.749749|WH04|52.726813|4.744852","routeGeometry":[[52.726173,4.74961],[52.726223,4.749622],[52.726183,4.749402],[52.726307,4.749341],[52.726204,4.748766],[52.726113,4.748806],[52.726099,4.748761],[52.72614,4.748207],[52.726319,4.748247],[52.726373,4.746633],[52.726416,4.746617],[52.726604,4.746314],[52.726696,4.746246],[52.72668,4.745977],[52.726713,4.745926],[52.726702,4.74577],[52.726757,4.745791],[52.726804,4.745082],[52.726792,4.744848]],"routeError":null}],"straightDistance":163.3,"walkingDistance":174.9,"walkingDuration":139.8,"coverageStatus":"between_150_275","analysisError":null},{"id":"80dac209-b794-57bc-80bf-70a4418d24c2","address":"Heerlijkheid 34","postcode":"1749LA","city":"Warmenhuizen","lat":52.72594562395827,"lon":4.7496849238842405,"nearestContainerId":"WH06","nearestContainerAddress":"Soeverein 2","nearestContainerAccuracy":"hvc import (exacte locatie)","nearestContainers":[{"id":"WH06","address":"Soeverein 2","accuracy":"hvc import (exacte locatie)","type":"rest","status":"existing","straightDistance":187.5,"walkingDistance":187.5,"walkingDuration":150,"coverageStatus":"between_150_275","routeCacheKey":"route-v1|https://routing.openstreetmap.de/routed-foot|foot|80dac209-b794-57bc-80bf-70a4418d24c2|52.725946|4.749685|WH06|52.727578|4.750383","routeGeometry":[[52.726028,4.749705],[52.726015,4.749854],[52.727589,4.750259]],"routeError":null},{"id":"WH05","address":"Kuipersven 36","accuracy":"hvc import (exacte locatie)","type":"rest","status":"existing","straightDistance":132.3,"walkingDistance":213.6,"walkingDuration":170.8,"coverageStatus":"between_150_275","routeCacheKey":"route-v1|https://routing.openstreetmap.de/routed-foot|foot|80dac209-b794-57bc-80bf-70a4418d24c2|52.725946|4.749685|WH05|52.726883|4.748476","routeGeometry":[[52.726028,4.749705],[52.726087,4.749053],[52.726242,4.748978],[52.726204,4.748766],[52.726113,4.748806],[52.726099,4.748761],[52.72614,4.748207],[52.726891,4.748392]],"routeError":null},{"id":"WH04","address":"Maasweid 1","accuracy":"handmatig bepaald (zeer hoog, onzekerheid -1 m)","type":"rest","status":"new","straightDistance":339.4,"walkingDistance":408.5,"walkingDuration":326.7,"coverageStatus":"over_275","routeCacheKey":"route-v1|https://routing.openstreetmap.de/routed-foot|foot|80dac209-b794-57bc-80bf-70a4418d24c2|52.725946|4.749685|WH04|52.726813|4.744852","routeGeometry":[[52.726028,4.749705],[52.726087,4.749053],[52.726242,4.748978],[52.726204,4.748766],[52.726113,4.748806],[52.726099,4.748761],[52.72614,4.748207],[52.726319,4.748247],[52.726373,4.746633],[52.726416,4.746617],[52.726604,4.746314],[52.726696,4.746246],[52.72668,4.745977],[52.726713,4.745926],[52.726702,4.74577],[52.726757,4.745791],[52.726804,4.745082],[52.726792,4.744848]],"routeError":null}],"straightDistance":187.5,"walkingDistance":187.5,"walkingDuration":150,"coverageStatus":"between_150_275","analysisError":null},{"id":"11065e69-4665-51a9-87b8-09f294244f04","address":"Heerlijkheid 36","postcode":"1749LA","city":"Warmenhuizen","lat":52.72594809744255,"lon":4.7496114518582555,"nearestContainerId":"WH05","nearestContainerAddress":"Kuipersven 36","nearestContainerAccuracy":"hvc import (exacte locatie)","nearestContainers":[{"id":"WH05","address":"Kuipersven 36","accuracy":"hvc import (exacte locatie)","type":"rest","status":"existing","straightDistance":129,"walkingDistance":192.7,"walkingDuration":154.2,"coverageStatus":"between_150_275","routeCacheKey":"route-v1|https://routing.openstreetmap.de/routed-foot|foot|11065e69-4665-51a9-87b8-09f294244f04|52.725948|4.749611|WH05|52.726883|4.748476","routeGeometry":[[52.725862,4.74959],[52.725933,4.748841],[52.726099,4.748761],[52.72614,4.748207],[52.726891,4.748392]],"routeError":null},{"id":"WH06","address":"Soeverein 2","accuracy":"hvc import (exacte locatie)","type":"rest","status":"existing","straightDistance":188.5,"walkingDistance":211.7,"walkingDuration":169.4,"coverageStatus":"between_150_275","routeCacheKey":"route-v1|https://routing.openstreetmap.de/routed-foot|foot|11065e69-4665-51a9-87b8-09f294244f04|52.725948|4.749611|WH06|52.727578|4.750383","routeGeometry":[[52.725862,4.74959],[52.725842,4.749808],[52.727589,4.750259]],"routeError":null},{"id":"WH04","address":"Maasweid 1","accuracy":"handmatig bepaald (zeer hoog, onzekerheid -1 m)","type":"rest","status":"new","straightDistance":334.6,"walkingDistance":387.6,"walkingDuration":310.1,"coverageStatus":"over_275","routeCacheKey":"route-v1|https://routing.openstreetmap.de/routed-foot|foot|11065e69-4665-51a9-87b8-09f294244f04|52.725948|4.749611|WH04|52.726813|4.744852","routeGeometry":[[52.725862,4.74959],[52.725933,4.748841],[52.726099,4.748761],[52.72614,4.748207],[52.726319,4.748247],[52.726373,4.746633],[52.726416,4.746617],[52.726604,4.746314],[52.726696,4.746246],[52.72668,4.745977],[52.726713,4.745926],[52.726702,4.74577],[52.726757,4.745791],[52.726804,4.745082],[52.726792,4.744848]],"routeError":null}],"straightDistance":129,"walkingDistance":192.7,"walkingDuration":154.2,"coverageStatus":"between_150_275","analysisError":null},{"id":"cb46eb16-31ba-5b87-a7cd-f95ef55307d2","address":"Heerlijkheid 38","postcode":"1749LA","city":"Warmenhuizen","lat":52.725963470531845,"lon":4.749469774068369,"nearestContainerId":"WH06","nearestContainerAddress":"Soeverein 2","nearestContainerAccuracy":"hvc import (exacte locatie)","nearestContainers":[{"id":"WH06","address":"Soeverein 2","accuracy":"hvc import (exacte locatie)","type":"rest","status":"existing","straightDistance":189.8,"walkingDistance":195.8,"walkingDuration":156.5,"coverageStatus":"between_150_275","routeCacheKey":"route-v1|https://routing.openstreetmap.de/routed-foot|foot|cb46eb16-31ba-5b87-a7cd-f95ef55307d2|52.725963|4.749470|WH06|52.727578|4.750383","routeGeometry":[[52.726048,4.749491],[52.72604,4.749578],[52.726363,4.749656],[52.726417,4.749962],[52.727589,4.750259]],"routeError":null},{"id":"WH05","address":"Kuipersven 36","accuracy":"hvc import (exacte locatie)","type":"rest","status":"existing","straightDistance":122.2,"walkingDistance":198.9,"walkingDuration":159.2,"coverageStatus":"between_150_275","routeCacheKey":"route-v1|https://routing.openstreetmap.de/routed-foot|foot|cb46eb16-31ba-5b87-a7cd-f95ef55307d2|52.725963|4.749470|WH05|52.726883|4.748476","routeGeometry":[[52.726048,4.749491],[52.726087,4.749053],[52.726242,4.748978],[52.726204,4.748766],[52.726113,4.748806],[52.726099,4.748761],[52.72614,4.748207],[52.726891,4.748392]],"routeError":null},{"id":"WH04","address":"Maasweid 1","accuracy":"handmatig bepaald (zeer hoog, onzekerheid -1 m)","type":"rest","status":"new","straightDistance":325,"walkingDistance":393.9,"walkingDuration":315.1,"coverageStatus":"over_275","routeCacheKey":"route-v1|https://routing.openstreetmap.de/routed-foot|foot|cb46eb16-31ba-5b87-a7cd-f95ef55307d2|52.725963|4.749470|WH04|52.726813|4.744852","routeGeometry":[[52.726048,4.749491],[52.726087,4.749053],[52.726242,4.748978],[52.726204,4.748766],[52.726113,4.748806],[52.726099,4.748761],[52.72614,4.748207],[52.726319,4.748247],[52.726373,4.746633],[52.726416,4.746617],[52.726604,4.746314],[52.726696,4.746246],[52.72668,4.745977],[52.726713,4.745926],[52.726702,4.74577],[52.726757,4.745791],[52.726804,4.745082],[52.726792,4.744848]],"routeError":null}],"straightDistance":189.8,"walkingDistance":195.8,"walkingDuration":156.5,"coverageStatus":"between_150_275","analysisError":null},{"id":"5ae5d286-a33a-5def-b22c-b83fd64f885c","address":"Heerlijkheid 40","postcode":"1749LA","city":"Warmenhuizen","lat":52.72597020527838,"lon":4.749394907832987,"nearestContainerId":"WH05","nearestContainerAddress":"Kuipersven 36","nearestContainerAccuracy":"hvc import (exacte locatie)","nearestContainers":[{"id":"WH05","address":"Kuipersven 36","accuracy":"hvc import (exacte locatie)","type":"rest","status":"existing","straightDistance":118.9,"walkingDistance":193.8,"walkingDuration":155.1,"coverageStatus":"between_150_275","routeCacheKey":"route-v1|https://routing.openstreetmap.de/routed-foot|foot|5ae5d286-a33a-5def-b22c-b83fd64f885c|52.725970|4.749395|WH05|52.726883|4.748476","routeGeometry":[[52.726055,4.749416],[52.726087,4.749053],[52.726242,4.748978],[52.726204,4.748766],[52.726113,4.748806],[52.726099,4.748761],[52.72614,4.748207],[52.726891,4.748392]],"routeError":null},{"id":"WH06","address":"Soeverein 2","accuracy":"hvc import (exacte locatie)","type":"rest","status":"existing","straightDistance":190.8,"walkingDistance":200.9,"walkingDuration":160.6,"coverageStatus":"between_150_275","routeCacheKey":"route-v1|https://routing.openstreetmap.de/routed-foot|foot|5ae5d286-a33a-5def-b22c-b83fd64f885c|52.725970|4.749395|WH06|52.727578|4.750383","routeGeometry":[[52.726055,4.749416],[52.72604,4.749578],[52.726363,4.749656],[52.726417,4.749962],[52.727589,4.750259]],"routeError":null},{"id":"WH04","address":"Maasweid 1","accuracy":"handmatig bepaald (zeer hoog, onzekerheid -1 m)","type":"rest","status":"new","straightDistance":320,"walkingDistance":388.8,"walkingDuration":311,"coverageStatus":"over_275","routeCacheKey":"route-v1|https://routing.openstreetmap.de/routed-foot|foot|5ae5d286-a33a-5def-b22c-b83fd64f885c|52.725970|4.749395|WH04|52.726813|4.744852","routeGeometry":[[52.726055,4.749416],[52.726087,4.749053],[52.726242,4.748978],[52.726204,4.748766],[52.726113,4.748806],[52.726099,4.748761],[52.72614,4.748207],[52.726319,4.748247],[52.726373,4.746633],[52.726416,4.746617],[52.726604,4.746314],[52.726696,4.746246],[52.72668,4.745977],[52.726713,4.745926],[52.726702,4.74577],[52.726757,4.745791],[52.726804,4.745082],[52.726792,4.744848]],"routeError":null}],"straightDistance":118.9,"walkingDistance":193.8,"walkingDuration":155.1,"coverageStatus":"between_150_275","analysisError":null},{"id":"6776a982-6ef6-5eaa-b53d-ad97e44919c9","address":"Heerlijkheid 42","postcode":"1749LA","city":"Warmenhuizen","lat":52.7259762319572,"lon":4.749325440044217,"nearestContainerId":"WH05","nearestContainerAddress":"Kuipersven 36","nearestContainerAccuracy":"hvc import (exacte locatie)","nearestContainers":[{"id":"WH05","address":"Kuipersven 36","accuracy":"hvc import (exacte locatie)","type":"rest","status":"existing","straightDistance":115.9,"walkingDistance":189,"walkingDuration":151.3,"coverageStatus":"between_150_275","routeCacheKey":"route-v1|https://routing.openstreetmap.de/routed-foot|foot|6776a982-6ef6-5eaa-b53d-ad97e44919c9|52.725976|4.749325|WH05|52.726883|4.748476","routeGeometry":[[52.726061,4.749346],[52.726087,4.749053],[52.726242,4.748978],[52.726204,4.748766],[52.726113,4.748806],[52.726099,4.748761],[52.72614,4.748207],[52.726891,4.748392]],"routeError":null},{"id":"WH06","address":"Soeverein 2","accuracy":"hvc import (exacte locatie)","type":"rest","status":"existing","straightDistance":191.8,"walkingDistance":205.7,"walkingDuration":164.4,"coverageStatus":"between_150_275","routeCacheKey":"route-v1|https://routing.openstreetmap.de/routed-foot|foot|6776a982-6ef6-5eaa-b53d-ad97e44919c9|52.725976|4.749325|WH06|52.727578|4.750383","routeGeometry":[[52.726061,4.749346],[52.72604,4.749578],[52.726363,4.749656],[52.726417,4.749962],[52.727589,4.750259]],"routeError":null},{"id":"WH04","address":"Maasweid 1","accuracy":"handmatig bepaald (zeer hoog, onzekerheid -1 m)","type":"rest","status":"new","straightDistance":315.3,"walkingDistance":384,"walkingDuration":307.2,"coverageStatus":"over_275","routeCacheKey":"route-v1|https://routing.openstreetmap.de/routed-foot|foot|6776a982-6ef6-5eaa-b53d-ad97e44919c9|52.725976|4.749325|WH04|52.726813|4.744852","routeGeometry":[[52.726061,4.749346],[52.726087,4.749053],[52.726242,4.748978],[52.726204,4.748766],[52.726113,4.748806],[52.726099,4.748761],[52.72614,4.748207],[52.726319,4.748247],[52.726373,4.746633],[52.726416,4.746617],[52.726604,4.746314],[52.726696,4.746246],[52.72668,4.745977],[52.726713,4.745926],[52.726702,4.74577],[52.726757,4.745791],[52.726804,4.745082],[52.726792,4.744848]],"routeError":null}],"straightDistance":115.9,"walkingDistance":189,"walkingDuration":151.3,"coverageStatus":"between_150_275","analysisError":null},{"id":"4937b3ba-81ca-51ed-838f-8c4a25944a30","address":"Heerlijkheid 44","postcode":"1749LA","city":"Warmenhuizen","lat":52.72598303940149,"lon":4.749249062832631,"nearestContainerId":"WH05","nearestContainerAddress":"Kuipersven 36","nearestContainerAccuracy":"hvc import (exacte locatie)","nearestContainers":[{"id":"WH05","address":"Kuipersven 36","accuracy":"hvc import (exacte locatie)","type":"rest","status":"existing","straightDistance":112.8,"walkingDistance":168.4,"walkingDuration":134.8,"coverageStatus":"between_150_275","routeCacheKey":"route-v1|https://routing.openstreetmap.de/routed-foot|foot|4937b3ba-81ca-51ed-838f-8c4a25944a30|52.725983|4.749249|WH05|52.726883|4.748476","routeGeometry":[[52.725959,4.749115],[52.725904,4.749142],[52.725933,4.748841],[52.726099,4.748761],[52.72614,4.748207],[52.726891,4.748392]],"routeError":null},{"id":"WH06","address":"Soeverein 2","accuracy":"hvc import (exacte locatie)","type":"rest","status":"existing","straightDistance":193.1,"walkingDistance":228.6,"walkingDuration":182.7,"coverageStatus":"between_150_275","routeCacheKey":"route-v1|https://routing.openstreetmap.de/routed-foot|foot|4937b3ba-81ca-51ed-838f-8c4a25944a30|52.725983|4.749249|WH06|52.727578|4.750383","routeGeometry":[[52.725959,4.749115],[52.726116,4.749039],[52.726223,4.749622],[52.726363,4.749656],[52.726417,4.749962],[52.727589,4.750259]],"routeError":null},{"id":"WH04","address":"Maasweid 1","accuracy":"handmatig bepaald (zeer hoog, onzekerheid -1 m)","type":"rest","status":"new","straightDistance":310.2,"walkingDistance":363.4,"walkingDuration":290.7,"coverageStatus":"over_275","routeCacheKey":"route-v1|https://routing.openstreetmap.de/routed-foot|foot|4937b3ba-81ca-51ed-838f-8c4a25944a30|52.725983|4.749249|WH04|52.726813|4.744852","routeGeometry":[[52.725959,4.749115],[52.725904,4.749142],[52.725933,4.748841],[52.726099,4.748761],[52.72614,4.748207],[52.726319,4.748247],[52.726373,4.746633],[52.726416,4.746617],[52.726604,4.746314],[52.726696,4.746246],[52.72668,4.745977],[52.726713,4.745926],[52.726702,4.74577],[52.726757,4.745791],[52.726804,4.745082],[52.726792,4.744848]],"routeError":null}],"straightDistance":112.8,"walkingDistance":168.4,"walkingDuration":134.8,"coverageStatus":"between_150_275","analysisError":null},{"id":"63d1e021-093b-548c-86b8-c494319e1768","address":"Heerlijkheid 46","postcode":"1749LA","city":"Warmenhuizen","lat":52.72603165381627,"lon":4.748936078252956,"nearestContainerId":"WH05","nearestContainerAddress":"Kuipersven 36","nearestContainerAccuracy":"hvc import (exacte locatie)","nearestContainers":[{"id":"WH05","address":"Kuipersven 36","accuracy":"hvc import (exacte locatie)","type":"rest","status":"existing","straightDistance":99.6,"walkingDistance":132.6,"walkingDuration":106.1,"coverageStatus":"between_125_150","routeCacheKey":"route-v1|https://routing.openstreetmap.de/routed-foot|foot|63d1e021-093b-548c-86b8-c494319e1768|52.726032|4.748936|WH05|52.726883|4.748476","routeGeometry":[[52.726009,4.748804],[52.726099,4.748761],[52.72614,4.748207],[52.726891,4.748392]],"routeError":null},{"id":"WH06","address":"Soeverein 2","accuracy":"hvc import (exacte locatie)","type":"rest","status":"existing","straightDistance":197.6,"walkingDistance":240.5,"walkingDuration":192.1,"coverageStatus":"between_150_275","routeCacheKey":"route-v1|https://routing.openstreetmap.de/routed-foot|foot|63d1e021-093b-548c-86b8-c494319e1768|52.726032|4.748936|WH06|52.727578|4.750383","routeGeometry":[[52.726009,4.748804],[52.726204,4.748766],[52.726417,4.749962],[52.727589,4.750259]],"routeError":null},{"id":"WH04","address":"Maasweid 1","accuracy":"handmatig bepaald (zeer hoog, onzekerheid -1 m)","type":"rest","status":"new","straightDistance":288.4,"walkingDistance":327.6,"walkingDuration":262,"coverageStatus":"over_275","routeCacheKey":"route-v1|https://routing.openstreetmap.de/routed-foot|foot|63d1e021-093b-548c-86b8-c494319e1768|52.726032|4.748936|WH04|52.726813|4.744852","routeGeometry":[[52.726009,4.748804],[52.726099,4.748761],[52.72614,4.748207],[52.726319,4.748247],[52.726373,4.746633],[52.726416,4.746617],[52.726604,4.746314],[52.726696,4.746246],[52.72668,4.745977],[52.726713,4.745926],[52.726702,4.74577],[52.726757,4.745791],[52.726804,4.745082],[52.726792,4.744848]],"routeError":null}],"straightDistance":99.6,"walkingDistance":132.6,"walkingDuration":106.1,"coverageStatus":"between_125_150","analysisError":null},{"id":"e6927be6-e722-5d13-bfc4-0c160f8dfd3b","address":"Heerlijkheid 48","postcode":"1749LA","city":"Warmenhuizen","lat":52.72607952788171,"lon":4.7489125858515955,"nearestContainerId":"WH05","nearestContainerAddress":"Kuipersven 36","nearestContainerAccuracy":"hvc import (exacte locatie)","nearestContainers":[{"id":"WH05","address":"Kuipersven 36","accuracy":"hvc import (exacte locatie)","type":"rest","status":"existing","straightDistance":94.1,"walkingDistance":125.6,"walkingDuration":100.5,"coverageStatus":"between_125_150","routeCacheKey":"route-v1|https://routing.openstreetmap.de/routed-foot|foot|e6927be6-e722-5d13-bfc4-0c160f8dfd3b|52.726080|4.748913|WH05|52.726883|4.748476","routeGeometry":[[52.726113,4.748806],[52.726099,4.748761],[52.72614,4.748207],[52.726891,4.748392]],"routeError":null},{"id":"WH06","address":"Soeverein 2","accuracy":"hvc import (exacte locatie)","type":"rest","status":"existing","straightDistance":193.8,"walkingDistance":226.7,"walkingDuration":181.1,"coverageStatus":"between_150_275","routeCacheKey":"route-v1|https://routing.openstreetmap.de/routed-foot|foot|e6927be6-e722-5d13-bfc4-0c160f8dfd3b|52.726080|4.748913|WH06|52.727578|4.750383","routeGeometry":[[52.726113,4.748806],[52.726204,4.748766],[52.726417,4.749962],[52.727589,4.750259]],"routeError":null},{"id":"WH04","address":"Maasweid 1","accuracy":"handmatig bepaald (zeer hoog, onzekerheid -1 m)","type":"rest","status":"new","straightDistance":285.4,"walkingDistance":320.6,"walkingDuration":256.4,"coverageStatus":"over_275","routeCacheKey":"route-v1|https://routing.openstreetmap.de/routed-foot|foot|e6927be6-e722-5d13-bfc4-0c160f8dfd3b|52.726080|4.748913|WH04|52.726813|4.744852","routeGeometry":[[52.726113,4.748806],[52.726099,4.748761],[52.72614,4.748207],[52.726319,4.748247],[52.726373,4.746633],[52.726416,4.746617],[52.726604,4.746314],[52.726696,4.746246],[52.72668,4.745977],[52.726713,4.745926],[52.726702,4.74577],[52.726757,4.745791],[52.726804,4.745082],[52.726792,4.744848]],"routeError":null}],"straightDistance":94.1,"walkingDistance":125.6,"walkingDuration":100.5,"coverageStatus":"between_125_150","analysisError":null},{"id":"fcb2cbf0-76f8-51f9-a81d-6d2f0c162ba3","address":"Heerlijkheid 50","postcode":"1749LA","city":"Warmenhuizen","lat":52.726124782063806,"lon":4.748894934175439,"nearestContainerId":"WH05","nearestContainerAddress":"Kuipersven 36","nearestContainerAccuracy":"hvc import (exacte locatie)","nearestContainers":[{"id":"WH05","address":"Kuipersven 36","accuracy":"hvc import (exacte locatie)","type":"rest","status":"existing","straightDistance":88.9,"walkingDistance":125.6,"walkingDuration":100.5,"coverageStatus":"between_125_150","routeCacheKey":"route-v1|https://routing.openstreetmap.de/routed-foot|foot|fcb2cbf0-76f8-51f9-a81d-6d2f0c162ba3|52.726125|4.748895|WH05|52.726883|4.748476","routeGeometry":[[52.726113,4.748806],[52.726099,4.748761],[52.72614,4.748207],[52.726891,4.748392]],"routeError":null},{"id":"WH06","address":"Soeverein 2","accuracy":"hvc import (exacte locatie)","type":"rest","status":"existing","straightDistance":190.1,"walkingDistance":226.7,"walkingDuration":181.1,"coverageStatus":"between_150_275","routeCacheKey":"route-v1|https://routing.openstreetmap.de/routed-foot|foot|fcb2cbf0-76f8-51f9-a81d-6d2f0c162ba3|52.726125|4.748895|WH06|52.727578|4.750383","routeGeometry":[[52.726113,4.748806],[52.726204,4.748766],[52.726417,4.749962],[52.727589,4.750259]],"routeError":null},{"id":"WH04","address":"Maasweid 1","accuracy":"handmatig bepaald (zeer hoog, onzekerheid -1 m)","type":"rest","status":"new","straightDistance":282.8,"walkingDistance":320.6,"walkingDuration":256.4,"coverageStatus":"over_275","routeCacheKey":"route-v1|https://routing.openstreetmap.de/routed-foot|foot|fcb2cbf0-76f8-51f9-a81d-6d2f0c162ba3|52.726125|4.748895|WH04|52.726813|4.744852","routeGeometry":[[52.726113,4.748806],[52.726099,4.748761],[52.72614,4.748207],[52.726319,4.748247],[52.726373,4.746633],[52.726416,4.746617],[52.726604,4.746314],[52.726696,4.746246],[52.72668,4.745977],[52.726713,4.745926],[52.726702,4.74577],[52.726757,4.745791],[52.726804,4.745082],[52.726792,4.744848]],"routeError":null}],"straightDistance":88.9,"walkingDistance":125.6,"walkingDuration":100.5,"coverageStatus":"between_125_150","analysisError":null},{"id":"9b070c62-fcae-53a7-896a-91f5e676ff01","address":"Heerlijkheid 52","postcode":"1749LA","city":"Warmenhuizen","lat":52.72615744144584,"lon":4.748873202445962,"nearestContainerId":"WH05","nearestContainerAddress":"Kuipersven 36","nearestContainerAccuracy":"hvc import (exacte locatie)","nearestContainers":[{"id":"WH05","address":"Kuipersven 36","accuracy":"hvc import (exacte locatie)","type":"rest","status":"existing","straightDistance":85,"walkingDistance":129.2,"walkingDuration":103.3,"coverageStatus":"between_125_150","routeCacheKey":"route-v1|https://routing.openstreetmap.de/routed-foot|foot|9b070c62-fcae-53a7-896a-91f5e676ff01|52.726157|4.748873|WH05|52.726883|4.748476","routeGeometry":[[52.726144,4.748792],[52.726113,4.748806],[52.726099,4.748761],[52.72614,4.748207],[52.726891,4.748392]],"routeError":null},{"id":"WH06","address":"Soeverein 2","accuracy":"hvc import (exacte locatie)","type":"rest","status":"existing","straightDistance":187.9,"walkingDistance":223.1,"walkingDuration":178.3,"coverageStatus":"between_150_275","routeCacheKey":"route-v1|https://routing.openstreetmap.de/routed-foot|foot|9b070c62-fcae-53a7-896a-91f5e676ff01|52.726157|4.748873|WH06|52.727578|4.750383","routeGeometry":[[52.726144,4.748792],[52.726204,4.748766],[52.726417,4.749962],[52.727589,4.750259]],"routeError":null},{"id":"WH04","address":"Maasweid 1","accuracy":"handmatig bepaald (zeer hoog, onzekerheid -1 m)","type":"rest","status":"new","straightDistance":280.4,"walkingDistance":324.2,"walkingDuration":259.2,"coverageStatus":"over_275","routeCacheKey":"route-v1|https://routing.openstreetmap.de/routed-foot|foot|9b070c62-fcae-53a7-896a-91f5e676ff01|52.726157|4.748873|WH04|52.726813|4.744852","routeGeometry":[[52.726144,4.748792],[52.726113,4.748806],[52.726099,4.748761],[52.72614,4.748207],[52.726319,4.748247],[52.726373,4.746633],[52.726416,4.746617],[52.726604,4.746314],[52.726696,4.746246],[52.72668,4.745977],[52.726713,4.745926],[52.726702,4.74577],[52.726757,4.745791],[52.726804,4.745082],[52.726792,4.744848]],"routeError":null}],"straightDistance":85,"walkingDistance":129.2,"walkingDuration":103.3,"coverageStatus":"between_125_150","analysisError":null}]}
