{"detailBundle":"kiebos","street":"Kiebos","houses":[{"id":"a91311b5-5605-5083-b589-e9764c3ec076","address":"Kiebos 1","postcode":"1749HA","city":"Warmenhuizen","lat":52.723961478196024,"lon":4.740382477613572,"nearestContainerId":"WH14","nearestContainerAddress":"Doorbraak 23","nearestContainerAccuracy":"hvc import (exacte locatie)","nearestContainers":[{"id":"WH14","address":"Doorbraak 23","accuracy":"hvc import (exacte locatie)","type":"rest","status":"existing","straightDistance":177.1,"walkingDistance":224.1,"walkingDuration":179.4,"coverageStatus":"between_150_275","routeCacheKey":"route-v1|https://routing.openstreetmap.de/routed-foot|foot|a91311b5-5605-5083-b589-e9764c3ec076|52.723961|4.740382|WH14|52.722411|4.740981","routeGeometry":[[52.724009,4.740231],[52.72382,4.740067],[52.723714,4.740079],[52.723647,4.740155],[52.722918,4.740268],[52.7229,4.74033],[52.722895,4.740918],[52.722609,4.74093],[52.722418,4.74089]],"routeError":null},{"id":"WH15","address":"Doorbraak 14","accuracy":"handmatig bepaald (zeer hoog, onzekerheid -1 m)","type":"rest","status":"new","straightDistance":223,"walkingDistance":274.4,"walkingDuration":219.4,"coverageStatus":"between_150_275","routeCacheKey":"route-v1|https://routing.openstreetmap.de/routed-foot|foot|a91311b5-5605-5083-b589-e9764c3ec076|52.723961|4.740382|WH15|52.721977|4.740861","routeGeometry":[[52.724009,4.740231],[52.72382,4.740067],[52.723714,4.740079],[52.723647,4.740155],[52.722918,4.740268],[52.7229,4.74033],[52.722895,4.740918],[52.722609,4.74093],[52.722011,4.7408],[52.722005,4.740867]],"routeError":null},{"id":"WH08","address":"Dorpsstraat 89","accuracy":"hvc import (exacte locatie)","type":"rest","status":"existing","straightDistance":186.6,"walkingDistance":294.2,"walkingDuration":235.4,"coverageStatus":"over_275","routeCacheKey":"route-v1|https://routing.openstreetmap.de/routed-foot|foot|a91311b5-5605-5083-b589-e9764c3ec076|52.723961|4.740382|WH08|52.725435|4.739056","routeGeometry":[[52.724009,4.740231],[52.724278,4.740465],[52.724387,4.740089],[52.724435,4.739825],[52.72441,4.739675],[52.724244,4.739496],[52.724305,4.739077],[52.724652,4.739147],[52.724973,4.738973],[52.725121,4.738987],[52.725206,4.738813],[52.725314,4.73881],[52.725362,4.738875],[52.725491,4.738939],[52.725478,4.739068]],"routeError":null}],"straightDistance":177.1,"walkingDistance":224.1,"walkingDuration":179.4,"coverageStatus":"between_150_275","analysisError":null},{"id":"13d23fb3-5661-5927-a693-7ed659be5b78","address":"Kiebos 2","postcode":"1749HB","city":"Warmenhuizen","lat":52.72421722481433,"lon":4.740251973145602,"nearestContainerId":"WH14","nearestContainerAddress":"Doorbraak 23","nearestContainerAccuracy":"hvc import (exacte locatie)","nearestContainers":[{"id":"WH14","address":"Doorbraak 23","accuracy":"hvc import (exacte locatie)","type":"rest","status":"existing","straightDistance":206.8,"walkingDistance":245.3,"walkingDuration":196.3,"coverageStatus":"between_150_275","routeCacheKey":"route-v1|https://routing.openstreetmap.de/routed-foot|foot|13d23fb3-5661-5927-a693-7ed659be5b78|52.724217|4.740252|WH14|52.722411|4.740981","routeGeometry":[[52.724177,4.740377],[52.72382,4.740067],[52.723714,4.740079],[52.723647,4.740155],[52.722933,4.740263],[52.722902,4.740294],[52.722895,4.740918],[52.722609,4.74093],[52.722418,4.74089]],"routeError":null},{"id":"WH08","address":"Dorpsstraat 89","accuracy":"hvc import (exacte locatie)","type":"rest","status":"existing","straightDistance":157.6,"walkingDistance":273.1,"walkingDuration":218.5,"coverageStatus":"between_150_275","routeCacheKey":"route-v1|https://routing.openstreetmap.de/routed-foot|foot|13d23fb3-5661-5927-a693-7ed659be5b78|52.724217|4.740252|WH08|52.725435|4.739056","routeGeometry":[[52.724177,4.740377],[52.724278,4.740465],[52.72443,4.73991],[52.724401,4.739644],[52.724244,4.739496],[52.724305,4.739077],[52.724652,4.739147],[52.724973,4.738973],[52.725121,4.738987],[52.725206,4.738813],[52.725314,4.73881],[52.725362,4.738875],[52.725491,4.738939],[52.725478,4.739068]],"routeError":null},{"id":"WH11","address":"Wiekeland 2","accuracy":"handmatig bepaald (zeer hoog, onzekerheid -1 m)","type":"rest","status":"new","straightDistance":244.7,"walkingDistance":285.4,"walkingDuration":228.5,"coverageStatus":"over_275","routeCacheKey":"route-v1|https://routing.openstreetmap.de/routed-foot|foot|13d23fb3-5661-5927-a693-7ed659be5b78|52.724217|4.740252|WH11|52.723809|4.743822","routeGeometry":[[52.724177,4.740377],[52.724278,4.740465],[52.724117,4.741075],[52.72414,4.741983],[52.723872,4.742005],[52.723893,4.743033],[52.723863,4.743902],[52.723803,4.743887]],"routeError":null}],"straightDistance":206.8,"walkingDistance":245.3,"walkingDuration":196.3,"coverageStatus":"between_150_275","analysisError":null},{"id":"8e68acc5-e74a-5d73-bc74-af9d618dc752","address":"Kiebos 3","postcode":"1749HA","city":"Warmenhuizen","lat":52.72391932670636,"lon":4.740345708902665,"nearestContainerId":"WH14","nearestContainerAddress":"Doorbraak 23","nearestContainerAccuracy":"hvc import (exacte locatie)","nearestContainers":[{"id":"WH14","address":"Doorbraak 23","accuracy":"hvc import (exacte locatie)","type":"rest","status":"existing","straightDistance":173.1,"walkingDistance":218.9,"walkingDuration":175.2,"coverageStatus":"between_150_275","routeCacheKey":"route-v1|https://routing.openstreetmap.de/routed-foot|foot|8e68acc5-e74a-5d73-bc74-af9d618dc752|52.723919|4.740346|WH14|52.722411|4.740981","routeGeometry":[[52.723967,4.740195],[52.72382,4.740067],[52.723714,4.740079],[52.723647,4.740155],[52.722918,4.740268],[52.7229,4.74033],[52.722895,4.740918],[52.722609,4.74093],[52.722418,4.74089]],"routeError":null},{"id":"WH15","address":"Doorbraak 14","accuracy":"handmatig bepaald (zeer hoog, onzekerheid -1 m)","type":"rest","status":"new","straightDistance":218.7,"walkingDistance":269.2,"walkingDuration":215.2,"coverageStatus":"between_150_275","routeCacheKey":"route-v1|https://routing.openstreetmap.de/routed-foot|foot|8e68acc5-e74a-5d73-bc74-af9d618dc752|52.723919|4.740346|WH15|52.721977|4.740861","routeGeometry":[[52.723967,4.740195],[52.72382,4.740067],[52.723714,4.740079],[52.723647,4.740155],[52.722918,4.740268],[52.7229,4.74033],[52.722895,4.740918],[52.722609,4.74093],[52.722011,4.7408],[52.722005,4.740867]],"routeError":null},{"id":"WH08","address":"Dorpsstraat 89","accuracy":"hvc import (exacte locatie)","type":"rest","status":"existing","straightDistance":189.6,"walkingDistance":299.5,"walkingDuration":239.6,"coverageStatus":"over_275","routeCacheKey":"route-v1|https://routing.openstreetmap.de/routed-foot|foot|8e68acc5-e74a-5d73-bc74-af9d618dc752|52.723919|4.740346|WH08|52.725435|4.739056","routeGeometry":[[52.723967,4.740195],[52.724278,4.740465],[52.724435,4.739825],[52.724401,4.739644],[52.724244,4.739496],[52.724305,4.739077],[52.724652,4.739147],[52.724973,4.738973],[52.725121,4.738987],[52.725206,4.738813],[52.725314,4.73881],[52.725362,4.738875],[52.725491,4.738939],[52.725478,4.739068]],"routeError":null}],"straightDistance":173.1,"walkingDistance":218.9,"walkingDuration":175.2,"coverageStatus":"between_150_275","analysisError":null},{"id":"ad714a42-7968-5397-9df1-67a5d7b422fd","address":"Kiebos 4","postcode":"1749HB","city":"Warmenhuizen","lat":52.72407598661131,"lon":4.740126816402118,"nearestContainerId":"WH14","nearestContainerAddress":"Doorbraak 23","nearestContainerAccuracy":"hvc import (exacte locatie)","nearestContainers":[{"id":"WH14","address":"Doorbraak 23","accuracy":"hvc import (exacte locatie)","type":"rest","status":"existing","straightDistance":193.9,"walkingDistance":227.4,"walkingDuration":182,"coverageStatus":"between_150_275","routeCacheKey":"route-v1|https://routing.openstreetmap.de/routed-foot|foot|ad714a42-7968-5397-9df1-67a5d7b422fd|52.724076|4.740127|WH14|52.722411|4.740981","routeGeometry":[[52.724035,4.740254],[52.72382,4.740067],[52.723714,4.740079],[52.723647,4.740155],[52.722918,4.740268],[52.7229,4.74033],[52.722895,4.740918],[52.722609,4.74093],[52.722418,4.74089]],"routeError":null},{"id":"WH15","address":"Doorbraak 14","accuracy":"handmatig bepaald (zeer hoog, onzekerheid -1 m)","type":"rest","status":"new","straightDistance":238.6,"walkingDistance":277.7,"walkingDuration":222,"coverageStatus":"over_275","routeCacheKey":"route-v1|https://routing.openstreetmap.de/routed-foot|foot|ad714a42-7968-5397-9df1-67a5d7b422fd|52.724076|4.740127|WH15|52.721977|4.740861","routeGeometry":[[52.724035,4.740254],[52.72382,4.740067],[52.723714,4.740079],[52.723647,4.740155],[52.722918,4.740268],[52.7229,4.74033],[52.722895,4.740918],[52.722609,4.74093],[52.722011,4.7408],[52.722005,4.740867]],"routeError":null},{"id":"WH08","address":"Dorpsstraat 89","accuracy":"hvc import (exacte locatie)","type":"rest","status":"existing","straightDistance":167.4,"walkingDistance":290.9,"walkingDuration":232.8,"coverageStatus":"over_275","routeCacheKey":"route-v1|https://routing.openstreetmap.de/routed-foot|foot|ad714a42-7968-5397-9df1-67a5d7b422fd|52.724076|4.740127|WH08|52.725435|4.739056","routeGeometry":[[52.724035,4.740254],[52.724278,4.740465],[52.72443,4.73991],[52.724401,4.739644],[52.724244,4.739496],[52.724305,4.739077],[52.724652,4.739147],[52.724973,4.738973],[52.725121,4.738987],[52.725206,4.738813],[52.725314,4.73881],[52.725362,4.738875],[52.725491,4.738939],[52.725478,4.739068]],"routeError":null}],"straightDistance":193.9,"walkingDistance":227.4,"walkingDuration":182,"coverageStatus":"between_150_275","analysisError":null},{"id":"4ea14346-56dc-5da1-8b54-2c76578d5d39","address":"Kiebos 5","postcode":"1749HA","city":"Warmenhuizen","lat":52.723881293335,"lon":4.7403126244738205,"nearestContainerId":"WH14","nearestContainerAddress":"Doorbraak 23","nearestContainerAccuracy":"hvc import (exacte locatie)","nearestContainers":[{"id":"WH14","address":"Doorbraak 23","accuracy":"hvc import (exacte locatie)","type":"rest","status":"existing","straightDistance":169.6,"walkingDistance":214.1,"walkingDuration":171.3,"coverageStatus":"between_150_275","routeCacheKey":"route-v1|https://routing.openstreetmap.de/routed-foot|foot|4ea14346-56dc-5da1-8b54-2c76578d5d39|52.723881|4.740313|WH14|52.722411|4.740981","routeGeometry":[[52.723929,4.740162],[52.72382,4.740067],[52.723714,4.740079],[52.723647,4.740155],[52.722918,4.740268],[52.7229,4.74033],[52.722895,4.740918],[52.722609,4.74093],[52.722418,4.74089]],"routeError":null},{"id":"WH15","address":"Doorbraak 14","accuracy":"handmatig bepaald (zeer hoog, onzekerheid -1 m)","type":"rest","status":"new","straightDistance":214.9,"walkingDistance":264.4,"walkingDuration":211.3,"coverageStatus":"between_150_275","routeCacheKey":"route-v1|https://routing.openstreetmap.de/routed-foot|foot|4ea14346-56dc-5da1-8b54-2c76578d5d39|52.723881|4.740313|WH15|52.721977|4.740861","routeGeometry":[[52.723929,4.740162],[52.72382,4.740067],[52.723714,4.740079],[52.723647,4.740155],[52.722918,4.740268],[52.7229,4.74033],[52.722895,4.740918],[52.722609,4.74093],[52.722011,4.7408],[52.722005,4.740867]],"routeError":null},{"id":"WH08","address":"Dorpsstraat 89","accuracy":"hvc import (exacte locatie)","type":"rest","status":"existing","straightDistance":192.4,"walkingDistance":304.3,"walkingDuration":243.5,"coverageStatus":"over_275","routeCacheKey":"route-v1|https://routing.openstreetmap.de/routed-foot|foot|4ea14346-56dc-5da1-8b54-2c76578d5d39|52.723881|4.740313|WH08|52.725435|4.739056","routeGeometry":[[52.723929,4.740162],[52.724278,4.740465],[52.724435,4.739825],[52.724401,4.739644],[52.724244,4.739496],[52.724305,4.739077],[52.724652,4.739147],[52.724973,4.738973],[52.725121,4.738987],[52.725206,4.738813],[52.725314,4.73881],[52.725362,4.738875],[52.725491,4.738939],[52.725478,4.739068]],"routeError":null}],"straightDistance":169.6,"walkingDistance":214.1,"walkingDuration":171.3,"coverageStatus":"between_150_275","analysisError":null},{"id":"36f3659b-35c6-5b6b-a4d4-05103202ec32","address":"Kiebos 6","postcode":"1749HB","city":"Warmenhuizen","lat":52.72395718242492,"lon":4.7400401257667895,"nearestContainerId":"WH14","nearestContainerAddress":"Doorbraak 23","nearestContainerAccuracy":"hvc import (exacte locatie)","nearestContainers":[{"id":"WH14","address":"Doorbraak 23","accuracy":"hvc import (exacte locatie)","type":"rest","status":"existing","straightDistance":183.2,"walkingDistance":213.1,"walkingDuration":170.5,"coverageStatus":"between_150_275","routeCacheKey":"route-v1|https://routing.openstreetmap.de/routed-foot|foot|36f3659b-35c6-5b6b-a4d4-05103202ec32|52.723957|4.740040|WH14|52.722411|4.740981","routeGeometry":[[52.723921,4.740154],[52.72382,4.740067],[52.723714,4.740079],[52.723647,4.740155],[52.722918,4.740268],[52.7229,4.74033],[52.722895,4.740918],[52.722609,4.74093],[52.722418,4.74089]],"routeError":null},{"id":"WH15","address":"Doorbraak 14","accuracy":"handmatig bepaald (zeer hoog, onzekerheid -1 m)","type":"rest","status":"new","straightDistance":227,"walkingDistance":263.3,"walkingDuration":210.5,"coverageStatus":"between_150_275","routeCacheKey":"route-v1|https://routing.openstreetmap.de/routed-foot|foot|36f3659b-35c6-5b6b-a4d4-05103202ec32|52.723957|4.740040|WH15|52.721977|4.740861","routeGeometry":[[52.723921,4.740154],[52.72382,4.740067],[52.723714,4.740079],[52.723647,4.740155],[52.722918,4.740268],[52.7229,4.74033],[52.722895,4.740918],[52.722609,4.74093],[52.722011,4.7408],[52.722005,4.740867]],"routeError":null},{"id":"WH08","address":"Dorpsstraat 89","accuracy":"hvc import (exacte locatie)","type":"rest","status":"existing","straightDistance":177.2,"walkingDistance":305.3,"walkingDuration":244.3,"coverageStatus":"over_275","routeCacheKey":"route-v1|https://routing.openstreetmap.de/routed-foot|foot|36f3659b-35c6-5b6b-a4d4-05103202ec32|52.723957|4.740040|WH08|52.725435|4.739056","routeGeometry":[[52.723921,4.740154],[52.724278,4.740465],[52.724435,4.739825],[52.724401,4.739644],[52.724244,4.739496],[52.724305,4.739077],[52.724652,4.739147],[52.724973,4.738973],[52.725121,4.738987],[52.725206,4.738813],[52.725314,4.73881],[52.725362,4.738875],[52.725491,4.738939],[52.725478,4.739068]],"routeError":null}],"straightDistance":183.2,"walkingDistance":213.1,"walkingDuration":170.5,"coverageStatus":"between_150_275","analysisError":null},{"id":"a7ff3002-c3b3-519f-859d-b5663cee99b4","address":"Kiebos 7","postcode":"1749HA","city":"Warmenhuizen","lat":52.72383945843695,"lon":4.740276236081959,"nearestContainerId":"WH14","nearestContainerAddress":"Doorbraak 23","nearestContainerAccuracy":"hvc import (exacte locatie)","nearestContainers":[{"id":"WH14","address":"Doorbraak 23","accuracy":"hvc import (exacte locatie)","type":"rest","status":"existing","straightDistance":165.8,"walkingDistance":208.8,"walkingDuration":167.1,"coverageStatus":"between_150_275","routeCacheKey":"route-v1|https://routing.openstreetmap.de/routed-foot|foot|a7ff3002-c3b3-519f-859d-b5663cee99b4|52.723839|4.740276|WH14|52.722411|4.740981","routeGeometry":[[52.723887,4.740125],[52.72382,4.740067],[52.723714,4.740079],[52.723647,4.740155],[52.722918,4.740268],[52.7229,4.74033],[52.722895,4.740918],[52.722609,4.74093],[52.722418,4.74089]],"routeError":null},{"id":"WH15","address":"Doorbraak 14","accuracy":"handmatig bepaald (zeer hoog, onzekerheid -1 m)","type":"rest","status":"new","straightDistance":210.8,"walkingDistance":259.1,"walkingDuration":207.1,"coverageStatus":"between_150_275","routeCacheKey":"route-v1|https://routing.openstreetmap.de/routed-foot|foot|a7ff3002-c3b3-519f-859d-b5663cee99b4|52.723839|4.740276|WH15|52.721977|4.740861","routeGeometry":[[52.723887,4.740125],[52.72382,4.740067],[52.723714,4.740079],[52.723647,4.740155],[52.722918,4.740268],[52.7229,4.74033],[52.722895,4.740918],[52.722609,4.74093],[52.722011,4.7408],[52.722005,4.740867]],"routeError":null},{"id":"WH08","address":"Dorpsstraat 89","accuracy":"hvc import (exacte locatie)","type":"rest","status":"existing","straightDistance":195.5,"walkingDistance":309.6,"walkingDuration":247.7,"coverageStatus":"over_275","routeCacheKey":"route-v1|https://routing.openstreetmap.de/routed-foot|foot|a7ff3002-c3b3-519f-859d-b5663cee99b4|52.723839|4.740276|WH08|52.725435|4.739056","routeGeometry":[[52.723887,4.740125],[52.724278,4.740465],[52.724435,4.739825],[52.724401,4.739644],[52.724244,4.739496],[52.724305,4.739077],[52.724652,4.739147],[52.724973,4.738973],[52.725121,4.738987],[52.725206,4.738813],[52.725314,4.73881],[52.725362,4.738875],[52.725491,4.738939],[52.725478,4.739068]],"routeError":null}],"straightDistance":165.8,"walkingDistance":208.8,"walkingDuration":167.1,"coverageStatus":"between_150_275","analysisError":null},{"id":"24232f23-abf8-5de7-a5d8-376387c77771","address":"Kiebos 8","postcode":"1749HB","city":"Warmenhuizen","lat":52.723852033879375,"lon":4.739939349967942,"nearestContainerId":"WH14","nearestContainerAddress":"Doorbraak 23","nearestContainerAccuracy":"hvc import (exacte locatie)","nearestContainers":[{"id":"WH14","address":"Doorbraak 23","accuracy":"hvc import (exacte locatie)","type":"rest","status":"existing","straightDistance":174.9,"walkingDistance":200.4,"walkingDuration":160.4,"coverageStatus":"between_150_275","routeCacheKey":"route-v1|https://routing.openstreetmap.de/routed-foot|foot|24232f23-abf8-5de7-a5d8-376387c77771|52.723852|4.739939|WH14|52.722411|4.740981","routeGeometry":[[52.72382,4.740067],[52.723714,4.740079],[52.723647,4.740155],[52.722918,4.740268],[52.7229,4.74033],[52.722895,4.740918],[52.722609,4.74093],[52.722418,4.74089]],"routeError":null},{"id":"WH15","address":"Doorbraak 14","accuracy":"handmatig bepaald (zeer hoog, onzekerheid -1 m)","type":"rest","status":"new","straightDistance":217.5,"walkingDistance":250.6,"walkingDuration":200.4,"coverageStatus":"between_150_275","routeCacheKey":"route-v1|https://routing.openstreetmap.de/routed-foot|foot|24232f23-abf8-5de7-a5d8-376387c77771|52.723852|4.739939|WH15|52.721977|4.740861","routeGeometry":[[52.72382,4.740067],[52.723714,4.740079],[52.723647,4.740155],[52.722918,4.740268],[52.7229,4.74033],[52.722895,4.740918],[52.722609,4.74093],[52.722011,4.7408],[52.722005,4.740867]],"routeError":null},{"id":"WH08","address":"Dorpsstraat 89","accuracy":"hvc import (exacte locatie)","type":"rest","status":"existing","straightDistance":185.8,"walkingDistance":318,"walkingDuration":254.4,"coverageStatus":"over_275","routeCacheKey":"route-v1|https://routing.openstreetmap.de/routed-foot|foot|24232f23-abf8-5de7-a5d8-376387c77771|52.723852|4.739939|WH08|52.725435|4.739056","routeGeometry":[[52.72382,4.740067],[52.724278,4.740465],[52.724435,4.739825],[52.724401,4.739644],[52.724244,4.739496],[52.724305,4.739077],[52.724652,4.739147],[52.724973,4.738973],[52.725121,4.738987],[52.725206,4.738813],[52.725314,4.73881],[52.725362,4.738875],[52.725491,4.738939],[52.725478,4.739068]],"routeError":null}],"straightDistance":174.9,"walkingDistance":200.4,"walkingDuration":160.4,"coverageStatus":"between_150_275","analysisError":null},{"id":"ad754a6e-976f-5bbf-9ca8-45c7983622d7","address":"Kiebos 9","postcode":"1749HA","city":"Warmenhuizen","lat":52.723199746763726,"lon":4.740414928313261,"nearestContainerId":"WH14","nearestContainerAddress":"Doorbraak 23","nearestContainerAccuracy":"hvc import (exacte locatie)","nearestContainers":[{"id":"WH14","address":"Doorbraak 23","accuracy":"hvc import (exacte locatie)","type":"rest","status":"existing","straightDistance":95.6,"walkingDistance":128.2,"walkingDuration":102.8,"coverageStatus":"between_125_150","routeCacheKey":"route-v1|https://routing.openstreetmap.de/routed-foot|foot|ad754a6e-976f-5bbf-9ca8-45c7983622d7|52.723200|4.740415|WH14|52.722411|4.740981","routeGeometry":[[52.723188,4.74022],[52.722902,4.740294],[52.722895,4.740918],[52.722609,4.74093],[52.722418,4.74089]],"routeError":null},{"id":"WH15","address":"Doorbraak 14","accuracy":"handmatig bepaald (zeer hoog, onzekerheid -1 m)","type":"rest","status":"new","straightDistance":139.2,"walkingDistance":178.5,"walkingDuration":142.8,"coverageStatus":"between_150_275","routeCacheKey":"route-v1|https://routing.openstreetmap.de/routed-foot|foot|ad754a6e-976f-5bbf-9ca8-45c7983622d7|52.723200|4.740415|WH15|52.721977|4.740861","routeGeometry":[[52.723188,4.74022],[52.722902,4.740294],[52.722895,4.740918],[52.722609,4.74093],[52.722011,4.7408],[52.722005,4.740867]],"routeError":null},{"id":"WH11","address":"Wiekeland 2","accuracy":"handmatig bepaald (zeer hoog, onzekerheid -1 m)","type":"rest","status":"new","straightDistance":239.2,"walkingDistance":332,"walkingDuration":265.7,"coverageStatus":"over_275","routeCacheKey":"route-v1|https://routing.openstreetmap.de/routed-foot|foot|ad754a6e-976f-5bbf-9ca8-45c7983622d7|52.723200|4.740415|WH11|52.723809|4.743822","routeGeometry":[[52.723188,4.74022],[52.723477,4.740164],[52.723502,4.741092],[52.723858,4.741085],[52.723893,4.743033],[52.723863,4.743902],[52.723803,4.743887]],"routeError":null}],"straightDistance":95.6,"walkingDistance":128.2,"walkingDuration":102.8,"coverageStatus":"between_125_150","analysisError":null},{"id":"f0c0bee3-1f16-588c-bc36-3d9304174c63","address":"Kiebos 10","postcode":"1749HB","city":"Warmenhuizen","lat":52.723694731886084,"lon":4.739891239422249,"nearestContainerId":"WH14","nearestContainerAddress":"Doorbraak 23","nearestContainerAccuracy":"hvc import (exacte locatie)","nearestContainers":[{"id":"WH14","address":"Doorbraak 23","accuracy":"hvc import (exacte locatie)","type":"rest","status":"existing","straightDistance":160.5,"walkingDistance":188.5,"walkingDuration":150.9,"coverageStatus":"between_150_275","routeCacheKey":"route-v1|https://routing.openstreetmap.de/routed-foot|foot|f0c0bee3-1f16-588c-bc36-3d9304174c63|52.723695|4.739891|WH14|52.722411|4.740981","routeGeometry":[[52.723714,4.740079],[52.723647,4.740155],[52.722918,4.740268],[52.7229,4.74033],[52.722895,4.740918],[52.722609,4.74093],[52.722418,4.74089]],"routeError":null},{"id":"WH15","address":"Doorbraak 14","accuracy":"handmatig bepaald (zeer hoog, onzekerheid -1 m)","type":"rest","status":"new","straightDistance":201.9,"walkingDistance":238.8,"walkingDuration":190.9,"coverageStatus":"between_150_275","routeCacheKey":"route-v1|https://routing.openstreetmap.de/routed-foot|foot|f0c0bee3-1f16-588c-bc36-3d9304174c63|52.723695|4.739891|WH15|52.721977|4.740861","routeGeometry":[[52.723714,4.740079],[52.723647,4.740155],[52.722918,4.740268],[52.7229,4.74033],[52.722895,4.740918],[52.722609,4.74093],[52.722011,4.7408],[52.722005,4.740867]],"routeError":null},{"id":"WH11","address":"Wiekeland 2","accuracy":"handmatig bepaald (zeer hoog, onzekerheid -1 m)","type":"rest","status":"new","straightDistance":265,"walkingDistance":327.1,"walkingDuration":261.8,"coverageStatus":"over_275","routeCacheKey":"route-v1|https://routing.openstreetmap.de/routed-foot|foot|f0c0bee3-1f16-588c-bc36-3d9304174c63|52.723695|4.739891|WH11|52.723809|4.743822","routeGeometry":[[52.723714,4.740079],[52.723742,4.740486],[52.724179,4.740837],[52.724117,4.741075],[52.72414,4.741983],[52.723872,4.742005],[52.723893,4.743033],[52.723863,4.743902],[52.723803,4.743887]],"routeError":null}],"straightDistance":160.5,"walkingDistance":188.5,"walkingDuration":150.9,"coverageStatus":"between_150_275","analysisError":null},{"id":"658f50fe-946f-5c0e-8da3-d99c1cba1890","address":"Kiebos 11","postcode":"1749HA","city":"Warmenhuizen","lat":52.723116214452574,"lon":4.740420392484728,"nearestContainerId":"WH14","nearestContainerAddress":"Doorbraak 23","nearestContainerAccuracy":"hvc import (exacte locatie)","nearestContainers":[{"id":"WH14","address":"Doorbraak 23","accuracy":"hvc import (exacte locatie)","type":"rest","status":"existing","straightDistance":87,"walkingDistance":118.9,"walkingDuration":95.3,"coverageStatus":"between_100_125","routeCacheKey":"route-v1|https://routing.openstreetmap.de/routed-foot|foot|658f50fe-946f-5c0e-8da3-d99c1cba1890|52.723116|4.740420|WH14|52.722411|4.740981","routeGeometry":[[52.723105,4.740234],[52.722902,4.740294],[52.722895,4.740918],[52.722609,4.74093],[52.722418,4.74089]],"routeError":null},{"id":"WH15","address":"Doorbraak 14","accuracy":"handmatig bepaald (zeer hoog, onzekerheid -1 m)","type":"rest","status":"new","straightDistance":130.1,"walkingDistance":169.2,"walkingDuration":135.3,"coverageStatus":"between_150_275","routeCacheKey":"route-v1|https://routing.openstreetmap.de/routed-foot|foot|658f50fe-946f-5c0e-8da3-d99c1cba1890|52.723116|4.740420|WH15|52.721977|4.740861","routeGeometry":[[52.723105,4.740234],[52.722902,4.740294],[52.722895,4.740918],[52.722609,4.74093],[52.722011,4.7408],[52.722005,4.740867]],"routeError":null},{"id":"WH11","address":"Wiekeland 2","accuracy":"handmatig bepaald (zeer hoog, onzekerheid -1 m)","type":"rest","status":"new","straightDistance":241.7,"walkingDistance":341.3,"walkingDuration":273.2,"coverageStatus":"over_275","routeCacheKey":"route-v1|https://routing.openstreetmap.de/routed-foot|foot|658f50fe-946f-5c0e-8da3-d99c1cba1890|52.723116|4.740420|WH11|52.723809|4.743822","routeGeometry":[[52.723105,4.740234],[52.723477,4.740164],[52.723502,4.741092],[52.723858,4.741085],[52.723893,4.743033],[52.723863,4.743902],[52.723803,4.743887]],"routeError":null}],"straightDistance":87,"walkingDistance":118.9,"walkingDuration":95.3,"coverageStatus":"between_100_125","analysisError":null},{"id":"2566b813-0fb7-55e7-b4be-74ea1ecfa032","address":"Kiebos 13","postcode":"1749HA","city":"Warmenhuizen","lat":52.72304939213239,"lon":4.740424751913036,"nearestContainerId":"WH14","nearestContainerAddress":"Doorbraak 23","nearestContainerAccuracy":"hvc import (exacte locatie)","nearestContainers":[{"id":"WH14","address":"Doorbraak 23","accuracy":"hvc import (exacte locatie)","type":"rest","status":"existing","straightDistance":80.3,"walkingDistance":111.4,"walkingDuration":89.3,"coverageStatus":"between_100_125","routeCacheKey":"route-v1|https://routing.openstreetmap.de/routed-foot|foot|2566b813-0fb7-55e7-b4be-74ea1ecfa032|52.723049|4.740425|WH14|52.722411|4.740981","routeGeometry":[[52.723038,4.740245],[52.722902,4.740294],[52.722895,4.740918],[52.722609,4.74093],[52.722418,4.74089]],"routeError":null},{"id":"WH15","address":"Doorbraak 14","accuracy":"handmatig bepaald (zeer hoog, onzekerheid -1 m)","type":"rest","status":"new","straightDistance":122.8,"walkingDistance":161.7,"walkingDuration":129.3,"coverageStatus":"between_150_275","routeCacheKey":"route-v1|https://routing.openstreetmap.de/routed-foot|foot|2566b813-0fb7-55e7-b4be-74ea1ecfa032|52.723049|4.740425|WH15|52.721977|4.740861","routeGeometry":[[52.723038,4.740245],[52.722902,4.740294],[52.722895,4.740918],[52.722609,4.74093],[52.722011,4.7408],[52.722005,4.740867]],"routeError":null},{"id":"WH11","address":"Wiekeland 2","accuracy":"handmatig bepaald (zeer hoog, onzekerheid -1 m)","type":"rest","status":"new","straightDistance":243.9,"walkingDistance":348.8,"walkingDuration":279.2,"coverageStatus":"over_275","routeCacheKey":"route-v1|https://routing.openstreetmap.de/routed-foot|foot|2566b813-0fb7-55e7-b4be-74ea1ecfa032|52.723049|4.740425|WH11|52.723809|4.743822","routeGeometry":[[52.723038,4.740245],[52.723477,4.740164],[52.723502,4.741092],[52.723858,4.741085],[52.723893,4.743033],[52.723863,4.743902],[52.723803,4.743887]],"routeError":null}],"straightDistance":80.3,"walkingDistance":111.4,"walkingDuration":89.3,"coverageStatus":"between_100_125","analysisError":null},{"id":"4f066dfb-1ec2-5c5f-8b5e-2a9007892be1","address":"Kiebos 14","postcode":"1749HB","city":"Warmenhuizen","lat":52.72356773837971,"lon":4.739987696329094,"nearestContainerId":"WH14","nearestContainerAddress":"Doorbraak 23","nearestContainerAccuracy":"hvc import (exacte locatie)","nearestContainers":[{"id":"WH14","address":"Doorbraak 23","accuracy":"hvc import (exacte locatie)","type":"rest","status":"existing","straightDistance":145,"walkingDistance":171,"walkingDuration":136.9,"coverageStatus":"between_150_275","routeCacheKey":"route-v1|https://routing.openstreetmap.de/routed-foot|foot|4f066dfb-1ec2-5c5f-8b5e-2a9007892be1|52.723568|4.739988|WH14|52.722411|4.740981","routeGeometry":[[52.723571,4.740159],[52.722918,4.740268],[52.7229,4.74033],[52.722895,4.740918],[52.722609,4.74093],[52.722418,4.74089]],"routeError":null},{"id":"WH15","address":"Doorbraak 14","accuracy":"handmatig bepaald (zeer hoog, onzekerheid -1 m)","type":"rest","status":"new","straightDistance":186.4,"walkingDistance":221.3,"walkingDuration":176.9,"coverageStatus":"between_150_275","routeCacheKey":"route-v1|https://routing.openstreetmap.de/routed-foot|foot|4f066dfb-1ec2-5c5f-8b5e-2a9007892be1|52.723568|4.739988|WH15|52.721977|4.740861","routeGeometry":[[52.723571,4.740159],[52.722918,4.740268],[52.7229,4.74033],[52.722895,4.740918],[52.722609,4.74093],[52.722011,4.7408],[52.722005,4.740867]],"routeError":null},{"id":"WH11","address":"Wiekeland 2","accuracy":"handmatig bepaald (zeer hoog, onzekerheid -1 m)","type":"rest","status":"new","straightDistance":259.6,"walkingDistance":310.1,"walkingDuration":248.2,"coverageStatus":"over_275","routeCacheKey":"route-v1|https://routing.openstreetmap.de/routed-foot|foot|4f066dfb-1ec2-5c5f-8b5e-2a9007892be1|52.723568|4.739988|WH11|52.723809|4.743822","routeGeometry":[[52.723571,4.740159],[52.723477,4.740164],[52.723502,4.741092],[52.723858,4.741085],[52.723893,4.743033],[52.723863,4.743902],[52.723803,4.743887]],"routeError":null}],"straightDistance":145,"walkingDistance":171,"walkingDuration":136.9,"coverageStatus":"between_150_275","analysisError":null},{"id":"f35ae1f6-1075-55b8-b5be-1df17aa9a287","address":"Kiebos 15","postcode":"1749HA","city":"Warmenhuizen","lat":52.72295813354539,"lon":4.740430699933698,"nearestContainerId":"WH14","nearestContainerAddress":"Doorbraak 23","nearestContainerAccuracy":"hvc import (exacte locatie)","nearestContainers":[{"id":"WH14","address":"Doorbraak 23","accuracy":"hvc import (exacte locatie)","type":"rest","status":"existing","straightDistance":71.2,"walkingDistance":86.1,"walkingDuration":69,"coverageStatus":"within_100","routeCacheKey":"route-v1|https://routing.openstreetmap.de/routed-foot|foot|f35ae1f6-1075-55b8-b5be-1df17aa9a287|52.722958|4.740431|WH14|52.722411|4.740981","routeGeometry":[[52.722901,4.740433],[52.722895,4.740918],[52.722609,4.74093],[52.722418,4.74089]],"routeError":null},{"id":"WH15","address":"Doorbraak 14","accuracy":"handmatig bepaald (zeer hoog, onzekerheid -1 m)","type":"rest","status":"new","straightDistance":112.9,"walkingDistance":136.3,"walkingDuration":109,"coverageStatus":"between_125_150","routeCacheKey":"route-v1|https://routing.openstreetmap.de/routed-foot|foot|f35ae1f6-1075-55b8-b5be-1df17aa9a287|52.722958|4.740431|WH15|52.721977|4.740861","routeGeometry":[[52.722901,4.740433],[52.722895,4.740918],[52.722609,4.74093],[52.722011,4.7408],[52.722005,4.740867]],"routeError":null},{"id":"WH11","address":"Wiekeland 2","accuracy":"handmatig bepaald (zeer hoog, onzekerheid -1 m)","type":"rest","status":"new","straightDistance":247.2,"walkingDistance":328.3,"walkingDuration":262.5,"coverageStatus":"over_275","routeCacheKey":"route-v1|https://routing.openstreetmap.de/routed-foot|foot|f35ae1f6-1075-55b8-b5be-1df17aa9a287|52.722958|4.740431|WH11|52.723809|4.743822","routeGeometry":[[52.722901,4.740433],[52.7229,4.741077],[52.723151,4.741112],[52.723159,4.741425],[52.723117,4.741617],[52.723118,4.741775],[52.723151,4.741946],[52.723173,4.742963],[52.723128,4.743718],[52.723803,4.743887]],"routeError":null}],"straightDistance":71.2,"walkingDistance":86.1,"walkingDuration":69,"coverageStatus":"within_100","analysisError":null},{"id":"0bc57d4c-1962-5aea-ae57-23e5065ab4f4","address":"Kiebos 16","postcode":"1749HB","city":"Warmenhuizen","lat":52.72340007816858,"lon":4.739978327042005,"nearestContainerId":"WH14","nearestContainerAddress":"Doorbraak 23","nearestContainerAccuracy":"hvc import (exacte locatie)","nearestContainers":[{"id":"WH14","address":"Doorbraak 23","accuracy":"hvc import (exacte locatie)","type":"rest","status":"existing","straightDistance":129.1,"walkingDistance":155,"walkingDuration":124.1,"coverageStatus":"between_150_275","routeCacheKey":"route-v1|https://routing.openstreetmap.de/routed-foot|foot|0bc57d4c-1962-5aea-ae57-23e5065ab4f4|52.723400|4.739978|WH14|52.722411|4.740981","routeGeometry":[[52.723292,4.739982],[52.723295,4.740202],[52.722902,4.740294],[52.722895,4.740918],[52.722609,4.74093],[52.722418,4.74089]],"routeError":null},{"id":"WH15","address":"Doorbraak 14","accuracy":"handmatig bepaald (zeer hoog, onzekerheid -1 m)","type":"rest","status":"new","straightDistance":169,"walkingDistance":205.3,"walkingDuration":164.1,"coverageStatus":"between_150_275","routeCacheKey":"route-v1|https://routing.openstreetmap.de/routed-foot|foot|0bc57d4c-1962-5aea-ae57-23e5065ab4f4|52.723400|4.739978|WH15|52.721977|4.740861","routeGeometry":[[52.723292,4.739982],[52.723295,4.740202],[52.722902,4.740294],[52.722895,4.740918],[52.722609,4.74093],[52.722011,4.7408],[52.722005,4.740867]],"routeError":null},{"id":"WH11","address":"Wiekeland 2","accuracy":"handmatig bepaald (zeer hoog, onzekerheid -1 m)","type":"rest","status":"new","straightDistance":262.8,"walkingDistance":334.9,"walkingDuration":268,"coverageStatus":"over_275","routeCacheKey":"route-v1|https://routing.openstreetmap.de/routed-foot|foot|0bc57d4c-1962-5aea-ae57-23e5065ab4f4|52.723400|4.739978|WH11|52.723809|4.743822","routeGeometry":[[52.723292,4.739982],[52.723295,4.740202],[52.723477,4.740164],[52.723502,4.741092],[52.723858,4.741085],[52.723893,4.743033],[52.723863,4.743902],[52.723803,4.743887]],"routeError":null}],"straightDistance":129.1,"walkingDistance":155,"walkingDuration":124.1,"coverageStatus":"between_150_275","analysisError":null},{"id":"4463603f-40cd-5fd7-998b-e5590cc5a171","address":"Kiebos 18","postcode":"1749HB","city":"Warmenhuizen","lat":52.72338267357873,"lon":4.739478193088574,"nearestContainerId":"WH14","nearestContainerAddress":"Doorbraak 23","nearestContainerAccuracy":"hvc import (exacte locatie)","nearestContainers":[{"id":"WH14","address":"Doorbraak 23","accuracy":"hvc import (exacte locatie)","type":"rest","status":"existing","straightDistance":148,"walkingDistance":185,"walkingDuration":148.1,"coverageStatus":"between_150_275","routeCacheKey":"route-v1|https://routing.openstreetmap.de/routed-foot|foot|4463603f-40cd-5fd7-998b-e5590cc5a171|52.723383|4.739478|WH14|52.722411|4.740981","routeGeometry":[[52.723287,4.739538],[52.723295,4.740202],[52.722902,4.740294],[52.722895,4.740918],[52.722609,4.74093],[52.722418,4.74089]],"routeError":null},{"id":"WH15","address":"Doorbraak 14","accuracy":"handmatig bepaald (zeer hoog, onzekerheid -1 m)","type":"rest","status":"new","straightDistance":181.9,"walkingDistance":235.3,"walkingDuration":188.1,"coverageStatus":"between_150_275","routeCacheKey":"route-v1|https://routing.openstreetmap.de/routed-foot|foot|4463603f-40cd-5fd7-998b-e5590cc5a171|52.723383|4.739478|WH15|52.721977|4.740861","routeGeometry":[[52.723287,4.739538],[52.723295,4.740202],[52.722902,4.740294],[52.722895,4.740918],[52.722609,4.74093],[52.722011,4.7408],[52.722005,4.740867]],"routeError":null},{"id":"WH13","address":"Alingterp 2","accuracy":"handmatig bepaald (zeer hoog, onzekerheid -1 m)","type":"rest","status":"new","straightDistance":283.7,"walkingDistance":349.2,"walkingDuration":279.3,"coverageStatus":"over_275","routeCacheKey":"route-v1|https://routing.openstreetmap.de/routed-foot|foot|4463603f-40cd-5fd7-998b-e5590cc5a171|52.723383|4.739478|WH13|52.723362|4.735266","routeGeometry":[[52.723287,4.739538],[52.723245,4.739553],[52.723229,4.739048],[52.723126,4.739002],[52.723215,4.738508],[52.72312,4.73845],[52.722923,4.738108],[52.722973,4.738045],[52.723182,4.737942],[52.723199,4.737872],[52.72324,4.73581],[52.723336,4.735225],[52.723363,4.735228]],"routeError":null}],"straightDistance":148,"walkingDistance":185,"walkingDuration":148.1,"coverageStatus":"between_150_275","analysisError":null},{"id":"443e849e-cf4e-5bb7-90c7-16646c1f5301","address":"Kiebos 20","postcode":"1749HB","city":"Warmenhuizen","lat":52.72340861206325,"lon":4.739265433562561,"nearestContainerId":"WH14","nearestContainerAddress":"Doorbraak 23","nearestContainerAccuracy":"hvc import (exacte locatie)","nearestContainers":[{"id":"WH14","address":"Doorbraak 23","accuracy":"hvc import (exacte locatie)","type":"rest","status":"existing","straightDistance":160.2,"walkingDistance":207.4,"walkingDuration":166,"coverageStatus":"between_150_275","routeCacheKey":"route-v1|https://routing.openstreetmap.de/routed-foot|foot|443e849e-cf4e-5bb7-90c7-16646c1f5301|52.723409|4.739265|WH14|52.722411|4.740981","routeGeometry":[[52.723236,4.739279],[52.723245,4.739553],[52.723287,4.73955],[52.723295,4.740202],[52.722902,4.740294],[52.722895,4.740918],[52.722609,4.74093],[52.722418,4.74089]],"routeError":null},{"id":"WH15","address":"Doorbraak 14","accuracy":"handmatig bepaald (zeer hoog, onzekerheid -1 m)","type":"rest","status":"new","straightDistance":192.1,"walkingDistance":257.7,"walkingDuration":206,"coverageStatus":"between_150_275","routeCacheKey":"route-v1|https://routing.openstreetmap.de/routed-foot|foot|443e849e-cf4e-5bb7-90c7-16646c1f5301|52.723409|4.739265|WH15|52.721977|4.740861","routeGeometry":[[52.723236,4.739279],[52.723245,4.739553],[52.723287,4.73955],[52.723295,4.740202],[52.722902,4.740294],[52.722895,4.740918],[52.722609,4.74093],[52.722011,4.7408],[52.722005,4.740867]],"routeError":null},{"id":"WH13","address":"Alingterp 2","accuracy":"handmatig bepaald (zeer hoog, onzekerheid -1 m)","type":"rest","status":"new","straightDistance":269.4,"walkingDistance":325.2,"walkingDuration":260.2,"coverageStatus":"over_275","routeCacheKey":"route-v1|https://routing.openstreetmap.de/routed-foot|foot|443e849e-cf4e-5bb7-90c7-16646c1f5301|52.723409|4.739265|WH13|52.723362|4.735266","routeGeometry":[[52.723236,4.739279],[52.723229,4.739048],[52.723126,4.739002],[52.723215,4.738508],[52.72312,4.73845],[52.722923,4.738108],[52.722973,4.738045],[52.723182,4.737942],[52.723199,4.737872],[52.72324,4.73581],[52.723336,4.735225],[52.723363,4.735228]],"routeError":null}],"straightDistance":160.2,"walkingDistance":207.4,"walkingDuration":166,"coverageStatus":"between_150_275","analysisError":null},{"id":"2033089c-5e55-5eb1-8bc9-edd68e273b4b","address":"Kiebos 24","postcode":"1749HB","city":"Warmenhuizen","lat":52.723236289275086,"lon":4.739971875896391,"nearestContainerId":"WH14","nearestContainerAddress":"Doorbraak 23","nearestContainerAccuracy":"hvc import (exacte locatie)","nearestContainers":[{"id":"WH14","address":"Doorbraak 23","accuracy":"hvc import (exacte locatie)","type":"rest","status":"existing","straightDistance":114.2,"walkingDistance":155.8,"walkingDuration":124.8,"coverageStatus":"between_150_275","routeCacheKey":"route-v1|https://routing.openstreetmap.de/routed-foot|foot|2033089c-5e55-5eb1-8bc9-edd68e273b4b|52.723236|4.739972|WH14|52.722411|4.740981","routeGeometry":[[52.723292,4.73997],[52.723295,4.740202],[52.722902,4.740294],[52.722895,4.740918],[52.722609,4.74093],[52.722418,4.74089]],"routeError":null},{"id":"WH15","address":"Doorbraak 14","accuracy":"handmatig bepaald (zeer hoog, onzekerheid -1 m)","type":"rest","status":"new","straightDistance":152.3,"walkingDistance":206.1,"walkingDuration":164.8,"coverageStatus":"between_150_275","routeCacheKey":"route-v1|https://routing.openstreetmap.de/routed-foot|foot|2033089c-5e55-5eb1-8bc9-edd68e273b4b|52.723236|4.739972|WH15|52.721977|4.740861","routeGeometry":[[52.723292,4.73997],[52.723295,4.740202],[52.722902,4.740294],[52.722895,4.740918],[52.722609,4.74093],[52.722011,4.7408],[52.722005,4.740867]],"routeError":null},{"id":"WH11","address":"Wiekeland 2","accuracy":"handmatig bepaald (zeer hoog, onzekerheid -1 m)","type":"rest","status":"new","straightDistance":267,"walkingDistance":335.7,"walkingDuration":268.7,"coverageStatus":"over_275","routeCacheKey":"route-v1|https://routing.openstreetmap.de/routed-foot|foot|2033089c-5e55-5eb1-8bc9-edd68e273b4b|52.723236|4.739972|WH11|52.723809|4.743822","routeGeometry":[[52.723292,4.73997],[52.723295,4.740202],[52.723477,4.740164],[52.723502,4.741092],[52.723858,4.741085],[52.723893,4.743033],[52.723863,4.743902],[52.723803,4.743887]],"routeError":null}],"straightDistance":114.2,"walkingDistance":155.8,"walkingDuration":124.8,"coverageStatus":"between_150_275","analysisError":null},{"id":"ed703956-61fd-5ec1-a611-186daf74c794","address":"Kiebos 26","postcode":"1749HB","city":"Warmenhuizen","lat":52.72316271246427,"lon":4.739978585484274,"nearestContainerId":"WH14","nearestContainerAddress":"Doorbraak 23","nearestContainerAccuracy":"hvc import (exacte locatie)","nearestContainers":[{"id":"WH14","address":"Doorbraak 23","accuracy":"hvc import (exacte locatie)","type":"rest","status":"existing","straightDistance":107.4,"walkingDistance":155.5,"walkingDuration":124.5,"coverageStatus":"between_150_275","routeCacheKey":"route-v1|https://routing.openstreetmap.de/routed-foot|foot|ed703956-61fd-5ec1-a611-186daf74c794|52.723163|4.739979|WH14|52.722411|4.740981","routeGeometry":[[52.723292,4.739975],[52.723295,4.740202],[52.722902,4.740294],[52.722895,4.740918],[52.722609,4.74093],[52.722418,4.74089]],"routeError":null},{"id":"WH15","address":"Doorbraak 14","accuracy":"handmatig bepaald (zeer hoog, onzekerheid -1 m)","type":"rest","status":"new","straightDistance":144.6,"walkingDistance":205.8,"walkingDuration":164.5,"coverageStatus":"between_150_275","routeCacheKey":"route-v1|https://routing.openstreetmap.de/routed-foot|foot|ed703956-61fd-5ec1-a611-186daf74c794|52.723163|4.739979|WH15|52.721977|4.740861","routeGeometry":[[52.723292,4.739975],[52.723295,4.740202],[52.722902,4.740294],[52.722895,4.740918],[52.722609,4.74093],[52.722011,4.7408],[52.722005,4.740867]],"routeError":null},{"id":"WH11","address":"Wiekeland 2","accuracy":"handmatig bepaald (zeer hoog, onzekerheid -1 m)","type":"rest","status":"new","straightDistance":268.6,"walkingDistance":335.4,"walkingDuration":268.4,"coverageStatus":"over_275","routeCacheKey":"route-v1|https://routing.openstreetmap.de/routed-foot|foot|ed703956-61fd-5ec1-a611-186daf74c794|52.723163|4.739979|WH11|52.723809|4.743822","routeGeometry":[[52.723292,4.739975],[52.723295,4.740202],[52.723477,4.740164],[52.723502,4.741092],[52.723858,4.741085],[52.723893,4.743033],[52.723863,4.743902],[52.723803,4.743887]],"routeError":null}],"straightDistance":107.4,"walkingDistance":155.5,"walkingDuration":124.5,"coverageStatus":"between_150_275","analysisError":null},{"id":"5add0f67-cf89-511f-8bef-884f6dc080dc","address":"Kiebos 28","postcode":"1749HB","city":"Warmenhuizen","lat":52.72310181058202,"lon":4.739994137213071,"nearestContainerId":"WH14","nearestContainerAddress":"Doorbraak 23","nearestContainerAccuracy":"hvc import (exacte locatie)","nearestContainers":[{"id":"WH14","address":"Doorbraak 23","accuracy":"hvc import (exacte locatie)","type":"rest","status":"existing","straightDistance":101.6,"walkingDistance":120.2,"walkingDuration":96.4,"coverageStatus":"between_100_125","routeCacheKey":"route-v1|https://routing.openstreetmap.de/routed-foot|foot|5add0f67-cf89-511f-8bef-884f6dc080dc|52.723102|4.739994|WH14|52.722411|4.740981","routeGeometry":[[52.723117,4.740232],[52.722902,4.740294],[52.722895,4.740918],[52.722609,4.74093],[52.722418,4.74089]],"routeError":null},{"id":"WH15","address":"Doorbraak 14","accuracy":"handmatig bepaald (zeer hoog, onzekerheid -1 m)","type":"rest","status":"new","straightDistance":138,"walkingDistance":170.5,"walkingDuration":136.4,"coverageStatus":"between_150_275","routeCacheKey":"route-v1|https://routing.openstreetmap.de/routed-foot|foot|5add0f67-cf89-511f-8bef-884f6dc080dc|52.723102|4.739994|WH15|52.721977|4.740861","routeGeometry":[[52.723117,4.740232],[52.722902,4.740294],[52.722895,4.740918],[52.722609,4.74093],[52.722011,4.7408],[52.722005,4.740867]],"routeError":null},{"id":"WH11","address":"Wiekeland 2","accuracy":"handmatig bepaald (zeer hoog, onzekerheid -1 m)","type":"rest","status":"new","straightDistance":269.5,"walkingDistance":339.9,"walkingDuration":272.1,"coverageStatus":"over_275","routeCacheKey":"route-v1|https://routing.openstreetmap.de/routed-foot|foot|5add0f67-cf89-511f-8bef-884f6dc080dc|52.723102|4.739994|WH11|52.723809|4.743822","routeGeometry":[[52.723117,4.740232],[52.723477,4.740164],[52.723502,4.741092],[52.723858,4.741085],[52.723893,4.743033],[52.723863,4.743902],[52.723803,4.743887]],"routeError":null}],"straightDistance":101.6,"walkingDistance":120.2,"walkingDuration":96.4,"coverageStatus":"between_100_125","analysisError":null},{"id":"8a31a723-ef5f-575f-b7d8-291d4805c00e","address":"Kiebos 30","postcode":"1749HB","city":"Warmenhuizen","lat":52.72301547538213,"lon":4.740024599172761,"nearestContainerId":"WH14","nearestContainerAddress":"Doorbraak 23","nearestContainerAccuracy":"hvc import (exacte locatie)","nearestContainers":[{"id":"WH14","address":"Doorbraak 23","accuracy":"hvc import (exacte locatie)","type":"rest","status":"existing","straightDistance":93.1,"walkingDistance":110.4,"walkingDuration":88.5,"coverageStatus":"between_100_125","routeCacheKey":"route-v1|https://routing.openstreetmap.de/routed-foot|foot|8a31a723-ef5f-575f-b7d8-291d4805c00e|52.723015|4.740025|WH14|52.722411|4.740981","routeGeometry":[[52.723029,4.740247],[52.722902,4.740294],[52.722895,4.740918],[52.722609,4.74093],[52.722418,4.74089]],"routeError":null},{"id":"WH15","address":"Doorbraak 14","accuracy":"handmatig bepaald (zeer hoog, onzekerheid -1 m)","type":"rest","status":"new","straightDistance":128.5,"walkingDistance":160.7,"walkingDuration":128.5,"coverageStatus":"between_150_275","routeCacheKey":"route-v1|https://routing.openstreetmap.de/routed-foot|foot|8a31a723-ef5f-575f-b7d8-291d4805c00e|52.723015|4.740025|WH15|52.721977|4.740861","routeGeometry":[[52.723029,4.740247],[52.722902,4.740294],[52.722895,4.740918],[52.722609,4.74093],[52.722011,4.7408],[52.722005,4.740867]],"routeError":null},{"id":"WH11","address":"Wiekeland 2","accuracy":"handmatig bepaald (zeer hoog, onzekerheid -1 m)","type":"rest","status":"new","straightDistance":270.5,"walkingDistance":349.8,"walkingDuration":280,"coverageStatus":"over_275","routeCacheKey":"route-v1|https://routing.openstreetmap.de/routed-foot|foot|8a31a723-ef5f-575f-b7d8-291d4805c00e|52.723015|4.740025|WH11|52.723809|4.743822","routeGeometry":[[52.723029,4.740247],[52.723477,4.740164],[52.723502,4.741092],[52.723858,4.741085],[52.723893,4.743033],[52.723863,4.743902],[52.723803,4.743887]],"routeError":null}],"straightDistance":93.1,"walkingDistance":110.4,"walkingDuration":88.5,"coverageStatus":"between_100_125","analysisError":null},{"id":"1c553fb6-1345-5338-9d33-ee80dfebd4b1","address":"Kiebos 32","postcode":"1749HB","city":"Warmenhuizen","lat":52.72296105427162,"lon":4.740028776349339,"nearestContainerId":"WH14","nearestContainerAddress":"Doorbraak 23","nearestContainerAccuracy":"hvc import (exacte locatie)","nearestContainers":[{"id":"WH14","address":"Doorbraak 23","accuracy":"hvc import (exacte locatie)","type":"rest","status":"existing","straightDistance":88.6,"walkingDistance":104.4,"walkingDuration":83.7,"coverageStatus":"between_100_125","routeCacheKey":"route-v1|https://routing.openstreetmap.de/routed-foot|foot|1c553fb6-1345-5338-9d33-ee80dfebd4b1|52.722961|4.740029|WH14|52.722411|4.740981","routeGeometry":[[52.722975,4.740256],[52.722902,4.740294],[52.722895,4.740918],[52.722609,4.74093],[52.722418,4.74089]],"routeError":null},{"id":"WH15","address":"Doorbraak 14","accuracy":"handmatig bepaald (zeer hoog, onzekerheid -1 m)","type":"rest","status":"new","straightDistance":122.9,"walkingDistance":154.6,"walkingDuration":123.7,"coverageStatus":"between_150_275","routeCacheKey":"route-v1|https://routing.openstreetmap.de/routed-foot|foot|1c553fb6-1345-5338-9d33-ee80dfebd4b1|52.722961|4.740029|WH15|52.721977|4.740861","routeGeometry":[[52.722975,4.740256],[52.722902,4.740294],[52.722895,4.740918],[52.722609,4.74093],[52.722011,4.7408],[52.722005,4.740867]],"routeError":null},{"id":"WH11","address":"Wiekeland 2","accuracy":"handmatig bepaald (zeer hoog, onzekerheid -1 m)","type":"rest","status":"new","straightDistance":272.3,"walkingDistance":346.6,"walkingDuration":277.2,"coverageStatus":"over_275","routeCacheKey":"route-v1|https://routing.openstreetmap.de/routed-foot|foot|1c553fb6-1345-5338-9d33-ee80dfebd4b1|52.722961|4.740029|WH11|52.723809|4.743822","routeGeometry":[[52.722975,4.740256],[52.722902,4.740294],[52.722892,4.741045],[52.722925,4.7411],[52.723151,4.741112],[52.723159,4.741425],[52.723117,4.741617],[52.723118,4.741775],[52.723151,4.741946],[52.723173,4.742963],[52.723128,4.743718],[52.723803,4.743887]],"routeError":null}],"straightDistance":88.6,"walkingDistance":104.4,"walkingDuration":83.7,"coverageStatus":"between_100_125","analysisError":null},{"id":"0e215ea5-ab9d-5317-9a9c-2344b5f8a899","address":"Kiebos 34","postcode":"1749HB","city":"Warmenhuizen","lat":52.72291756885332,"lon":4.740032659065191,"nearestContainerId":"WH14","nearestContainerAddress":"Doorbraak 23","nearestContainerAccuracy":"hvc import (exacte locatie)","nearestContainers":[{"id":"WH14","address":"Doorbraak 23","accuracy":"hvc import (exacte locatie)","type":"rest","status":"existing","straightDistance":85.2,"walkingDistance":99.7,"walkingDuration":79.9,"coverageStatus":"within_100","routeCacheKey":"route-v1|https://routing.openstreetmap.de/routed-foot|foot|0e215ea5-ab9d-5317-9a9c-2344b5f8a899|52.722918|4.740033|WH14|52.722411|4.740981","routeGeometry":[[52.722933,4.740263],[52.722902,4.740294],[52.722895,4.740918],[52.722609,4.74093],[52.722418,4.74089]],"routeError":null},{"id":"WH15","address":"Doorbraak 14","accuracy":"handmatig bepaald (zeer hoog, onzekerheid -1 m)","type":"rest","status":"new","straightDistance":118.5,"walkingDistance":149.9,"walkingDuration":119.9,"coverageStatus":"between_125_150","routeCacheKey":"route-v1|https://routing.openstreetmap.de/routed-foot|foot|0e215ea5-ab9d-5317-9a9c-2344b5f8a899|52.722918|4.740033|WH15|52.721977|4.740861","routeGeometry":[[52.722933,4.740263],[52.722902,4.740294],[52.722895,4.740918],[52.722609,4.74093],[52.722011,4.7408],[52.722005,4.740867]],"routeError":null},{"id":"WH11","address":"Wiekeland 2","accuracy":"handmatig bepaald (zeer hoog, onzekerheid -1 m)","type":"rest","status":"new","straightDistance":273.8,"walkingDistance":341.9,"walkingDuration":273.4,"coverageStatus":"over_275","routeCacheKey":"route-v1|https://routing.openstreetmap.de/routed-foot|foot|0e215ea5-ab9d-5317-9a9c-2344b5f8a899|52.722918|4.740033|WH11|52.723809|4.743822","routeGeometry":[[52.722933,4.740263],[52.722902,4.740294],[52.722892,4.741045],[52.722925,4.7411],[52.723151,4.741112],[52.723159,4.741425],[52.723117,4.741617],[52.723118,4.741775],[52.723151,4.741946],[52.723173,4.742963],[52.723128,4.743718],[52.723803,4.743887]],"routeError":null}],"straightDistance":85.2,"walkingDistance":99.7,"walkingDuration":79.9,"coverageStatus":"within_100","analysisError":null}]}
